Workbook

Sheet RESUMEN PROYECTO
C5: UNIDAD FUNCIONAL / INSTALACIÓN | D5: COSTO DIRECTO | E5: ADMINISTRACIÓN - 22% - | F5: IMPREVISTOS - 4% - | G5: UTILIDAD - 4% - | H5: I.V.A. - 19% - (sobre utilidad) | I5: COSTO TOTAL
C7: UF 0D | D7: =ROUND(UUFF!E17,2) -> 1.6466883e+10 | E7: =ROUND((D7*22%),2) -> 3.6227143e+09 | F7: =ROUND((D7*4%),2) -> 6.5867533e+08 | G7: =ROUND((D7*4%),2) -> 6.5867533e+08 | H7: =ROUND((G7*19%),2) -> 1.2514831e+08 | I7: =SUM(D7:H7) -> 2.1532096e+10
C8: UF 1 | D8: =ROUND(UUFF!G17,2) -> 6.2530024e+08 | E8: =ROUND((D8*22%),2) -> 1.3756605e+08 | F8: =ROUND((D8*4%),2) -> 25012010 | G8: =ROUND((D8*4%),2) -> 25012010 | H8: =ROUND((G8*19%),2) -> 4752281.8 | I8: =SUM(D8:H8) -> 8.176426e+08
C9: UF 2 | D9: =ROUND(UUFF!I17,2) -> 2.233377e+09 | E9: =ROUND((D9*22%),2) -> 4.9134294e+08 | F9: =ROUND((D9*4%),2) -> 89335080 | G9: =ROUND((D9*4%),2) -> 89335080 | H9: =ROUND((G9*19%),2) -> 16973665 | I9: =SUM(D9:H9) -> 2.9203638e+09
C10: UF 3 | D10: =ROUND(UUFF!K17,2) -> 1.396382e+09 | E10: =ROUND((D10*22%),2) -> 3.0720404e+08 | F10: =ROUND((D10*4%),2) -> 55855280 | G10: =ROUND((D10*4%),2) -> 55855280 | H10: =ROUND((G10*19%),2) -> 10612503 | I10: =SUM(D10:H10) -> 1.8259091e+09
C11: UF 4 | D11: =ROUND(UUFF!M17,2) -> 1.2374223e+09 | E11: =ROUND((D11*22%),2) -> 2.722329e+08 | F11: =ROUND((D11*4%),2) -> 49496892 | G11: =ROUND((D11*4%),2) -> 49496892 | H11: =ROUND((G11*19%),2) -> 9404409.4 | I11: =SUM(D11:H11) -> 1.6180534e+09
C12: UF 5 | D12: =ROUND(UUFF!O17,2) -> 5.1123698e+09 | E12: =ROUND((D12*22%),2) -> 1.1247214e+09 | F12: =ROUND((D12*4%),2) -> 2.0449479e+08 | G12: =ROUND((D12*4%),2) -> 2.0449479e+08 | H12: =ROUND((G12*19%),2) -> 38854011 | I12: =SUM(D12:H12) -> 6.6849348e+09
C13: UF 6 | D13: =ROUND(UUFF!R17,2) -> 1.1657859e+09 | E13: =ROUND((D13*22%),2) -> 2.564729e+08 | F13: =ROUND((D13*4%),2) -> 46631436 | G13: =ROUND((D13*4%),2) -> 46631436 | H13: =ROUND((G13*19%),2) -> 8859972.8 | I13: =SUM(D13:H13) -> 1.5243816e+09
C14: UF 7 | D14: =ROUND(UUFF!T17,2) -> 1.5519735e+09 | E14: =ROUND((D14*22%),2) -> 3.4143416e+08 | F14: =ROUND((D14*4%),2) -> 62078938 | G14: =ROUND((D14*4%),2) -> 62078938 | H14: =ROUND((G14*19%),2) -> 11794998 | I14: =SUM(D14:H14) -> 2.0293605e+09
C15: UF 8 | D15: =ROUND(UUFF!V17,2) -> 1.0944928e+09 | E15: =ROUND((D15*22%),2) -> 2.4078842e+08 | F15: =ROUND((D15*4%),2) -> 43779713 | G15: =ROUND((D15*4%),2) -> 43779713 | H15: =ROUND((G15*19%),2) -> 8318145.4 | I15: =SUM(D15:H15) -> 1.4311588e+09
C16: UF 9 | D16: =ROUND(UUFF!X17,2) -> 1.0151298e+09 | E16: =ROUND((D16*22%),2) -> 2.2332856e+08 | F16: =ROUND((D16*4%),2) -> 40605192 | G16: =ROUND((D16*4%),2) -> 40605192 | H16: =ROUND((G16*19%),2) -> 7714986.5 | I16: =SUM(D16:H16) -> 1.3273837e+09
C17: UF 10 | D17: =ROUND(UUFF!Z17,2) -> 1.1911112e+09 | E17: =ROUND((D17*22%),2) -> 2.6204447e+08 | F17: =ROUND((D17*4%),2) -> 47644449 | G17: =ROUND((D17*4%),2) -> 47644449 | H17: =ROUND((G17*19%),2) -> 9052445.4 | I17: =SUM(D17:H17) -> 1.5574971e+09
C18: UF 11 | D18: =ROUND(UUFF!AB17,2) -> 4.0077251e+09 | E18: =ROUND((D18*22%),2) -> 8.8169953e+08 | F18: =ROUND((D18*4%),2) -> 1.60309e+08 | G18: =ROUND((D18*4%),2) -> 1.60309e+08 | H18: =ROUND((G18*19%),2) -> 30458711 | I18: =SUM(D18:H18) -> 5.2405014e+09
C19: UF 12 | D19: =ROUND(UUFF!AD17,2) -> 2.1686404e+09 | E19: =ROUND((D19*22%),2) -> 4.7710089e+08 | F19: =ROUND((D19*4%),2) -> 86745617 | G19: =ROUND((D19*4%),2) -> 86745617 | H19: =ROUND((G19*19%),2) -> 16481667 | I19: =SUM(D19:H19) -> 2.8357142e+09
C20: UF 13 | D20: =ROUND(UUFF!AF17,2) -> 1.2633158e+09 | E20: =ROUND((D20*22%),2) -> 2.7792947e+08 | F20: =ROUND((D20*4%),2) -> 50532631 | G20: =ROUND((D20*4%),2) -> 50532631 | H20: =ROUND((G20*19%),2) -> 9601199.9 | I20: =SUM(D20:H20) -> 1.6519117e+09
C21: PEAJES | D21: =ROUND((UUFF!AI11+UUFF!AI12),2) -> 3.4309473e+09 | E21: =ROUND((D21*22%),2) -> 7.5480841e+08 | F21: =ROUND((D21*4%),2) -> 1.3723789e+08 | G21: =ROUND((D21*4%),2) -> 1.3723789e+08 | H21: =ROUND((G21*19%),2) -> 26075200 | I21: =SUM(D21:H21) -> 4.4863067e+09
C22: PESAJES | D22: =ROUND(UUFF!AI13,2) -> 3.2916973e+09 | E22: =ROUND((D22*22%),2) -> 7.2417341e+08 | F22: =ROUND((D22*4%),2) -> 1.3166789e+08 | G22: =ROUND((D22*4%),2) -> 1.3166789e+08 | H22: =ROUND((G22*19%),2) -> 25016900 | I22: =SUM(D22:H22) -> 4.3042234e+09
C23: CCO | D23: =ROUND(UUFF!AI15,2) -> 3.934077e+09 | E23: =ROUND((D23*22%),2) -> 8.6549694e+08 | F23: =ROUND((D23*4%),2) -> 1.5736308e+08 | G23: =ROUND((D23*4%),2) -> 1.5736308e+08 | H23: =ROUND((G23*19%),2) -> 29898985 | I23: =SUM(D23:H23) -> 5.1441991e+09
C24: RADIO COMUNICACIONES | D24: =ROUND(UUFF!AI14,2) -> 1.8120381e+09 | E24: =ROUND((D24*22%),2) -> 3.9864838e+08 | F24: =ROUND((D24*4%),2) -> 72481524 | G24: =ROUND((D24*4%),2) -> 72481524 | H24: =ROUND((G24*19%),2) -> 13771490 | I24: =SUM(D24:H24) -> 2.369421e+09
C26: TOTALES | D26: =SUM(D7:D24) -> 5.2998669e+10 | E26: =SUM(E7:E24) -> 1.1659707e+10 | F26: =SUM(F7:F24) -> 2.1199468e+09 | G26: =SUM(G7:G24) -> 2.1199468e+09 | H26: =SUM(H7:H24) -> 4.0278988e+08 | I26: =SUM(D26:H26) -> 6.9301059e+10

Sheet RESUMEN COMPONENTES
B2: PROYECTO TRONCAL MAGDALENA 1
B3: TABLA DE CANTIDADES
B4: UNIDADES FUNCIONALES TOTAL 0 - 13
C6: PRESUPUESTO WUXY
B8: ítem | C8: ITS | E8: COSTO TOTAL
B10: 1 | C10: SISTEMA DE TELEFONÍA DE EMERGENCIA | E10: ='Postes SOS'!J40 -> 6.7891053e+09
B11: 2 | C11: ESTACIÓN METEOROLÓGICA | E11: ='ESTACIÓN METEOROLOGICA'!J40 -> 4.8677534e+08
B12: 3 | C12: PANEL DE MENSAJERÍA VARIABLE | E12: =PMV!J35 -> 1.0900278e+10
B13: 4 | C13: SISTEMA DE CONTROL DE ALTURA | E13: =GALIBO!J43 -> 2.419255e+09
B14: 5 | C14: ESTACIÓN TOMA DE DATOS | E14: =ETD!J35 -> 1.7151537e+09
B15: 6 | C15: SISTEMA DE CCTV | E15: =CCTV!J36 -> 1.8944836e+09
B16: 7 | C16: FIBRA OPTICA Y COMUNICACIONES | E16: ='FO COMUNICACION'!J33 -> 1.6324858e+10
B17: 8 | C17: PEAJE | E17: =PEAJE!J93 -> 3.3525228e+09
B18: 9 | C18: PESAJE (Básculas sentido Sur y Norte) | E18: ='BásculaS Sur y Norte'!J81 -> 3.2916973e+09
B19: 10 | C19: RADIO COMUNICACIONES | E19: ='RADIO COMUNICACIONES'!J66 -> 1.8120381e+09
B20: 11 | C20: CCO | E20: =CCO!J59 -> 3.934077e+09
B21: 12 | C21: CONTROL DE ACCESOS EN PEAJE | E21: ='Control de accesos en Peaje'!J27 -> 78424521
B23: TOTAL COSTOS DIRECTOS | E23: =SUM(E10:E21) -> 5.2998669e+10
B24: ADMINISTRACION (A) | D24: 0.22 | E24: =E23*D24 -> 1.1659707e+10
B25: IMPREVISTOS (I) | D25: 0.04 | E25: =E23*D25 -> 2.1199468e+09
B26: UTILIDAD (U) | D26: 0.04 | E26: =E23*D26 -> 2.1199468e+09
B27: SUBTOTAL COSTOS DIRECTOS + AIU | E27: =SUM(E23:E26) -> 6.8898269e+10
B28: IVA SOBRE LA UTILIDAD 19% | D28: 0.19 | E28: =E26*D28 -> 4.0278988e+08
B30: TOTAL COSTO DIRECTO+AIU + IVA | E30: =E27+E28 -> 6.9301059e+10
B33: ítem | C33: ITS | E33: COSTO TOTAL
B35: 13 | C35: PASO ELEVADO FIBRA OPTICA | E35: ='Paso elevado FO'!J17 -> 82081639
B37: TOTAL COSTOS DIRECTOS | E37: =E35 -> 82081639
B38: ADMINISTRACION (A) | D38: 0.22 | E38: =E37*D38 -> 18057961
B39: IMPREVISTOS (I) | D39: 0.04 | E39: =E37*D39 -> 3283265.6
B40: UTILIDAD (U) | D40: 0.04 | E40: =E37*D40 -> 3283265.6
B41: SUBTOTAL COSTOS DIRECTOS + AIU | E41: =SUM(E37:E40) -> 1.0670613e+08
B42: IVA SOBRE LA UTILIDAD 19% | D42: 0.19 | E42: =E40*D42 -> 623820.46
B44: TOTAL COSTO DIRECTO+AIU + IVA | E44: =E41+E42 -> 1.0732995e+08
B46: ítem | C46: ITS | E46: COSTO TOTAL
B48: 14 | C48: BÁSCULAS DINAMICAS EN ZONA DE PEAJE | E48: ='Basculas Dinamicas en peaje'!J31 -> 3182719610
B50: TOTAL COSTOS DIRECTOS | E50: =E48 -> 3182719610
B51: ADMINISTRACION (A) | D51: 0.22 | E51: =E50*D51 -> 7.0019831e+08
B52: IMPREVISTOS (I) | D52: 0.04 | E52: =E50*D52 -> 1.2730878e+08
B53: UTILIDAD (U) | D53: 0.04 | E53: =E50*D53 -> 1.2730878e+08
B54: SUBTOTAL COSTOS DIRECTOS + AIU | E54: =SUM(E50:E53) -> 4137535493
B55: IVA SOBRE LA UTILIDAD 19% | D55: 0.19 | E55: =E53*D55 -> 24188669
B57: TOTAL COSTO DIRECTO+AIU + IVA | E57: =E54+E55 -> 4.1617242e+09

Sheet UBICACIÓN EQUIPOS ITS v3
A1: UBICACIÓN EQUIPOS ITS | M1: SISTEMA | N1: CANTIDAD
A2: 45918 | G2: SEPARACIÓN | J2: OBSERVACIÓN | N2: NO OBJETADOS | O2: EPC
A3: CANTIDAD | B3: RUTA | C3: UF | D3: VIA | E3: SISTEMA | F3: UBICACIÓN | G3: SOS | H3: PMV IZQ | I3: PMV DERE | M3: RADAR-ANPR | N3: 38 | O3: =COUNTIF(E4:E174,M3) -> 12
M4: PMV | N4: 29 | O4: =COUNTIF(E4:E175,M4) -> 28
A5: 1 | B5: 4510 | C5: 5.2 | D5: UNIDIRECCIONAL | E5: CCTV | F5: 38100 | M5: CCTV | N5: 121 | O5: =COUNTIF(E4:E176,M5) -> 30
A6: 2 | B6: 4510 | C6: 0D | D6: SEPARADOR | E6: CCTV | F6: 40050 | M6: POSTE SOS | N6: 88 | O6: =COUNTIF(E4:E177,M6) -> 88
A7: 3 | B7: 4510 | C7: 0D | D7: DERECHA | E7: PMV | F7: 41000 | J7: 40450 | K7: INTER KORAN | M7: GALIBO | N7: 19 | O7: =COUNTIF(E4:E178,M7) -> 8
A8: 4 | B8: 4510 | C8: 0D | D8: IZQUERDA | E8: PMV | F8: 41200 | M8: METEO | N8: 11 | O8: =COUNTIF(E4:E179,M8) -> 4
A9: 5 | B9: 4510 | C9: 0D | D9: DERECHA | E9: POSTE SOS | F9: 41180 | M9: TOTAL | N9: =SUM(N3:N8) -> 306 | O9: =SUM(O3:O8) -> 170
A10: 6 | B10: 4510 | C10: 0D | D10: DERECHA | E10: GALIBO | F10: 41350
A11: 7 | B11: 4510 | C11: 0D | D11: IZQUERDA | E11: POSTE SOS | F11: 43560 | G11: =F11-F9 -> 2380
A12: 8 | B12: 4510 | C12: 0D | D12: DERECHA | E12: POSTE SOS | F12: 46550 | G12: =F12-F11 -> 2990 | J12: 48360 | K12: PEATONAL
A13: 9 | B13: 4510 | C13: 0D | D13: IZQUERDA | E13: POSTE SOS | F13: 49550 | G13: =F13-F12 -> 3000
A14: 10 | B14: 4510 | C14: 0D | D14: DERECHA | E14: POSTE SOS | F14: 52550 | G14: =F14-F13 -> 3000
A15: 11 | B15: 4510 | C15: 0D | D15: IZQUERDA | E15: RADAR-ANPR | F15: 54000
A16: 12 | B16: 4510 | C16: 0D | D16: DERECHA | E16: RADAR-ANPR | F16: 54000
A17: 13 | B17: 4510 | C17: 0D | D17: IZQUERDA | E17: POSTE SOS | F17: 55500 | G17: =F17-F14 -> 2950
A18: 14 | B18: 4510 | C18: 0D | D18: IZQUERDA | E18: PMV | F18: 57350 | H18: =F18-F8 -> 16150
A19: 15 | B19: 4510 | C19: 0D | D19: DERECHA | E19: POSTE SOS | F19: 58500 | G19: =F19-F17 -> 3000
A20: 16 | B20: 4510 | C20: 0D | D20: DERECHA | E20: PMV | F20: 58950 | I20: =F20-F7 -> 17950
A21: 17 | B21: 4510 | C21: 0D | D21: IZQUERDA | E21: POSTE SOS | F21: 61500 | G21: =F21-F19 -> 3000
A22: 18 | B22: 4510 | C22: 0D | D22: DERECHA | E22: POSTE SOS | F22: 64450 | G22: =F22-F21 -> 2950
A23: 19 | B23: 4510 | C23: 0D | D23: IZQUERDA | E23: POSTE SOS | F23: 67150 | G23: =F23-F22 -> 2700
A24: 20 | B24: 4510 | C24: 0D | D24: SEPARADOR | E24: CCTV | F24: 69000 | J24: 68434 | K24: PEATONAL
A25: 21 | B25: 4510 | C25: 0D | D25: DERECHA | E25: POSTE SOS | F25: 70150 | G25: =F25-F23 -> 3000
A26: 22 | B26: 4510 | C26: 0D | D26: IZQUERDA | E26: POSTE SOS | F26: 73110 | G26: =F26-F25 -> 2960
A27: 23 | B27: 4510 | C27: 0D | D27: DERECHA | E27: POSTE SOS | F27: 76020 | G27: =F27-F26 -> 2910
A28: 24 | B28: 4510 | C28: 0D | D28: IZQUERDA | E28: PMV | F28: 77350 | H28: =F28-F18 -> 20000
A29: 25 | B29: 4510 | C29: 0D | D29: IZQUERDA | E29: POSTE SOS | F29: 78800 | G29: =F29-F27 -> 2780
A30: 26 | B30: 4510 | C30: 0D | D30: DERECHA | E30: PMV | F30: 78950 | I30: =F30-F20 -> 20000
A31: 27 | B31: 4510 | C31: 0D | D31: SEPARADOR | E31: CCTV | F31: 81000
A32: 28 | B32: 4510 | C32: 0D | D32: DERECHA | E32: POSTE SOS | F32: 81500 | G32: =F32-F29 -> 2700
A33: 29 | B33: 4510 | C33: 0D | D33: SEPARADOR | E33: METEO | F33: 83250
A34: 30 | B34: 4510 | C34: 0D | D34: IZQUERDA | E34: POSTE SOS | F34: 83950 | G34: =F34-F32 -> 2450
A35: 31 | B35: 4510 | C35: 1 | D35: SEPARADOR | E35: CCTV | F35: 85370
A36: 32 | B36: 4510 | C36: 1 | D36: DERECHA | E36: POSTE SOS | F36: 86900 | G36: =F36-F34 -> 2950 | J36: 86290 | K36: PEATONAL
A37: 33 | B37: 4510 | C37: 1 | D37: SEPARADOR | E37: CCTV | F37: 87100
A38: 34 | B38: 4510 | C38: 0D | D38: IZQUERDA | E38: POSTE SOS | F38: 89780 | G38: =F38-F36 -> 2880
A39: 35 | B39: 4510 | C39: 5.1 | D39: SEPARADOR | E39: CCTV | F39: 91850
A40: 36 | B40: 4510 | C40: 1 | D40: DERECHA | E40: POSTE SOS | F40: 92520 | G40: =F40-F38 -> 2740
A41: 37 | B41: 4510 | C41: 1 | D41: SEPARADOR | E41: CCTV | F41: 93920
A42: 38 | B42: 4510 | C42: 0D | D42: IZQUERDA | E42: POSTE SOS | F42: 95300 | G42: =F42-F40 -> 2780
A43: 39 | B43: 4510 | C43: 0D | D43: SEPARADOR | E43: CCTV | F43: 97030 | J43: 96890 | K43: INTER PTO BOYACA
A44: 40 | B44: 4510 | C44: 0D | D44: IZQUERDA | E44: PMV | F44: 97250 | H44: =F44-F28 -> 19900
A45: 41 | B45: 4510 | C45: 0D | D45: DERECHA | E45: POSTE SOS | F45: 98250 | G45: =F45-F42 -> 2950
A46: 42 | B46: 4510 | C46: 0D | D46: DERECHA | E46: PMV | F46: 98750 | I46: =F46-F30 -> 19800
A47: 43 | B47: 4510 | C47: 0D | D47: IZQUERDA | E47: POSTE SOS | F47: 100750 | G47: =F47-F45 -> 2500
A48: 44 | B48: 4510 | C48: 0D | D48: DERECHA | E48: POSTE SOS | F48: 102800 | G48: =F48-F47 -> 2050
A49: 45 | B49: 4510 | C49: 0D | D49: SEPARADOR | E49: CCTV | F49: 104150 | J49: 104100 | K49: Area Servicio Zambito
A50: 46 | B50: 4510 | C50: 0D | D50: IZQUERDA | E50: POSTE SOS | F50: 105360 | G50: =F50-F48 -> 2560
A51: 47 | B51: 4510 | C51: 0D | D51: DERECHA | E51: POSTE SOS | F51: 108130 | G51: =F51-F50 -> 2770 | J51: 109357 | K51: PEATONAL
A52: 48 | B52: 4510 | C52: 0D | D52: IZQUERDA | E52: POSTE SOS | F52: 111070 | G52: =F52-F51 -> 2940
A53: 49 | B53: 4510 | C53: 0D | D53: DERECHA | E53: POSTE SOS | F53: 114050 | G53: =F53-F52 -> 2980
A54: 50 | B54: 4510 | C54: 0D | D54: IZQUERDA | E54: RADAR-ANPR | F54: 116200
A55: 51 | B55: 4510 | C55: 0D | D55: DERECHA | E55: RADAR-ANPR | F55: 116200 | J55: 115673 | K55: PEATONAL
A56: 52 | B56: 4510 | C56: 0D | D56: IZQUERDA | E56: GALIBO | F56: 116200
A57: 53 | B57: 4510 | C57: 0D | D57: IZQUERDA | E57: POSTE SOS | F57: 117020 | G57: =F57-F53 -> 2970
A58: 54 | B58: 4510 | C58: 0D | D58: IZQUERDA | E58: PMV | F58: 117250 | H58: =F58-F44 -> 20000
A59: 55 | B59: 4510 | C59: 0D | D59: DERECHA | E59: PMV | F59: 118660 | I59: =F59-F46 -> 19910
A60: 56 | B60: 4510 | C60: 0D | D60: DERECHA | E60: POSTE SOS | F60: 119940 | G60: =F60-F57 -> 2920
A61: 57 | B61: 4510 | C61: 0D | D61: IZQUERDA | E61: POSTE SOS | F61: 122940 | G61: =F61-F60 -> 3000 | J61: 123806 | K61: PEATONAL
A62: 58 | B62: 4510 | C62: 2 | D62: DERECHA | E62: POSTE SOS | F62: 125940 | G62: =F62-F61 -> 3000 | J62: 125514 | K62: PEATONAL
A63: 59 | B63: 4510 | C63: 5.1 | D63: IZQUERDA | E63: POSTE SOS | F63: 128840 | G63: =F63-F62 -> 2900
A64: 60 | B64: 4510 | C64: 0D | D64: DERECHA | E64: POSTE SOS | F64: 131700 | G64: =F64-F63 -> 2860 | J64: 130000 | K64: PEATONAL
A65: 61 | B65: 4511 | C65: 5.1 | D65: IZQUERDA | E65: POSTE SOS | F65: 650 | G65: =(J65-F64)+F65 -> 2982 | J65: 134032 | K65: FIN RUTA 4510
A66: 62 | B66: 4511 | C66: 5.1 | D66: IZQUERDA | E66: PMV | F66: 2790 | H66: =F66+(J65-F58) -> 19572
A67: 63 | B67: 4511 | C67: 0D | D67: DERECHA | E67: POSTE SOS | F67: 3550 | G67: =F67-F65 -> 2900
A68: 64 | B68: 4511 | C68: 0D | D68: DERECHA | E68: GALIBO | F68: 3600
A69: 65 | B69: 4511 | C69: 0D | D69: DERECHA | E69: PMV | F69: 4200 | I69: =F69+(J65-F59) -> 19572 | J69: 4261 | K69: PEATONAL
A70: 66 | B70: 4511 | C70: 0D | D70: IZQUERDA | E70: POSTE SOS | F70: 6450 | G70: =F70-F67 -> 2900
A71: 67 | B71: 4511 | C71: 5.1 | D71: IZQUERDA | E71: CCTV | F71: 9100
A72: 68 | B72: 4511 | C72: 5.1 | D72: IZQUERDA | E72: METEO | F72: 9200 | J72: 9150 | K72: PEAJE ZAMBITO
A73: 69 | B73: 4511 | C73: 0D | D73: SEPARADOR | E73: CCTV | F73: 9365
A74: 70 | B74: 4511 | C74: 2 | D74: DERECHA | E74: POSTE SOS | F74: 11155 | G74: =F74-F70 -> 4705
A75: 71 | B75: 4511 | C75: 2 | D75: SEPARADOR | E75: CCTV | F75: 13470
A76: 72 | B76: 4511 | C76: 2 | D76: IZQUERDA | E76: POSTE SOS | F76: 13590 | G76: =F76-F74 -> 2435
A77: 73 | B77: 4511 | C77: 2 | D77: IZQUERDA | E77: PMV | F77: 14200 | H77: =F77-F66 -> 11410 | J77: 14131 | K77: PEATONAL
A78: 74 | B78: 4511 | C78: 2 | D78: SEPARADOR | E78: CCTV | F78: 14500
A79: 75 | B79: 4511 | C79: 2 | D79: DERECHA | E79: POSTE SOS | F79: 16460 | G79: =F79-F76 -> 2870
A80: 76 | B80: 4511 | C80: 5.1 | D80: IZQUERDA | E80: GALIBO | F80: 16550
A81: 77 | B81: 4511 | C81: 5.1 | D81: IZQUERDA | E81: POSTE SOS | F81: 19390 | G81: =F81-F79 -> 2930
A82: 78 | B82: 4511 | C82: 0D | D82: DERECHA | E82: POSTE SOS | F82: 22300 | G82: =F82-F81 -> 2910
A83: 79 | C83: 0D | D83: DERECHA | E83: PMV | F83: 22300 | I83: =F83-F69 -> 18100
A84: 80 | B84: 4511 | C84: 0D | D84: IZQUERDA | E84: POSTE SOS | F84: 25100 | G84: =F84-F82 -> 2800
A85: 81 | B85: 4511 | C85: 0D | D85: DERECHA | E85: POSTE SOS | F85: 28060 | G85: =F85-F84 -> 2960
A86: 82 | B86: 4511 | C86: 0D | D86: IZQUERDA | E86: POSTE SOS | F86: 30600 | G86: =F86-F85 -> 2540
A87: 83 | B87: 4511 | C87: 0D | D87: DERECHA | E87: POSTE SOS | F87: 33330 | G87: =F87-F86 -> 2730
A88: 84 | C88: 0D | D88: IZQUERDA | E88: PMV | F88: 34200 | H88: =F88-F77 -> 20000
A89: 85 | B89: 4511 | C89: 0D | D89: IZQUERDA | E89: POSTE SOS | F89: 36250 | G89: =F89-F87 -> 2920
A90: 86 | B90: 4511 | C90: 0D | D90: DERECHA | E90: RADAR-ANPR | F90: 37400
A91: 87 | B91: 4511 | C91: 0D | D91: DERECHA | E91: POSTE SOS | F91: 39100 | G91: =F91-F89 -> 2850
A92: 88 | B92: 4511 | C92: 5.1 | D92: SEPARADOR | E92: CCTV | F92: 41150
A93: 89 | B93: 4511 | C93: 0D | D93: SEPARADOR | E93: CCTV | F93: 41800
A94: 90 | B94: 4511 | C94: 2 | D94: IZQUERDA | E94: POSTE SOS | F94: 41940 | G94: =F94-F91 -> 2840
A95: 91 | B95: 4511 | C95: 5.1 | D95: DERECHA | E95: PMV | F95: 42300 | I95: =F95-F83 -> 20000
A96: 92 | B96: 4511 | C96: 5.1 | D96: DERECHA | E96: POSTE SOS | F96: 44550 | G96: =F96-F94 -> 2610
A97: 93 | B97: 4511 | C97: 2 | D97: IZQUERDA | E97: RADAR-ANPR | F97: 46900 | J97: 46143 | K97: PEATONAL
A98: 94 | B98: 4511 | C98: 2 | D98: IZQUERDA | E98: POSTE SOS | F98: 47510 | G98: =F98-F96 -> 2960
A99: 95 | B99: 4511 | C99: 5.1 | D99: DERECHA | E99: POSTE SOS | F99: 50470 | G99: =F99-F98 -> 2960
A100: 96 | B100: 4511 | C100: 3 | D100: IZQUERDA | E100: POSTE SOS | F100: 53320 | G100: =F100-F99 -> 2850
...

Sheet UUFF
A2: SUB SISTEMA | B2: UNIDAD | D2: 0D | F2: 1 | H2: 2 | J2: 3 | L2: 4 | N2: 5 | Q2: 6 | S2: 7 | U2: 8 | W2: 9 | Y2: 10 | AA2: 11 | AC2: 12 | AE2: 13 | AH2: CANTIDAD TOTAL | AI2: COSTO DIRECTO
D3: CANT | E3: VALOR | F3: CANT | G3: VALOR | H3: CANT | I3: VALOR | J3: CANT | K3: VALOR | L3: CANT | M3: VALOR | N3: CANT | O3: VALOR | P3: WUXY | Q3: CANT | R3: VALOR | S3: CANT | T3: VALOR | U3: CANT | V3: VALOR | W3: CANT | X3: VALOR | Y3: CANT | Z3: VALOR | AA3: CANT | AB3: VALOR | AC3: CANT | AD3: VALOR | AE3: CANT | AF3: VALOR | AG3: WUXY | AK3: VALOR UNITARIO
A4: SOS | B4: UND | D4: 38 | E4: =D4*AK4 -> 2.9316591e+09 | F4: 2 | G4: =F4*AK4 -> 1.5429785e+08 | H4: 6 | I4: =H4*AK4 -> 4.6289354e+08 | J4: 3 | K4: =J4*AK4 -> 2.3144677e+08 | L4: 1 | M4: =L4*AK4 -> 77148923 | N4: 9 | O4: =N4*AK4 -> 6.9434031e+08 | P4: =D4+F4+H4+J4+L4+N4 -> 59 | Q4: 1 | R4: =Q4*AK4 -> 77148923 | S4: 2 | T4: =S4*AK4 -> 1.5429785e+08 | U4: 1 | V4: =U4*AK4 -> 77148923 | W4: 2 | X4: =W4*AK4 -> 1.5429785e+08 | Y4: 2 | Z4: =Y4*AK4 -> 1.5429785e+08 | AA4: 15 | AB4: =AA4*AK4 -> 1.1572339e+09 | AC4: 4 | AD4: =AC4*AK4 -> 3.0859569e+08 | AE4: 2 | AF4: =AE4*AK4 -> 1.5429785e+08 | AG4: =Q4+S4+U4+W4+Y4+AA4+AC4+AE4 -> 29 | AH4: =AG4+P4 -> 88 | AI4: =ROUND(AH4*AK4,2) -> 6.7891053e+09 | AK4: =ROUND('RESUMEN COMPONENTES'!E10/88,2) -> 77148923
A5: ESTACIÓN METEOROLÓGICA | B5: UND | D5: 1 | E5: =D5*AK5 -> 1.2169384e+08 | F5: 0 | G5: =F5*AK5 -> 0 | H5: 0 | I5: =H5*AK5 -> 0 | J5: 0 | K5: =J5*AK5 -> 0 | L5: 0 | M5: =L5*AK5 -> 0 | N5: 1 | O5: =N5*AK5 -> 1.2169384e+08 | P5: =D5+F5+H5+J5+L5+N5 -> 2 | Q5: 1 | R5: =Q5*AK5 -> 1.2169384e+08 | S5: 0 | T5: =S5*AK5 -> 0 | U5: 0 | V5: =U5*AK5 -> 0 | W5: 0 | X5: =W5*AK5 -> 0 | Y5: 0 | Z5: =Y5*AK5 -> 0 | AA5: 0 | AB5: =AA5*AK5 -> 0 | AC5: 0 | AD5: =AC5*AK5 -> 0 | AE5: 1 | AF5: =AE5*AK5 -> 1.2169384e+08 | AG5: =Q5+S5+U5+W5+Y5+AA5+AC5+AE5 -> 2 | AH5: =AG5+P5 -> 4 | AI5: =ROUND(AH5*AK5,2) -> 4.8677534e+08 | AK5: =ROUND('RESUMEN COMPONENTES'!E11/4,2) -> 1.2169384e+08
A6: PANEL DE MENSAJERÍA VARIABLE | B6: UND | D6: 13 | E6: =D6*AK6 -> 5.0608433e+09 | F6: 0 | G6: =F6*AK6 -> 0 | H6: 1 | I6: =H6*AK6 -> 3.8929564e+08 | J6: 1 | K6: =J6*AK6 -> 3.8929564e+08 | L6: 1 | M6: =L6*AK6 -> 3.8929564e+08 | N6: 3 | O6: =N6*AK6 -> 1.1678869e+09 | P6: =D6+F6+H6+J6+L6+N6 -> 19 | Q6: 0 | R6: =Q6*AK6 -> 0 | S6: 1 | T6: =S6*AK6 -> 3.8929564e+08 | U6: 1 | V6: =U6*AK6 -> 3.8929564e+08 | W6: 0 | X6: =W6*AK6 -> 0 | Y6: 1 | Z6: =Y6*AK6 -> 3.8929564e+08 | AA6: 5 | AB6: =AA6*AK6 -> 1.9464782e+09 | AC6: 1 | AD6: =AC6*AK6 -> 3.8929564e+08 | AE6: 0 | AF6: =AE6*AK6 -> 0 | AG6: =Q6+S6+U6+W6+Y6+AA6+AC6+AE6 -> 9 | AH6: =AG6+P6 -> 28 | AI6: =ROUND(AH6*AK6,2) -> 1.0900278e+10 | AK6: =ROUND('RESUMEN COMPONENTES'!E12/28,2) -> 3.8929564e+08
A7: GÁLIBO | B7: UND | D7: 3 | E7: =D7*AK7 -> 9.0722061e+08 | F7: 0 | G7: =F7*AK7 -> 0 | H7: 0 | I7: =H7*AK7 -> 0 | J7: 0 | K7: =J7*AK7 -> 0 | L7: 0 | M7: =L7*AK7 -> 0 | N7: 2 | O7: =N7*AK7 -> 6.0481374e+08 | P7: =D7+F7+H7+J7+L7+N7 -> 5 | Q7: 1 | R7: =Q7*AK7 -> 3.0240687e+08 | S7: 0 | T7: =S7*AK7 -> 0 | U7: 0 | V7: =U7*AK7 -> 0 | W7: 0 | X7: =W7*AK7 -> 0 | Y7: 0 | Z7: =Y7*AK7 -> 0 | AA7: 1 | AB7: =AA7*AK7 -> 3.0240687e+08 | AC7: 0 | AD7: =AC7*AK7 -> 0 | AE7: 1 | AF7: =AE7*AK7 -> 3.0240687e+08 | AG7: =Q7+S7+U7+W7+Y7+AA7+AC7+AE7 -> 3 | AH7: =AG7+P7 -> 8 | AI7: =ROUND(AH7*AK7,2) -> 2.419255e+09 | AK7: =ROUND('RESUMEN COMPONENTES'!E13/8,2) -> 3.0240687e+08
A8: ESTACIÓN TOMA DE DATOS + CAMARA PLACAS | B8: UND | D8: 5 | E8: =D8*AK8 -> 7.1464736e+08 | F8: 0 | G8: =F8*AK8 -> 0 | H8: 1 | I8: =H8*AK8 -> 1.4292947e+08 | J8: 0 | K8: =J8*AK8 -> 0 | L8: 1 | M8: =L8*AK8 -> 1.4292947e+08 | N8: 1 | O8: =N8*AK8 -> 1.4292947e+08 | P8: =D8+F8+H8+J8+L8+N8 -> 8 | Q8: 0 | R8: =Q8*AK8 -> 0 | S8: 1 | T8: =S8*AK8 -> 1.4292947e+08 | U8: 0 | V8: =U8*AK8 -> 0 | W8: 0 | X8: =W8*AK8 -> 0 | Y8: 0 | Z8: =Y8*AK8 -> 0 | AA8: 2 | AB8: =AA8*AK8 -> 2.8585894e+08 | AC8: 1 | AD8: =AC8*AK8 -> 1.4292947e+08 | AE8: 0 | AF8: =AE8*AK8 -> 0 | AG8: =Q8+S8+U8+W8+Y8+AA8+AC8+AE8 -> 4 | AH8: =AG8+P8 -> 12 | AI8: =ROUND(AH8*AK8,2) -> 1.7151537e+09 | AK8: =ROUND('RESUMEN COMPONENTES'!E14/12,2) -> 1.4292947e+08
A9: SISTEMA DE CCTV | B9: UND | D9: 7 | E9: =D9*AK9 -> 4.4204618e+08 | F9: 3 | G9: =F9*AK9 -> 1.8944836e+08 | H9: 2 | I9: =H9*AK9 -> 1.2629891e+08 | J9: 0 | K9: =J9*AK9 -> 0 | L9: 0 | M9: =L9*AK9 -> 0 | N9: 7 | O9: =N9*AK9 -> 4.4204618e+08 | P9: =D9+F9+H9+J9+L9+N9 -> 19 | Q9: 2 | R9: =Q9*AK9 -> 1.2629891e+08 | S9: 0 | T9: =S9*AK9 -> 0 | U9: 0 | V9: =U9*AK9 -> 0 | W9: 3 | X9: =W9*AK9 -> 1.8944836e+08 | Y9: 0 | Z9: =Y9*AK9 -> 0 | AA9: 5 | AB9: =AA9*AK9 -> 3.1574727e+08 | AC9: 0 | AD9: =AC9*AK9 -> 0 | AE9: 1 | AF9: =AE9*AK9 -> 63149454 | AG9: =Q9+S9+U9+W9+Y9+AA9+AC9+AE9 -> 11 | AH9: =AG9+P9 -> 30 | AI9: =ROUND(AH9*AK9,2) -> 1.8944836e+09 | AK9: =ROUND('RESUMEN COMPONENTES'!E15/30,2) -> 63149454
A10: FIBRA OPTICA Y COMUNICACIONES | B10: KM | D10: =(45.14+3.94+20+10.58+20+0.472)*1.12 -> 112.14784 | E10: =D10*AK10 -> 6.2887728e+09 | F10: =(1.64+2.843)*1.12 -> 5.02096 | G10: =F10*AK10 -> 2.8155403e+08 | H10: =(6.605+11.1)*1.12 -> 19.8296 | I10: =H10*AK10 -> 1.1119594e+09 | J10: =(0.56+8.74+3.05)*1.12 -> 13.832 | K10: =J10*AK10 -> 7.756396e+08 | L10: =10*1.12 -> 11.2 | M10: =L10*AK10 -> 6.2804826e+08 | N10: =(5.04+1.18+0.505+1.092+8.456+13.395+0.4+0.8)*1.12 -> 34.57216 | O10: =N10*AK10 -> 1.9386594e+09 | P10: =D10+F10+H10+J10+L10+N10 -> 196.60256 | Q10: =8.57*1.12 -> 9.5984 | R10: =Q10*AK10 -> 5.3823736e+08 | S10: =13.78*1.12 -> 15.4336 | T10: =S10*AK10 -> 8.654505e+08 | U10: =10*1.12 -> 11.2 | V10: =U10*AK10 -> 6.2804826e+08 | W10: =10.69*1.12 -> 11.9728 | X10: =W10*AK10 -> 6.7138359e+08 | Y10: =10.31*1.12 -> 11.5472 | Z10: =Y10*AK10 -> 6.4751775e+08 | AA10: 0 | AB10: =AA10*AK10 -> 0 | AC10: =21.142*1.12 -> 23.67904 | AD10: =AC10*AK10 -> 1.3278196e+09 | AE10: =9.9*1.12 -> 11.088 | AF10: =AE10*AK10 -> 6.2176777e+08 | AG10: =Q10+S10+U10+W10+Y10+AA10+AC10+AE10 -> 94.51904 | AH10: =AG10+P10 -> 291.1216 | AI10: =ROUND(AH10*AK10,2) -> 1.6324858e+10 | AK10: =ROUND('RESUMEN COMPONENTES'!E16/291.1216,2) -> 56075737
A11: PEAJE | B11: GLB | P11: 1 | AG11: 1 | AH11: =AG11+P11 -> 2 | AI11: =ROUND(AH11*AK11,2) -> 3.3525228e+09 | AK11: =ROUND('RESUMEN COMPONENTES'!E17/2,2) -> 1.6762614e+09
A12: CONTROL DE ACCESOS EN PEAJE | B12: GLB | AH12: 2 | AI12: =ROUND(AH12*AK12,2) -> 78424521 | AK12: =ROUND('RESUMEN COMPONENTES'!E21/2,2) -> 39212261
A13: PESAJE Básculas sentido Sur y Norte | B13: GLB | P13: 0 | AG13: 2 | AH13: =AG13+P13 -> 2 | AI13: =ROUND(AH13*AK13,2) -> 3.2916973e+09 | AK13: =ROUND('RESUMEN COMPONENTES'!E18/2,2) -> 1.6458487e+09
A14: RADIO COMUNICACIONES | B14: UND | D14: 3 | L14: 1 | P14: 3 | W14: 1 | AC14: 1 | AG14: 3 | AH14: =AG14+P14 -> 6 | AI14: =ROUND(AH14*AK14,2) -> 1.8120381e+09 | AK14: =ROUND('RESUMEN COMPONENTES'!E19/6,2) -> 3.0200635e+08
A15: CCO | B15: GLB | AH15: 1 | AI15: =ROUND(AH15*AK15,2) -> 3.934077e+09 | AK15: =ROUND('RESUMEN COMPONENTES'!E20,2) -> 3.934077e+09
A17: TOTAL COSTOS DIRECTOS | E17: =SUM(E4:E15) -> 1.6466883e+10 | G17: =SUM(G4:G15) -> 6.2530024e+08 | I17: =SUM(I4:I15) -> 2.233377e+09 | K17: =SUM(K4:K15) -> 1.396382e+09 | M17: =SUM(M4:M15) -> 1.2374223e+09 | O17: =SUM(O4:O15) -> 5.1123698e+09 | R17: =SUM(R4:R15) -> 1.1657859e+09 | T17: =SUM(T4:T15) -> 1.5519735e+09 | V17: =SUM(V4:V15) -> 1.0944928e+09 | X17: =SUM(X4:X15) -> 1.0151298e+09 | Z17: =SUM(Z4:Z15) -> 1.1911112e+09 | AB17: =SUM(AB4:AB15) -> 4.0077251e+09 | AD17: =SUM(AD4:AD15) -> 2.1686404e+09 | AF17: =SUM(AF4:AF15) -> 1.2633158e+09 | AI17: =SUM(AI4:AI15) -> 5.2998669e+10 | AK17: =SUM(E17:AF17) -> 4.0529909e+10
A18: ADMINISTRACIÓN | C18: 0.22 | E18: =E17*$C$18 -> 3.6227143e+09 | G18: =G17*$C$18 -> 1.3756605e+08 | I18: =I17*$C$18 -> 4.9134294e+08 | K18: =K17*$C$18 -> 3.0720404e+08 | M18: =M17*$C$18 -> 2.722329e+08 | O18: =O17*$C$18 -> 1.1247214e+09 | R18: =R17*$C$18 -> 2.564729e+08 | T18: =T17*$C$18 -> 3.4143416e+08 | V18: =V17*$C$18 -> 2.4078842e+08 | X18: =X17*$C$18 -> 2.2332856e+08 | Z18: =Z17*$C$18 -> 2.6204447e+08 | AB18: =AB17*$C$18 -> 8.8169953e+08 | AD18: =AD17*$C$18 -> 4.7710089e+08 | AF18: =AF17*$C$18 -> 2.7792947e+08 | AI18: =$AI$17*C18 -> 1.1659707e+10
A19: IMPREVISTOS | C19: 0.04 | E19: =E17*$C$19 -> 6.5867533e+08 | G19: =G17*$C$19 -> 25012010 | I19: =I17*$C$19 -> 89335080 | K19: =K17*$C$19 -> 55855280 | M19: =M17*$C$19 -> 49496892 | O19: =O17*$C$19 -> 2.0449479e+08 | R19: =R17*$C$19 -> 46631436 | T19: =T17*$C$19 -> 62078938 | V19: =V17*$C$19 -> 43779713 | X19: =X17*$C$19 -> 40605192 | Z19: =Z17*$C$19 -> 47644449 | AB19: =AB17*$C$19 -> 1.60309e+08 | AD19: =AD17*$C$19 -> 86745617 | AF19: =AF17*$C$19 -> 50532631 | AI19: =$AI$17*C19 -> 2.1199468e+09
A20: UTILIDAD | C20: 0.04 | E20: =E17*$C$20 -> 6.5867533e+08 | G20: =G17*$C$20 -> 25012010 | I20: =I17*$C$20 -> 89335080 | K20: =K17*$C$20 -> 55855280 | M20: =M17*$C$20 -> 49496892 | O20: =O17*$C$20 -> 2.0449479e+08 | R20: =R17*$C$20 -> 46631436 | T20: =T17*$C$20 -> 62078938 | V20: =V17*$C$20 -> 43779713 | X20: =X17*$C$20 -> 40605192 | Z20: =Z17*$C$20 -> 47644449 | AB20: =AB17*$C$20 -> 1.60309e+08 | AD20: =AD17*$C$20 -> 86745617 | AF20: =AF17*$C$20 -> 50532631 | AI20: =$AI$17*C20 -> 2.1199468e+09
A21: SUB TOTAL COSTOS DIRECTOS + AIU | E21: =E17+E18+E19+E20 -> 2.1406948e+10 | G21: =G17+G18+G19+G20 -> 8.1289032e+08 | I21: =I17+I18+I19+I20 -> 2.9033901e+09 | K21: =K17+K18+K19+K20 -> 1.8152966e+09 | M21: =M17+M18+M19+M20 -> 1.608649e+09 | O21: =O17+O18+O19+O20 -> 6.6460807e+09 | R21: =R17+R18+R19+R20 -> 1.5155217e+09 | T21: =T17+T18+T19+T20 -> 2.0175655e+09 | V21: =V17+V18+V19+V20 -> 1.4228407e+09 | X21: =X17+X18+X19+X20 -> 1.3196687e+09 | Z21: =Z17+Z18+Z19+Z20 -> 1.5484446e+09 | AB21: =AB17+AB18+AB19+AB20 -> 5.2100427e+09 | AD21: =AD17+AD18+AD19+AD20 -> 2.8192326e+09 | AF21: =AF17+AF18+AF19+AF20 -> 1.6423105e+09 | AI21: =SUM(AI17:AI20) -> 6.8898269e+10
A22: IVA SOBRE UTILIDAD | C22: 0.19 | E22: =E20*$C$22 -> 1.2514831e+08 | G22: =G20*$C$22 -> 4752281.8 | I22: =I20*$C$22 -> 16973665 | K22: =K20*$C$22 -> 10612503 | M22: =M20*$C$22 -> 9404409.4 | O22: =O20*$C$22 -> 38854011 | R22: =R20*$C$22 -> 8859972.8 | T22: =T20*$C$22 -> 11794998 | V22: =V20*$C$22 -> 8318145.4 | X22: =X20*$C$22 -> 7714986.4 | Z22: =Z20*$C$22 -> 9052445.4 | AB22: =AB20*$C$22 -> 30458711 | AD22: =AD20*$C$22 -> 16481667 | AF22: =AF20*$C$22 -> 9601199.9 | AI22: =C22*AI20 -> 4.0278988e+08
A24: COSTO TOTAL | E24: =E22+E21 -> 2.1532096e+10 | G24: =G22+G21 -> 8.176426e+08 | I24: =I22+I21 -> 2.9203638e+09 | K24: =K22+K21 -> 1.8259091e+09 | M24: =M22+M21 -> 1.6180534e+09 | O24: =O22+O21 -> 6.6849348e+09 | R24: =R22+R21 -> 1.5243816e+09 | T24: =T22+T21 -> 2.0293605e+09 | V24: =V22+V21 -> 1.4311588e+09 | X24: =X22+X21 -> 1.3273837e+09 | Z24: =Z22+Z21 -> 1.5574971e+09 | AB24: =AB22+AB21 -> 5.2405014e+09 | AD24: =AD22+AD21 -> 2.8357142e+09 | AF24: =AF22+AF21 -> 1.6519117e+09 | AI24: =AI22+AI21 -> 6.9301059e+10 | AK24: =AI4+AI5+AI6+AI7+AI8+AI9+AI10 -> 4.0529909e+10
AK25: =SUM(E17:AF17) -> 4.0529909e+10

Sheet Postes SOS
B2: PROYECTO TRONCAL MAGDALENA 1
B3: TABLA DE CANTIDADES | D3: PRESUPUESTO WUXY
B4: UNIDADES FUNCIONALES TOTAL 0 - 13
B8: ítem | C8: ITS | D8: Unidad | E8: Cantidad | F8: SUMINISTRO | H8: INSTALACIÓN PUESTA EN FUNCIONAMIENTO Y PRUEBAS | J8: COSTO TOTAL
B9: 1 | C9: SISTEMA DE TELEFONÍA DE EMERGENCIA | F9: Costo unitario | G9: Total suministro | H9: Costo unitario | I9: Total Instalación | J9: TOTAL
E10: TOTAL | F10: Col $ | G10: Col $ | H10: Col $ | I10: Col $ | J10: Col $
B11: =B9+0.01 -> 1.01 | C11: Teléfono SOS, con gabinete IP65 sin ingreso de agua. Incluye switch de puerta abierta. | D11: Un | E11: 88 | F11: 2504818.8 | G11: =E11*F11 -> 2.2042406e+08 | H11: 5783685.6 | I11: =E11*H11 -> 5.0896433e+08 | J11: =G11+I11 -> 7.2938839e+08
B12: =B11+0.01 -> 1.02 | C12: Licenciamiento SOS | D12: Un | E12: 88 | G12: =E12*F12 -> 0 | I12: =E12*H12 -> 0 | J12: =G12+I12 -> 0
B13: =B12+0.01 -> 1.03 | C13: Estructura metálica poste de 6m, Gabinete IP65 | D13: Un | E13: 88 | F13: 8904763.9 | G13: =E13*F13 -> 7.8361922e+08 | H13: 7776312.5 | I13: =E13*H13 -> 6.843155e+08 | J13: =G13+I13 -> 1.4679347e+09
B14: =B13+0.01 -> 1.04 | C14: Corona antiescalatoria | D14: Un | E14: 88 | F14: 737969.81 | G14: =E14*F14 -> 64941343 | H14: 225338.4 | I14: =E14*H14 -> 19829779 | J14: =G14+I14 -> 84771123
B15: =B14+0.01 -> 1.05 | C15: Cinturón(es) antivandálico(s) con candado(s) | D15: Un | E15: 176 | F15: 1191045.6 | G15: =E15*F15 -> 2.0962403e+08 | H15: 258200.78 | I15: =E15*H15 -> 45443337 | J15: =G15+I15 -> 2.5506736e+08
B16: =B15+0.01 -> 1.06 | C16: Señalización postes SOS, según manual de señalización vigente más (No.SOS x 2, Instrucciones de uso y rotulo en Braille) | D16: Un | E16: 88 | F16: 319476.85 | G16: =E16*F16 -> 28113963 | H16: 688534 | I16: =E16*H16 -> 60590992 | J16: =G16+I16 -> 88704955
B17: =B16+0.01 -> 1.07 | C17: Cintas retrorreflectivas de color blanco 2x | D17: Un | E17: 88 | G17: =E17*F17 -> 0 | I17: =E17*H17 -> 0 | J17: =G17+I17 -> 0
B18: =B17+0.01 -> 1.08 | C18: Paneles solares, indicar capacidad * | D18: Un | E18: 88 | F18: 12770505 | G18: =E18*F18 -> 1.1238045e+09 | H18: 273849.28 | I18: =E18*H18 -> 24098736 | J18: =G18+I18 -> 1.1479032e+09
B19: =B18+0.01 -> 1.09 | C19: Soporte metálico para paneles solares | D19: Un | E19: 88 | G19: =E19*F19 -> 0 | I19: =E19*H19 -> 0 | J19: =G19+I19 -> 0
B20: =B19+0.01 -> 1.1 | C20: Baterías, indicar capacidad para autonomía de 72 horas | D20: Un | E20: 88 | G20: =E20*F20 -> 0 | I20: =E20*H20 -> 0 | J20: =G20+I20 -> 0
B21: =B20+0.01 -> 1.11 | C21: Controlador para panel solar | D21: Un | E21: 88 | G21: =E21*F21 -> 0 | I21: =E21*H21 -> 0 | J21: =G21+I21 -> 0
B22: =B21+0.01 -> 1.12 | C22: Gabinete IP 65, sin ingreso de agua, para baterías, tablero eléctrico protecciones eléctricas, (Termomagnéticas y sobretensión) Incluye switch de puerta abierta, con accesorios de fijación y montaje. | D22: Un | E22: 88 | F22: 5503707 | G22: =E22*F22 -> 484326216 | H22: 2798928.7 | I22: =E22*H22 -> 2.4630573e+08 | J22: =G22+I22 -> 7.3063194e+08
B23: =B22+0.01 -> 1.13 | C23: Sistema Puesta a Tierra SOS. (Incluye varilla(s), caja de inspección, Soldadura, tratamiento de suelo y medida) | D23: Un | E23: 88 | F23: 4486477.7 | G23: =E23*F23 -> 3.9481004e+08 | H23: 3914826.5 | I23: =E23*H23 -> 3.4450474e+08 | J23: =G23+I23 -> 7.3931477e+08
B24: =B23+0.01 -> 1.14 | C24: Cimentación Dado de 80x80x80 cm. Estos deben disponer de dos tubos de 3” para el ingreso del cableado y con un anclaje de 4 pernos de acero galvanizado a tierra de ¾" de diámetro, estos son usados para soporte y fijación de los postes SOS. ** | D24: Un | E24: 88 | G24: =E24*F24 -> 0 | H24: 3609587.7 | I24: =E24*H24 -> 3.1764372e+08 | J24: =G24+I24 -> 3.1764372e+08
B25: =B24+0.01 -> 1.15 | C25: Placa de concreto que rodea la cimentación del poste de 1,50 m x 1,70 m, con 20 cm de espesor reforzada. Apta, desde la calzada, para el acceso personas con capacidad reducida, incluye obras civiles para lograr el acceso (demolición, adecuaciones). ** | D25: Un | E25: 88 | G25: =E25*F25 -> 0 | I25: =E25*H25 -> 0 | J25: =G25+I25 -> 0
B26: =B25+0.01 -> 1.16 | C26: Barandas de protección, 3 barandas, de 1,3 m ancho x 1,2 m de alto | D26: Un | E26: 88 | F26: 1962182.7 | G26: =E26*F26 -> 1.7267207e+08 | H26: 360959.08 | I26: =E26*H26 -> 31764399 | J26: =G26+I26 -> 2.0443647e+08
B27: =B26+0.01 -> 1.17 | C27: Caja para empalme de 8 puertos | D27: Un | E27: 88 | F27: 275560 | G27: =E27*F27 -> 24249280 | H27: 180620 | I27: =E27*H27 -> 15894560 | J27: =G27+I27 -> 40143840
B28: =B27+0.01 -> 1.18 | C28: Patch Cord fibra óptica mono modo lc - lc | D28: Un | E28: 176 | F28: 31385 | G28: =E28*F28 -> 5523760 | H28: 31603.894 | I28: =E28*H28 -> 5562285.4 | J28: =G28+I28 -> 11086045
B29: =B28+0.01 -> 1.19 | C29: Caja de empalme tipo botella (mufla) para F.O de 48 hilos con cierre térmico para uso subterráneo. | D29: Un | E29: 88 | F29: 192904 | G29: =E29*F29 -> 16975552 | H29: 170263 | I29: =E29*H29 -> 14983144 | J29: =G29+I29 -> 31958696
B30: =B29+0.01 -> 1.2 | C30: Cajas para la Red Troncal, de paso o derivación, de 80X80X80, dimensiones internas | D30: Un | E30: 176 | F30: 962106 | G30: =E30*F30 -> 169330656 | H30: 817672.2 | I30: =E30*H30 -> 1.4391031e+08 | J30: =G30+I30 -> 3.1324096e+08
B31: =B30+0.01 -> 1.21 | C31: Caja de reserva para micro cable de Fibra Óptica | D31: Un | E31: 88 | F31: 455761 | G31: =E31*F31 -> 40106968 | H31: 97455 | I31: =E31*H31 -> 8576040 | J31: =G31+I31 -> 48683008
B32: =B31+0.01 -> 1.22 | C32: Pig Tail | D32: Un | E32: 352 | F32: 7418.4565 | G32: =E32*F32 -> 2611296.7 | H32: 2017.5034 | I32: =E32*H32 -> 710161.2 | J32: =G32+I32 -> 3321457.9
B33: =B32+0.01 -> 1.23 | C33: Cable de servicio de FO, 8 hilos y longitud promedio de 30 m, con características de calidad iguales o mejores a las del microducto de la troncal. | D33: Un | E33: 88 | F33: 149435 | G33: =E33*F33 -> 13150280 | H33: 138607.72 | I33: =E33*H33 -> 12197479 | J33: =G33+I33 -> 25347759
B34: =B35+0.01 -> 1.25 | C34: Canalización y ducto Conduit de 1 y 1/2", entre la troncal de FO y el ITS, en longitud promedio de 30 m | D34: Un | E34: 88 | F34: 263833 | G34: =E34*F34 -> 23217304 | H34: 2265263.4 | I34: =E34*H34 -> 1.9934318e+08 | J34: =G34+I34 -> 2.2256048e+08
B35: =B33+0.01 -> 1.24 | C35: Fusiones | D35: Un | E35: 1056 | F35: 7441 | G35: =E35*F35 -> 7857696 | H35: 45514 | I35: =E35*H35 -> 48062784 | J35: =G35+I35 -> 55920480
B36: =B34+0.01 -> 1.26 | C36: Pequeño material de montaje | D36: Gbl | E36: 88 | F36: 2977793.9 | G36: =E36*F36 -> 2.6204586e+08 | I36: =E36*H36 -> 0 | J36: =G36+I36 -> 2.6204586e+08
B37: =B36+0.01 -> 1.27 | C37: Capacitación | D37: Gbl | E37: 1 | F37: 9000000 | G37: =E37*F37 -> 9000000 | I37: =E37*H37 -> 0 | J37: =G37+I37 -> 9000000
B38: =B37+0.01 -> 1.28 | C38: Retiro y disposición adecuada de las estructuras metálicas y/o de concreto de los antiguos postes SOS existentes y disposición en sitios apropiados y con certificación en ZODME. | D38: Un | E38: 15 | G38: =E38*F38 -> 0 | H38: 4500000 | I38: =E38*H38 -> 67500000 | J38: =G38+I38 -> 67500000
H40: TOTAL COSTOS DIRECTOS | J40: =SUM(J11:J37) -> 6.7891053e+09
F41: ADMINISTRACION (A) | I41: 0.22 | J41: =J40*I41 -> 1.4936032e+09
F42: IMPREVISTOS (I) | I42: 0.04 | J42: =J40*I42 -> 2.7156421e+08
F43: UTILIDAD (U) | I43: 0.04 | J43: =J40*I43 -> 2.7156421e+08
F44: SUBTOTAL COSTOS DIRECTOS + AIU
F45: IVA SOBRE LA UTILIDAD 19% | I45: 0.19 | J45: =J43*I45 -> 51597200
H47: TOTAL COSTO DIRECTO+AIU + IVA | J47: =SUM(J40:J45) -> 8.877434e+09
B50: * | C50: El presupuesto de la solución solar incluye la totalidad de la solución
B51: ** | C51: El presupuesto de la cimentación y la placa se encuentran incluidos en el mismo valor

Sheet ESTACIÓN METEOROLOGICA
B2: PROYECTO TRONCAL MAGDALENA 1
B3: TABLA DE CANTIDADES | D3: PRESUPUESTO WUXY
B4: UNIDADES FUNCIONALES TOTAL 0 - 13
B6: ítem | C6: ITS | D6: Unidad | E6: Cantidad | F6: SUMINISTRO | H6: INSTALACIÓN PUESTA EN FUNCIONAMIENTO Y PRUEBAS | J6: COSTO TOTAL
B7: 2 | C7: ESTACIÓN METEOROLÓGICA | F7: Costo unitario | G7: Total suministro | H7: Costo unitario | I7: Total Instalación | J7: TOTAL
E8: TOTAL | F8: Col $ | G8: Col $ | H8: Col $ | I8: Col $ | J8: Col $
B9: =B7+0.01 -> 2.01 | C9: Estación Meteorológica integrada | D9: Un | E9: 4 | F9: =43966191*1.058 -> 46516230 | G9: =E9*F9 -> 1.8606492e+08 | H9: 1804793.3 | I9: =E9*H9 -> 7219173.3 | J9: =G9+I9 -> 1.9328409e+08
B10: =B9+0.01 -> 2.02 | C10: Sensor de visibilidad | D10: Un | E10: 4 | F10: =41305021*1.058 -> 43700712 | G10: =E10*F10 -> 1.7480285e+08 | I10: =E10*H10 -> 0 | J10: =G10+I10 -> 1.7480285e+08
B11: =B10+0.01 -> 2.03 | C11: Sensor de evapotranspiración potencial | D11: Un | E11: 4 | F11: =590000*2 -> 1180000 | G11: =E11*F11 -> 4720000 | H11: 450000 | I11: =E11*H11 -> 1800000 | J11: =G11+I11 -> 6520000
B12: =B11+0.01 -> 2.04 | C12: Paneles solares, indicar capacidad, no se requiere, se hará uso de la energía AC | D12: Un | E12: 0 | G12: =E12*F12 -> 0 | I12: =E12*H12 -> 0 | J12: =G12+I12 -> 0
B13: =B12+0.01 -> 2.05 | C13: Soporte metálico para paneles solares, no se requiere, se hará uso de la energía AC | D13: Un | E13: 0 | G13: =E13*F13 -> 0 | I13: =E13*H13 -> 0 | J13: =G13+I13 -> 0
B14: =B13+0.01 -> 2.06 | C14: Baterías, indicar capacidad para autonomía de 48 horas, no se requiere, se hará uso de la energía AC | D14: Un | E14: 0 | G14: =E14*F14 -> 0 | I14: =E14*H14 -> 0 | J14: =G14+I14 -> 0
B15: =B14+0.01 -> 2.07 | C15: Controlador para panel solar, no se requiere, se hará uso de la energía AC | D15: Un | E15: 0 | G15: =E15*F15 -> 0 | I15: =E15*H15 -> 0 | J15: =G15+I15 -> 0
B16: =B15+0.01 -> 2.08 | C16: Gabinete de control, protección IP65 sin ingreso de agua, el tamaño se ajustará dependiendo de los equipos a instalar y demás condiciones técnicas, con tablero eléctrico, protecciones eléctricas (Termomagnéticas y sobretensión). Incluye switch de puerta abierta, con accesorios de fijación y montaje. | D16: Un | E16: 4 | F16: =2747578*1.058 -> 2906937.5 | G16: =E16*F16 -> 11627750 | H16: 866300.96 | I16: =E16*H16 -> 3465203.8 | J16: =G16+I16 -> 15092954
B17: =B16+0.01 -> 2.09 | C17: Coraza liquid tight 3/4" | D17: Un | E17: 4 | F17: 150000 | G17: =E17*F17 -> 600000 | I17: =E17*H17 -> 0 | J17: =G17+I17 -> 600000
B18: =B17+0.01 -> 2.1 | C18: Conector Recto coraza liquid tight 3/4" acero galvanizado | D18: Un | E18: 4 | F18: 30500 | G18: =E18*F18 -> 122000 | I18: =E18*H18 -> 0 | J18: =G18+I18 -> 122000
B19: =B18+0.01 -> 2.11 | C19: Suministro e instalación Cable UTP CAT 6 certificado incluye ponchado y accesorios | D19: Un | E19: 4 | F19: =5632*1.058 -> 5958.656 | G19: =E19*F19 -> 23834.624 | H19: 4476.26 | I19: =E19*H19 -> 17905.04 | J19: =G19+I19 -> 41739.664
B20: =B19+0.01 -> 2.12 | C20: Poste octogonal de 6 metros en acero galvanizado para estación meteorológica. | D20: Un | E20: 4 | F20: =4998187*1.058 -> 5288081.8 | G20: =E20*F20 -> 21152327 | H20: 2487278.3 | I20: =E20*H20 -> 9949113.3 | J20: =G20+I20 -> 31101441
B21: =B20+0.01 -> 2.13 | C21: Cimentación para poste de la estación meteorológica. | D21: Un | E21: 4 | G21: =E21*F21 -> 0 | I21: =E21*H21 -> 0 | J21: =G21+I21 -> 0
B22: =B21+0.01 -> 2.14 | C22: Corona antiesclatoria | D22: Un | E22: 4 | G22: =E22*F22 -> 0 | I22: =E22*H22 -> 0 | J22: =G22+I22 -> 0
B23: =B22+0.01 -> 2.15 | C23: Canalización 80 m. | D23: Un | E23: 4 | G23: =E23*F23 -> 0 | I23: =E23*H23 -> 0 | J23: =G23+I23 -> 0
B24: =B23+0.01 -> 2.16 | C24: Cableado de energía y ducto 3/4", 90m aprox. | D24: Un | E24: 4 | G24: =E24*F24 -> 0 | I24: =E24*H24 -> 0 | J24: =G24+I24 -> 0
B25: =B24+0.01 -> 2.17 | C25: Cableado UTP Cat 6 y ducto 3/4", 90m aprox. | D25: Un | E25: 4 | G25: =E25*F25 -> 0 | I25: =E25*H25 -> 0 | J25: =G25+I25 -> 0
B26: =B25+0.01 -> 2.18 | C26: Puesta a tierra (Incluye varilla(s), caja de inspección, Soldadura, tratamiento de suelo y medida). | D26: Un | E26: 4 | G26: =E26*F26 -> 0 | I26: =E26*H26 -> 0 | J26: =G26+I26 -> 0
B27: =B26+0.01 -> 2.19 | C27: Encerramiento con malla eslabonada de 2,5 x 2,5 m y concertina. | D27: Un | E27: 4 | G27: =E27*F27 -> 0 | I27: =E27*H27 -> 0 | J27: =G27+I27 -> 0
B28: =B27+0.01 -> 2.2 | C28: Caja para empalme de 8 puertos. | D28: Un | E28: 4 | G28: =E28*F28 -> 0 | I28: =E28*H28 -> 0 | J28: =G28+I28 -> 0
B29: =B28+0.01 -> 2.21 | C29: Patch Cord fibra óptica mono modo lc - lc | D29: Un | E29: 8 | F29: 31385 | G29: =E29*F29 -> 251080 | H29: 31603.894 | I29: =E29*H29 -> 252831.15 | J29: =G29+I29 -> 503911.15
B30: =B29+0.01 -> 2.22 | C30: 'Caja de empalme tipo botella (mufla) para F.O de 48 hilos con cierre térmico para uso subterráneo. | D30: Un | E30: 4 | F30: 192904 | G30: =E30*F30 -> 771616 | H30: =153879+16384 -> 170263 | I30: =E30*H30 -> 681052 | J30: =G30+I30 -> 1452668
B31: =B29+0.01 -> 2.22 | C31: Cajas para la Red Troncal, de paso o derivación, de 80X80X80. | D31: Un | E31: 8 | F31: 962106 | G31: =E31*F31 -> 7696848 | H31: 817672.2 | I31: =E31*H31 -> 6541377.6 | J31: =G31+I31 -> 14238226
B32: =B31+0.01 -> 2.23 | C32: Caja de reserva para micro cable de Fibra Óptica. | D32: Un | E32: 4 | F32: 455761 | G32: =E32*F32 -> 1823044 | H32: 97455 | I32: =E32*H32 -> 389820 | J32: =G32+I32 -> 2212864
B33: =B32+0.01 -> 2.24 | C33: Pig Tail. | D33: Un | E33: 18 | F33: 7418.4565 | G33: =E33*F33 -> 133532.22 | H33: 2017.5034 | I33: =E33*H33 -> 36315.061 | J33: =G33+I33 -> 169847.28
B34: =B33+0.01 -> 2.25 | C34: Cable de servicio de FO, 8 hilos y longitud promedio de 80 m, con características de calidad iguales o mejores a las del microducto de la troncal. | D34: Un | E34: 4 | F34: 149435 | G34: =E34*F34 -> 597740 | H34: 138607.72 | I34: =E34*H34 -> 554430.87 | J34: =G34+I34 -> 1152170.9
B35: =B36+0.01 -> 2.27 | C35: Canalización y ducto Conduit de 1 y 1/2", entre la troncal de FO y el ITS, en longitud promedio de 80 m. | D35: Un | E35: 4 | F35: 263833 | G35: =E35*F35 -> 1055332 | H35: 2265263.4 | I35: =E35*H35 -> 9061053.5 | J35: =G35+I35 -> 10116386
B36: =B34+0.01 -> 2.26 | C36: Fusiones. | D36: Un | E36: 48 | F36: 7441 | G36: =E36*F36 -> 357168 | H36: 45514 | I36: =E36*H36 -> 2184672 | J36: =G36+I36 -> 2541840
B37: =B35+0.01 -> 2.28 | C37: Material de montaje + el cableado de energía y datos entre la estación meteorológica y el Switch en la edificación correspondiente. | D37: Gbl | E37: 4 | F37: =2814550*1.058*2 -> 5955587.8 | G37: =E37*F37 -> 23822351 | I37: =E37*H37 -> 0 | J37: =G37+I37 -> 23822351
B38: =B37+0.01 -> 2.29 | C38: Capacitación | D38: Gbl | E38: 1 | F38: 9000000 | G38: =E38*F38 -> 9000000 | I38: =E38*H38 -> 0 | J38: =G38+I38 -> 9000000
H40: TOTAL COSTOS DIRECTOS | J40: =SUM(J9:J38) -> 4.8677534e+08
F41: ADMINISTRACION (A) | I41: 0.22 | J41: =J40*I41 -> 1.0709057e+08
F42: IMPREVISTOS (I) | I42: 0.04 | J42: =J40*I42 -> 19471014
F43: UTILIDAD (U) | I43: 0.04 | J43: =J40*I43 -> 19471014
F44: SUBTOTAL COSTOS DIRECTOS + AIU
F45: IVA SOBRE LA UTILIDAD 19% | I45: 0.19 | J45: =J43*I45 -> 3699492.6
H47: TOTAL COSTO DIRECTO+AIU + IVA | J47: =SUM(J40:J45) -> 6.3650744e+08

Sheet PMV
B2: PROYECTO TRONCAL MAGDALENA 1
B3: TABLA DE CANTIDADES | D3: PRESUPUESTO WUXY
B4: UNIDADES FUNCIONALES TOTAL 0 - 13
B6: ítem | C6: ITS | D6: Unidad | E6: Cantidad | F6: SUMINISTRO | H6: INSTALACIÓN PUESTA EN FUNCIONAMIENTO Y PRUEBAS | J6: COSTO TOTAL
B7: 3 | C7: PANEL DE MENSAJERÍA VARIABLE | F7: Costo unitario | G7: Total suministro | H7: Costo unitario | I7: Total Instalación | J7: TOTAL
E8: TOTAL | F8: Col $ | G8: Col $ | H8: Col $ | I8: Col $ | J8: Col $
B9: =B7+0.01 -> 3.01 | C9: Panel de Señalización Variable con 1 área grafica de 64x64 pixeles y 3 líneas con 12 caracteres cada una. | D9: Un | E9: 28 | F9: 1.506441e+08 | G9: =E9*F9 -> 4.2180348e+09 | H9: 6607129.1 | I9: =E9*H9 -> 1.8499962e+08 | J9: =G9+I9 -> 4.4030344e+09
B10: =B9+0.01 -> 3.02 | C10: Estructura metálica tipo pórtico visitable, según las normas técnicas de seguridad aplicables en Colombia. | D10: Un | E10: 0 | F10: 85404206 | G10: =E10*F10 -> 0 | H10: 16903672 | I10: =E10*H10 -> 0 | J10: =G10+I10 -> 0
B11: =B10+0.01 -> 3.03 | C11: Cimentación ( incluye estudio de suelos y diseño de cimentación para panel tipo pórtico) | D11: Un | E11: 0 | F11: 1265020 | G11: =E11*F11 -> 0 | H11: 32378602 | I11: =E11*H11 -> 0 | J11: =G11+I11 -> 0
B12: =B11+0.01 -> 3.04 | C12: Estructura metálica tipo Banderola | D12: Un | E12: 28 | F12: 50935519 | G12: =E12*F12 -> 1.4261945e+09 | H12: 6575759.8 | I12: =E12*H12 -> 1.8412128e+08 | J12: =G12+I12 -> 1.6103158e+09
B13: =B12+0.01 -> 3.05 | C13: Cimentación ( incluye estudio de suelos y diseño de cimentación para panel tipo banderola) | D13: Un | E13: 28 | F13: 1265021 | G13: =E13*F13 -> 35420587 | H13: 14097854 | I13: =E13*H13 -> 3.9473993e+08 | J13: =G13+I13 -> 4.3016051e+08
B14: =B13+0.01 -> 3.06 | C14: Gabinete de control, protección IP65 sin ingreso de agua, el tamaño se ajustará dependiendo de los equipos a instalar y demás condiciones técnicas, con tablero eléctrico, protecciones eléctricas (Termomagnéticas y sobretensión). Incluye switch de puerta abierta, con accesorios de fijación y montaje | D14: Un | E14: 28 | F14: 5360021 | G14: =E14*F14 -> 150080588 | H14: 1439183.3 | I14: =E14*H14 -> 40297134 | J14: =G14+I14 -> 1.9037772e+08
B15: =B14+0.01 -> 3.07 | C15: UPS con autonomía de 15 minutos para el panel 1G3L. Se utiliza como una medida de protección adicional para el panel. | D15: Un | E15: 28 | F15: 12349335 | G15: =E15*F15 -> 345781380 | H15: 5437338.8 | I15: =E15*H15 -> 1.5224549e+08 | J15: =G15+I15 -> 4.9802687e+08
B16: =B15+0.01 -> 3.08 | C16: Cableado de energía eléctrica | D16: Un | E16: 28 | F16: 5429786 | G16: =E16*F16 -> 152034008 | H16: 1713552.3 | I16: =E16*H16 -> 47979465 | J16: =G16+I16 -> 2.0001347e+08
B17: =B16+0.01 -> 3.09 | C17: Puesta a tierra (Incluye varilla(s), caja de inspección, Soldadura, tratamiento de suelo y medida) | D17: Un | E17: 28 | F17: 4832728 | G17: =E17*F17 -> 135316384 | H17: 2682921.9 | I17: =E17*H17 -> 75121814 | J17: =G17+I17 -> 2.104382e+08
B18: =B17+0.01 -> 3.1 | C18: Pararrayos (incluye materiales) | D18: Un | E18: 28 | F18: 4656287 | G18: =E18*F18 -> 130376036 | H18: 1075857.3 | I18: =E18*H18 -> 30124003 | J18: =G18+I18 -> 1.6050004e+08
B19: =B18+0.01 -> 3.11 | C19: Materiales menores de montaje de Paneles y UPS | D19: Un | E19: 28 | F19: 1265020 | G19: =E19*F19 -> 35420560 | H19: 527984.07 | I19: =E19*H19 -> 14783554 | J19: =G19+I19 -> 50204114
B20: =B19+0.01 -> 3.12 | C20: Acometida AC, incluyendo el contador y la certificación RETIE, dimensionada con una reserva en potencia del 20% para el Switch, una cámara etc. | D20: Un | E20: 28 | F20: 54408062 | G20: =E20*F20 -> 1523425736 | H20: 44766860 | I20: =E20*H20 -> 1.2534721e+09 | J20: =G20+I20 -> 2.7768978e+09
B21: =B20+0.01 -> 3.13 | C21: Caja para empalme de 8 puertos | D21: Un | E21: 28 | F21: 275560 | G21: =E21*F21 -> 7715680 | H21: 180620 | I21: =E21*H21 -> 5057360 | J21: =G21+I21 -> 12773040
... B27: =B26+0.01 -> 3.19 | C27: Cable de servicio de FO, 8 hilos y longitud promedio de 30 m, con características de calidad iguales o mejores a las del microducto de la troncal. | D27: Un | E27: 28 | F27: 149435 | G27: =E27*F27 -> 4184180 | H27: 138607.72 | I27: =E27*H27 -> 3881016.1 | J27: =G27+I27 -> 8065196.1
B28: =B29+0.01 -> 3.21 | C28: Canalización y ducto Conduit de 1 y 1/2", entre la troncal de FO y el ITS, en longitud promedio de 30 m | D28: Un | E28: 28 | F28: 263833 | G28: =E28*F28 -> 7387324 | H28: 2265263.4 | I28: =E28*H28 -> 63427375 | J28: =G28+I28 -> 70814699
B29: =B27+0.01 -> 3.2 | C29: Fusiones | D29: Un | E29: 336 | F29: 7441 | G29: =E29*F29 -> 2500176 | H29: 45514 | I29: =E29*H29 -> 15292704 | J29: =G29+I29 -> 17792880
B30: =B28+0.01 -> 3.22 | C30: Señalización de los postes y estructuras según Manual de Señalización vigente. | D30: Gbl | E30: 28 | F30: 319476.85 | G30: =E30*F30 -> 8945351.9 | H30: 688534 | I30: =E30*H30 -> 19278952 | J30: =G30+I30 -> 28224304
B31: =B30+0.01 -> 3.23 | C31: Material de montaje | D31: Gbl | E31: 28 | F31: 2977793.9 | G31: =E31*F31 -> 83378229 | I31: =E31*H31 -> 0 | J31: =G31+I31 -> 83378229
B32: =B31+0.01 -> 3.24 | C32: Capacitación | D32: Gbl | E32: 1 | F32: 9000000 | G32: =E32*F32 -> 9000000 | I32: =E32*H32 -> 0 | J32: =G32+I32 -> 9000000
B33: =B32+0.01 -> 3.25 | C33: Retiro y disposición adecuada de las estructuras metálicas y/o de concreto del PMV existente, dispuestos en sitios apropiados y con certificación en ZODME. | D33: Un | E33: 1 | G33: =E33*F33 -> 0 | H33: 10350000 | I33: =E33*H33 -> 10350000 | J33: =G33+I33 -> 10350000
H35: TOTAL COSTOS DIRECTOS | J35: =SUM(J9:J33) -> 1.0900278e+10
F36: ADMINISTRACION (A) | I36: 0.22 | J36: =J35*I36 -> 2.3980611e+09
F37: IMPREVISTOS (I) | I37: 0.04 | J37: =J35*I37 -> 4.3601111e+08
F38: UTILIDAD (U) | I38: 0.04 | J38: =J35*I38 -> 4.3601111e+08
F39: SUBTOTAL COSTOS DIRECTOS + AIU
F40: IVA SOBRE LA UTILIDAD 19% | I40: 0.19 | J40: =J38*I40 -> 82842112
H42: TOTAL COSTO DIRECTO+AIU + IVA | J42: =SUM(J35:J40) -> 1.4253203e+10

Sheet GALIBO
B2: PROYECTO TRONCAL MAGDALENA 1
B3: TABLA DE CANTIDADES | D3: PRESUPUESTO WUXY
B4: UNIDADES FUNCIONALES TOTAL 0 - 13
B6: ítem | C6: ITS | D6: Unidad | E6: Cantidad | F6: SUMINISTRO | H6: INSTALACIÓN PUESTA EN FUNCIONAMIENTO Y PRUEBAS | J6: COSTO TOTAL
B7: 4 | C7: SISTEMA DE CONTROL DE ALTURA | F7: Costo unitario | G7: Total suministro | H7: Costo unitario | I7: Total Instalación | J7: TOTAL
E8: TOTAL | F8: Col $ | G8: Col $ | H8: Col $ | I8: Col $ | J8: Col $
B9: =B7+0.01 -> 4.01 | C9: Fotocélulas Emisor Receptor Doble 2X | D9: Un | E9: 8 | F9: 8786361 | G9: =E9*F9 -> 70290888 | I9: =E9*H9 -> 0 | J9: =G9+I9 -> 70290888
B10: =B9+0.01 -> 4.02 | C10: Gabinete de control, protección IP65 sin ingreso de agua, el tamaño se ajustará dependiendo de los equipos a instalar y demás condiciones técnicas, con equipo de control, PLC, tablero eléctrico, protecciones eléctricas, (Termomagnéticas y sobretensión) incluye switch de puerta abierta, con accesorios de fijación y montaje | D10: Un | E10: 8 | F10: 24952697 | G10: =E10*F10 -> 1.9962158e+08 | H10: 866300.96 | I10: =E10*H10 -> 6930407.7 | J10: =G10+I10 -> 2.0655199e+08
B11: =B10+0.01 -> 4.03 | C11: Suministro e instalación de juego de espiras inductivas en pavimento incluye corte sobre pavimento, herramientas, materiales, equipo, mano de obra, restauración de cualquier estructura afectada como corona, cunetas entre otras, limpieza, remoción de escombros hasta el sitio de desechos, todo según especificaciones técnicas. | D11: Un | E11: 8 | F11: 5257300 | G11: =E11*F11 -> 42058400 | H11: 610077.94 | I11: =E11*H11 -> 4880623.6 | J11: =G11+I11 -> 46939024
B12: =B11+0.01 -> 4.04 | C12: Poste octogonal de 6 metros en acero galvanizado para gálibo electrónico 2X | D12: Un | E12: 8 | F12: 5288081.8 | G12: =E12*F12 -> 42304655 | H12: 2487278.3 | I12: =E12*H12 -> 19898227 | J12: =G12+I12 -> 62202881
B13: =B12+0.01 -> 4.05 | C13: Cimentación para las columnas del gálibo electrónico 2X | D13: Un | E13: 8 | G13: =E13*F13 -> 0 | H13: 3609587.7 | I13: =E13*H13 -> 28876701 | J13: =G13+I13 -> 28876701
B14: =B13+0.01 -> 4.06 | C14: Juego de cámara de evidencias más cámara de identificación de placas, Incluye el software | D14: Un | E14: 8 | F14: 35374700 | G14: =E14*F14 -> 282997600 | I14: =E14*H14 -> 0 | J14: =G14+I14 -> 282997600
B15: =B14+0.01 -> 4.07 | C15: Poste octogonal de 6 metros en acero galvanizado para cámara de evidencias más cámara de identificación de placas | D15: Un | E15: 8 | F15: 5288081.8 | G15: =E15*F15 -> 42304655 | H15: 2487278.3 | I15: =E15*H15 -> 19898227 | J15: =G15+I15 -> 62202881
B16: =B15+0.01 -> 4.08 | C16: Cimentación para el poste de cámara de evidencias más cámara de identificación de placas | D16: Un | E16: 8 | G16: =E16*F16 -> 0 | H16: 3609587.7 | I16: =E16*H16 -> 28876701 | J16: =G16+I16 -> 28876701
B17: =B16+0.01 -> 4.09 | C17: PMV señal exceso de altura (Señal oculta) | D17: Un | E17: 8 | F17: 42967431 | G17: =E17*F17 -> 3.4373945e+08 | H17: 1443835.3 | I17: =E17*H17 -> 11550682 | J17: =G17+I17 -> 3.5529013e+08
B18: =B17+0.01 -> 4.1 | C18: Estructura metálica tipo horquilla para PMV (Señal oculta) | D18: Un | E18: 8 | F18: 5451449.7 | G18: =E18*F18 -> 43611598 | H18: 1815945.6 | I18: =E18*H18 -> 14527565 | J18: =G18+I18 -> 58139162
B19: =B18+0.01 -> 4.11 | C19: Cimentación PMV (Señal oculta) | D19: Un | E19: 8 | G19: =E19*F19 -> 0 | H19: 3609587.7 | I19: =E19*H19 -> 28876701 | J19: =G19+I19 -> 28876701
B20: =B19+0.01 -> 4.12 | C20: Estructura metálica tipo pórtico - Galibo mecánico, con cadenas | D20: Un | E20: 8 | F20: 40904016 | G20: =E20*F20 -> 3.2723213e+08 | H20: 6169262.5 | I20: =E20*H20 -> 49354100 | J20: =G20+I20 -> 3.7658623e+08
B21: =B20+0.01 -> 4.13 | C21: Cimentación estructura tipo pórtico, incluye análisis de suelos 2X | D21: Un | E21: 8 | F21: 1265020 | G21: =E21*F21 -> 10120160 | H21: 32378602 | I21: =E21*H21 -> 2.5902882e+08 | J21: =G21+I21 -> 2.6914898e+08
B22: =B21+0.01 -> 4.14 | C22: Canalización entre señal oculta y gálibo electrónico aprox 80m | D22: Un | E22: 8 | F22: 1675618.1 | G22: =E22*F22 -> 13404945 | H22: 8250499.4 | I22: =E22*H22 -> 66003995 | J22: =G22+I22 -> 79408940
B23: =B22+0.01 -> 4.15 | C23: Cableado de energía y ducto de 1 y 1/2" hasta la señal oculta 90m aprox | D23: Un | E23: 8 | F23: 1177395.3 | G23: =E23*F23 -> 9419162.4 | H23: 454842.72 | I23: =E23*H23 -> 3638741.8 | J23: =G23+I23 -> 13057904
B24: =B23+0.01 -> 4.16 | C24: Cableado UTP Cat 6 y ducto de 1 y 1/2" hasta la señal oculta 90m aprox | D24: Un | E24: 8 | F24: 536279.04 | G24: =E24*F24 -> 4290232.3 | H24: 4476.26 | I24: =E24*H24 -> 35810.08 | J24: =G24+I24 -> 4326042.4
B25: =B24+0.01 -> 4.17 | C25: Paneles solares, indicar capacidad * | D25: Un | E25: 8 | F25: 29114139 | G25: =E25*F25 -> 232913112 | H25: 4388231.8 | I25: =E25*H25 -> 35105854 | J25: =G25+I25 -> 2.6801897e+08
B26: =B25+0.01 -> 4.18 | C26: Soporte metálico para paneles solares | D26: Un | E26: 8 | G26: =E26*F26 -> 0 | I26: =E26*H26 -> 0 | J26: =G26+I26 -> 0
B27: =B26+0.01 -> 4.19 | C27: Baterías, indicar capacidad para autonomía de 48 horas | D27: Un | E27: 8 | G27: =E27*F27 -> 0 | I27: =E27*H27 -> 0 | J27: =G27+I27 -> 0
B28: =B27+0.01 -> 4.2 | C28: Controlador para panel solar | D28: Un | E28: 8 | G28: =E28*F28 -> 0 | I28: =E28*H28 -> 0 | J28: =G28+I28 -> 0
B29: =B28+0.01 -> 4.21 | C29: Puesta a tierra (Incluye varilla(s), caja de inspección, Soldadura, tratamiento de suelo y medida) | D29: Un | E29: 8 | F29: 4832728 | G29: =E29*F29 -> 38661824 | H29: 2682921.9 | I29: =E29*H29 -> 21463375 | J29: =G29+I29 -> 60125199
B30: =B29+0.01 -> 4.22 | C30: Señalización de los postes y estructuras según Manual de Señalización vigente. | D30: Gbl | E30: 8 | F30: 638953.71 | G30: =E30*F30 -> 5111629.7 | H30: 1377068 | I30: =E30*H30 -> 11016544 | J30: =G30+I30 -> 16128174
B31: =B30+0.01 -> 4.23 | C31: Caja para empalme de 8 puertos | D31: Un | E31: 8 | F31: 275560 | G31: =E31*F31 -> 2204480 | H31: 180620 | I31: =E31*H31 -> 1444960 | J31: =G31+I31 -> 3649440
B32: =B31+0.01 -> 4.24 | C32: Patch Cord fibra óptica mono modo lc - lc | D32: Un | E32: 16 | F32: 31385 | G32: =E32*F32 -> 502160 | H32: 31603.894 | I32: =E32*H32 -> 505662.31 | J32: =G32+I32 -> 1007822.3
B33: =B32+0.01 -> 4.25 | C33: Caja de empalme tipo botella (mufla) para F.O de 48 hilos con cierre térmico para uso subterráneo. | D33: Un | E33: 8 | F33: 192904 | G33: =E33*F33 -> 1543232 | H33: 170263 | I33: =E33*H33 -> 1362104 | J33: =G33+I33 -> 2905336
B34: =B33+0.01 -> 4.26 | C34: Cajas para la Red Troncal, de paso o derivación, de 80X80X80, dimensiones internas | D34: Un | E34: 16 | F34: 962106 | G34: =E34*F34 -> 15393696 | H34: 817672.2 | I34: =E34*H34 -> 13082755 | J34: =G34+I34 -> 28476451
B35: =B34+0.01 -> 4.27 | C35: Caja de reserva para micro cable de Fibra Óptica | D35: Un | E35: 8 | F35: 455761 | G35: =E35*F35 -> 3646088 | H35: 97455 | I35: =E35*H35 -> 779640 | J35: =G35+I35 -> 4425728
B36: =B35+0.01 -> 4.28 | C36: Pig Tail | D36: Un | E36: 32 | F36: 7418.4565 | G36: =E36*F36 -> 237390.61 | H36: 2017.5034 | I36: =E36*H36 -> 64560.109 | J36: =G36+I36 -> 301950.72
B37: =B36+0.01 -> 4.29 | C37: Cable de servicio de FO, 8 hilos y longitud promedio de 30 m, con características de calidad iguales o mejores a las del microducto de la troncal. | D37: Un | E37: 8 | F37: 149435 | G37: =E37*F37 -> 1195480 | H37: 138607.72 | I37: =E37*H37 -> 1108861.7 | J37: =G37+I37 -> 2304341.7
B38: =B39+0.01 -> 4.31 | C38: Canalización y ducto Conduit de 1 y 1/2", entre la troncal de FO y el ITS, en longitud promedio de 30 m | D38: Un | E38: 8 | F38: 263833 | G38: =E38*F38 -> 2110664 | H38: 2265263.4 | I38: =E38*H38 -> 18122107 | J38: =G38+I38 -> 20232771
B39: =B37+0.01 -> 4.3 | C39: Fusiones | D39: Un | E39: 96 | F39: 7441 | G39: =E39*F39 -> 714336 | H39: 45514 | I39: =E39*H39 -> 4369344 | J39: =G39+I39 -> 5083680
B40: =B38+0.01 -> 4.32 | C40: Material de montaje | D40: Gbl | E40: 8 | F40: 2977793.9 | G40: =E40*F40 -> 23822351 | I40: =E40*H40 -> 0 | J40: =G40+I40 -> 23822351
B41: =B40+0.01 -> 4.33 | C41: Capacitación | D41: Gbl | E41: 1 | F41: 9000000 | G41: =E41*F41 -> 9000000 | I41: =E41*H41 -> 0 | J41: =G41+I41 -> 9000000
H43: TOTAL COSTOS DIRECTOS | J43: =SUM(J9:J41) -> 2.419255e+09
F44: ADMINISTRACION (A) | I44: 0.22 | J44: =J43*I44 -> 5.3223609e+08
F45: IMPREVISTOS (I) | I45: 0.04 | J45: =J43*I45 -> 96770199
F46: UTILIDAD (U) | I46: 0.04 | J46: =J43*I46 -> 96770199
F47: SUBTOTAL COSTOS DIRECTOS + AIU
F48: IVA SOBRE LA UTILIDAD 19% | I48: 0.19 | J48: =J46*I48 -> 18386338
H50: TOTAL COSTO DIRECTO+AIU + IVA | J50: =SUM(J43:J48) -> 3.1634178e+09
B52: * | C52: El presupuesto de la solución solar incluye la totalidad de la solución

Sheet ETD
B2: PROYECTO TRONCAL MAGDALENA 1
B3: TABLA DE CANTIDADES | D3: PRESUPUESTO WUXY
B4: UNIDADES FUNCIONALES TOTAL 0 - 13
B6: ítem | C6: ITS | D6: Unidad | E6: Cantidad | F6: SUMINISTRO | H6: INSTALACIÓN PUESTA EN FUNCIONAMIENTO Y PRUEBAS | J6: COSTO TOTAL
B7: 5 | C7: ESTACIÓN TOMA DE DATOS | F7: Costo unitario | G7: Total suministro | H7: Costo unitario | I7: Total Instalación | J7: TOTAL
E8: TOTAL | F8: Col $ | G8: Col $ | H8: Col $ | I8: Col $ | J8: Col $
B9: =B7+0.01 -> 5.01 | C9: Controlador Estación de Toma de Datos ETD | D9: Un | E9: 12 | F9: 53600002 | G9: =E9*F9 -> 6.4320003e+08 | H9: 3619694.2 | I9: =E9*H9 -> 43436331 | J9: =G9+I9 -> 6.8663636e+08
B10: =B9+0.01 -> 5.02 | C10: Gabinete de control, protección IP65 sin ingreso de agua, el tamaño se ajustará dependiendo de los equipos a instalar y demás condiciones técnicas, con tablero eléctrico, protecciones eléctricas, (Termomagnéticas y sobretensión) incluye switch de puerta abierta, con accesorios de fijación y montaje | D10: Un | E10: 12 | F10: 6934396.5 | G10: =E10*F10 -> 83212758 | H10: 866300.96 | I10: =E10*H10 -> 10395612 | J10: =G10+I10 -> 93608370
B11: =B10+0.01 -> 5.03 | C11: Cámara para analítica de video, con su soporte | D11: Un | E11: 12 | F11: 35374700 | G11: =E11*F11 -> 424496400 | I11: =E11*H11 -> 0 | J11: =G11+I11 -> 424496400
B12: =B11+0.01 -> 5.04 | C12: Paneles solares, indicar capacidad * | D12: Un | E12: 12 | F12: 9704713 | G12: =E12*F12 -> 116456556 | H12: 1462743.9 | I12: =E12*H12 -> 17552927 | J12: =G12+I12 -> 1.3400948e+08
B13: =B12+0.01 -> 5.05 | C13: Soporte metálico para paneles solares | D13: Un | E13: 12 | G13: =E13*F13 -> 0 | I13: =E13*H13 -> 0 | J13: =G13+I13 -> 0
B14: =B13+0.01 -> 5.06 | C14: Baterías, indicar capacidad para autonomía de 48 horas | D14: Un | E14: 12 | G14: =E14*F14 -> 0 | I14: =E14*H14 -> 0 | J14: =G14+I14 -> 0
B15: =B14+0.01 -> 5.07 | C15: Controlador para panel solar | D15: Un | E15: 12 | G15: =E15*F15 -> 0 | I15: =E15*H15 -> 0 | J15: =G15+I15 -> 0
B16: =B15+0.01 -> 5.08 | C16: Poste en concreto 14 m | D16: Un | E16: 12 | F16: 2999598 | G16: =E16*F16 -> 35995176 | H16: 680994.05 | I16: =E16*H16 -> 8171928.6 | J16: =G16+I16 -> 44167105
B17: =B16+0.01 -> 5.09 | C17: Corona antiescalatoria | D17: Un | E17: 12 | F17: 737969.81 | G17: =E17*F17 -> 8855637.7 | H17: 225338.4 | I17: =E17*H17 -> 2704060.8 | J17: =G17+I17 -> 11559699
B18: =B17+0.01 -> 5.1 | C18: Cableado Energía | D18: Un | E18: 12 | F18: 812392.94 | G18: =E18*F18 -> 9748715.2 | H18: 328466.1 | I18: =E18*H18 -> 3941593.2 | J18: =G18+I18 -> 13690308
B19: =B18+0.01 -> 5.11 | C19: Cableado Control | D19: Un | E19: 12 | F19: 389948.61 | G19: =E19*F19 -> 4679383.3 | H19: 310191.81 | I19: =E19*H19 -> 3722301.7 | J19: =G19+I19 -> 8401685
B20: =B19+0.01 -> 5.12 | C20: Cable UTP Cat 6 Datos | D20: Un | E20: 12 | F20: 1624785.9 | G20: =E20*F20 -> 19497430 | H20: 1634674.4 | I20: =E20*H20 -> 19616093 | J20: =G20+I20 -> 39113524
B21: =B20+0.01 -> 5.13 | C21: Puesta a tierra (Incluye varilla(s), caja de inspección, Soldadura, tratamiento de suelo y medida) | D21: Un | E21: 12 | F21: 4486477.7 | G21: =E21*F21 -> 53837733 | H21: 3914826.5 | I21: =E21*H21 -> 46977918 | J21: =G21+I21 -> 1.0081565e+08
B22: =B21+0.01 -> 5.14 | C22: Señalización del poste según Manual de Señalización vigente | D22: Gbl | E22: 12 | F22: 319476.85 | G22: =E22*F22 -> 3833722.2 | H22: 688534 | I22: =E22*H22 -> 8262408 | J22: =G22+I22 -> 12096130
B23: =B22+0.01 -> 5.15 | C23: Caja para empalme de 8 puertos | D23: Un | E23: 12 | F23: 275560 | G23: =E23*F23 -> 3306720 | H23: 180620 | I23: =E23*H23 -> 2167440 | J23: =G23+I23 -> 5474160
B24: =B23+0.01 -> 5.16 | C24: Patch Cord fibra óptica mono modo lc - lc | D24: Un | E24: 12 | F24: 31385 | G24: =E24*F24 -> 376620 | H24: 31603.894 | I24: =E24*H24 -> 379246.73 | J24: =G24+I24 -> 755866.73
B25: =B24+0.01 -> 5.17 | C25: Caja de empalme tipo botella (mufla) para F.O de 48 hilos con cierre térmico para uso subterráneo. | D25: Un | E25: 12 | F25: 192904 | G25: =E25*F25 -> 2314848 | H25: 170263 | I25: =E25*H25 -> 2043156 | J25: =G25+I25 -> 4358004
B26: =B25+0.01 -> 5.18 | C26: Cajas para la Red Troncal, de paso o derivación, de 80X80X80, dimensiones internas | D26: Un | E26: 24 | F26: 962106 | G26: =E26*F26 -> 23090544 | H26: 817672.2 | I26: =E26*H26 -> 19624133 | J26: =G26+I26 -> 42714677
B27: =B26+0.01 -> 5.19 | C27: Caja de reserva para micro cable de Fibra Óptica | D27: Un | E27: 12 | F27: 455761 | G27: =E27*F27 -> 5469132 | H27: 97455 | I27: =E27*H27 -> 1169460 | J27: =G27+I27 -> 6638592
... B29: =B28+0.01 -> 5.21 | C29: Cable de servicio de FO, 8 hilos y longitud promedio de 40 m, con características de calidad iguales o mejores a las del microducto de la troncal. | D29: Un | E29: 12 | F29: 149435 | G29: =E29*F29 -> 1793220 | H29: 138607.72 | I29: =E29*H29 -> 1663292.6 | J29: =G29+I29 -> 3456512.6
B30: =B31+0.01 -> 5.23 | C30: Canalización y ducto Conduit de 1 y 1/2", entre la troncal de FO y el ITS, en longitud promedio de 30 m | D30: Un | E30: 12 | F30: 263833 | G30: =E30*F30 -> 3165996 | H30: 2265263.4 | I30: =E30*H30 -> 27183161 | J30: =G30+I30 -> 30349157
B31: =B29+0.01 -> 5.22 | C31: Fusiones | D31: Un | E31: 144 | F31: 7441 | G31: =E31*F31 -> 1071504 | H31: 45514 | I31: =E31*H31 -> 6554016 | J31: =G31+I31 -> 7625520
B32: =B30+0.01 -> 5.24 | C32: Pequeño material de montaje | D32: Gbl | E32: 12 | F32: 2977793.9 | G32: =E32*F32 -> 35733527 | I32: =E32*H32 -> 0 | J32: =G32+I32 -> 35733527
B33: =B32+0.01 -> 5.25 | C33: Capacitación | D33: Gbl | E33: 1 | F33: 9000000 | G33: =E33*F33 -> 9000000 | I33: =E33*H33 -> 0 | J33: =G33+I33 -> 9000000
H35: TOTAL COSTOS DIRECTOS | J35: =SUM(J9:J33) -> 1.7151537e+09
F36: ADMINISTRACION (A) | I36: 0.22 | J36: =J35*I36 -> 3.773338e+08
F37: IMPREVISTOS (I) | I37: 0.04 | J37: =J35*I37 -> 68606146
F38: UTILIDAD (U) | I38: 0.04 | J38: =J35*I38 -> 68606146
F39: SUBTOTAL COSTOS DIRECTOS + AIU
F40: IVA SOBRE LA UTILIDAD 19% | I40: 0.19 | J40: =J38*I40 -> 13035168
H42: TOTAL COSTO DIRECTO+AIU + IVA | J42: =SUM(J35:J40) -> 2.2427349e+09
B44: * | C44: El presupuesto de la solución solar incluye la totalidad de la solución

Sheet CCTV
B2: PROYECTO TRONCAL MAGDALENA 1
B3: TABLA DE CANTIDADES | D3: PRESUPUESTO WUXY
B4: UNIDADES FUNCIONALES TOTAL 0 - 13
B6: ítem | C6: ITS | D6: Unidad | E6: Cantidad | F6: SUMINISTRO | H6: INSTALACIÓN PUESTA EN FUNCIONAMIENTO Y PRUEBAS | J6: COSTO TOTAL
B7: 6 | C7: SISTEMA DE CCTV | F7: Costo unitario | G7: Total suministro | H7: Costo unitario | I7: Total Instalación | J7: TOTAL
E8: TOTAL | F8: Col $ | G8: Col $ | H8: Col $ | I8: Col $ | J8: Col $
B9: =B7+0.01 -> 6.01 | C9: Cámara PTZ Vía | D9: Un | E9: 30 | F9: 5251452 | G9: =E9*F9 -> 157543560 | H9: 2682748.3 | I9: =E9*H9 -> 80482450 | J9: =G9+I9 -> 2.3802601e+08
B10: =B9+0.01 -> 6.02 | C10: Soporte poste cámara | D10: Un | E10: 30 | F10: 175410 | G10: =E10*F10 -> 5262300 | H10: 203136.99 | I10: =E10*H10 -> 6094109.8 | J10: =G10+I10 -> 11356410
B11: =B10+0.01 -> 6.03 | C11: Brazo extensión cámara | D11: Un | E11: 30 | F11: 549178 | G11: =E11*F11 -> 16475340 | H11: 219306.23 | I11: =E11*H11 -> 6579187 | J11: =G11+I11 -> 23054527
B12: =B11+0.01 -> 6.04 | C12: Postes concreto CCTV de 14 m | D12: Un | E12: 30 | F12: 2999598 | G12: =E12*F12 -> 89987940 | H12: 680994.05 | I12: =E12*H12 -> 20429822 | J12: =G12+I12 -> 1.1041776e+08
B13: =B12+0.01 -> 6.05 | C13: Corona antiescalatoria | D13: Un | E13: 30 | F13: 737969.81 | G13: =E13*F13 -> 22139094 | H13: 225338.4 | I13: =E13*H13 -> 6760152 | J13: =G13+I13 -> 28899246
B14: =B13+0.01 -> 6.06 | C14: Paneles solares, indicar capacidad * | D14: Un | E14: 30 | F14: 9704713 | G14: =E14*F14 -> 291141390 | H14: 1462743.9 | I14: =E14*H14 -> 43882318 | J14: =G14+I14 -> 3.3502371e+08
B15: =B14+0.01 -> 6.07 | C15: Soporte metálico para paneles solares | D15: Un | E15: 30 | G15: =E15*F15 -> 0 | I15: =E15*H15 -> 0 | J15: =G15+I15 -> 0
B16: =B15+0.01 -> 6.08 | C16: Baterías, indicar capacidad para autonomía de 48 horas | D16: Un | E16: 30 | G16: =E16*F16 -> 0 | I16: =E16*H16 -> 0 | J16: =G16+I16 -> 0
B17: =B16+0.01 -> 6.09 | C17: Controlador para panel solar | D17: Un | E17: 30 | G17: =E17*F17 -> 0 | I17: =E17*H17 -> 0 | J17: =G17+I17 -> 0
B18: =B17+0.01 -> 6.1 | C18: Gabinete de control, protección IP65 sin ingreso de agua, el tamaño se ajustará dependiendo de los equipos a instalar y demás condiciones técnicas, con tablero eléctrico, protecciones eléctricas, (Termomagnéticas y sobretensión) incluye switch de puerta abierta, con accesorios de fijación y montaje | D18: Un | E18: 30 | F18: 9121928 | G18: =E18*F18 -> 273657840 | H18: 2798928.7 | I18: =E18*H18 -> 83967861 | J18: =G18+I18 -> 3.576257e+08
B19: =B18+0.01 -> 6.11 | C19: Cableado 3x12 Energía 3 m | D19: Un | E19: 30 | F19: 812392.94 | G19: =E19*F19 -> 24371788 | H19: 328466.1 | I19: =E19*H19 -> 9853983 | J19: =G19+I19 -> 34225771
B20: =B19+0.01 -> 6.12 | C20: Cableado 5x16 Control 3 m | D20: Un | E20: 30 | F20: 389948.61 | G20: =E20*F20 -> 11698458 | H20: 310191.81 | I20: =E20*H20 -> 9305754.3 | J20: =G20+I20 -> 21004213
B21: =B20+0.01 -> 6.13 | C21: Cable UTP Cat 6 Datos | D21: Un | E21: 30 | F21: 1624785.9 | G21: =E21*F21 -> 48743576 | H21: 1634674.4 | I21: =E21*H21 -> 49040233 | J21: =G21+I21 -> 97783810
B22: =B21+0.01 -> 6.14 | C22: Puesta a tierra (Incluye varilla(s), caja de inspección, Soldadura, tratamiento de suelo y medida) | D22: Un | E22: 30 | F22: 4486477.7 | G22: =E22*F22 -> 1.3459433e+08 | H22: 3914826.5 | I22: =E22*H22 -> 1.174448e+08 | J22: =G22+I22 -> 2.5203913e+08
B23: =B22+0.01 -> 6.15 | C23: Señalización del poste según Manual de Señalización vigente | D23: Un | E23: 30 | F23: 319476.85 | G23: =E23*F23 -> 9584305.6 | H23: 688534 | I23: =E23*H23 -> 20656020 | J23: =G23+I23 -> 30240326
B24: =B23+0.01 -> 6.16 | C24: Caja para empalme de 8 puertos | D24: Un | E24: 30 | F24: 275560 | G24: =E24*F24 -> 8266800 | H24: 180620 | I24: =E24*H24 -> 5418600 | J24: =G24+I24 -> 13685400
B25: =B24+0.01 -> 6.17 | C25: Patch Cord fibra óptica mono modo lc - lc | D25: Un | E25: 60 | F25: 31385 | G25: =E25*F25 -> 1883100 | H25: 31603.894 | I25: =E25*H25 -> 1896233.7 | J25: =G25+I25 -> 3779333.7
B26: =B25+0.01 -> 6.18 | C26: Caja de empalme tipo botella (mufla) para F.O de 48 hilos con cierre térmico para uso subterráneo. | D26: Un | E26: 30 | F26: 192904 | G26: =E26*F26 -> 5787120 | H26: 170263 | I26: =E26*H26 -> 5107890 | J26: =G26+I26 -> 10895010
B27: =B26+0.01 -> 6.19 | C27: Cajas para la Red Troncal, de paso o derivación, de 80X80X80, dimensiones internas | D27: Un | E27: 60 | F27: 962106 | G27: =E27*F27 -> 57726360 | H27: 817672.2 | I27: =E27*H27 -> 49060332 | J27: =G27+I27 -> 1.0678669e+08
B28: =B27+0.01 -> 6.2 | C28: Caja de reserva para micro cable de Fibra Óptica | D28: Un | E28: 30 | F28: 455761 | G28: =E28*F28 -> 13672830 | H28: 97455 | I28: =E28*H28 -> 2923650 | J28: =G28+I28 -> 16596480
B29: =B28+0.01 -> 6.21 | C29: Pig Tail | D29: Un | E29: 120 | F29: 7418.4565 | G29: =E29*F29 -> 890214.78 | H29: 2017.5034 | I29: =E29*H29 -> 242100.41 | J29: =G29+I29 -> 1132315.2
... B31: =B30+0.01 -> 6.23 | C31: Canalización y ducto Conduit de 1 y 1/2", entre la troncal de FO y el ITS, en longitud promedio de 30 m | D31: Un | E31: 30 | F31: 263833 | G31: =E31*F31 -> 7914990 | H31: 2265263.4 | I31: =E31*H31 -> 67957902 | J31: =G31+I31 -> 75872892
C32: Fusiones | D32: Un | E32: 360 | F32: 7441 | G32: =E32*F32 -> 2678760 | H32: 45514 | I32: =E32*H32 -> 16385040 | J32: =G32+I32 -> 19063800
B33: =B31+0.01 -> 6.24 | C33: Material de montaje | D33: Gbl | E33: 30 | F33: 2977793.9 | G33: =E33*F33 -> 89333817 | I33: =E33*H33 -> 0 | J33: =G33+I33 -> 89333817
B34: =B33+0.01 -> 6.25 | C34: Capacitación | D34: Gbl | E34: 1 | F34: 9000000 | G34: =E34*F34 -> 9000000 | I34: =E34*H34 -> 0 | J34: =G34+I34 -> 9000000
H36: TOTAL COSTOS DIRECTOS | J36: =SUM(J9:J34) -> 1.8944836e+09
F37: ADMINISTRACION (A) | I37: 0.22 | J37: =J36*I37 -> 4.167864e+08
F38: IMPREVISTOS (I) | I38: 0.04 | J38: =J36*I38 -> 75779345
F39: UTILIDAD (U) | I39: 0.04 | J39: =J36*I39 -> 75779345
F40: SUBTOTAL COSTOS DIRECTOS + AIU
F41: IVA SOBRE LA UTILIDAD 19% | I41: 0.19 | J41: =J39*I41 -> 14398076
H43: TOTAL COSTO DIRECTO+AIU + IVA | J43: =SUM(J36:J41) -> 2.4772268e+09
B45: * | C45: El presupuesto de la solución solar incluye la totalidad de la solución

Sheet FO COMUNICACION
B2: PROYECTO TRONCAL MAGDALENA 1
B3: TABLA DE CANTIDADES | D3: PRESUPUESTO WUXY
B4: UNIDADES FUNCIONALES TOTAL 0 - 13
B6: ítem | C6: ITS | D6: Unidad | E6: Cantidad | F6: SUMINISTRO | H6: INSTALACIÓN PUESTA EN FUNCIONAMIENTO Y PRUEBAS | J6: COSTO TOTAL
B7: 7 | C7: FIBRA OPTICA Y COMUNICACIONES | F7: Costo unitario | G7: Total suministro | H7: Costo unitario | I7: Total Instalación | J7: TOTAL
E8: TOTAL | F8: Col $ | G8: Col $ | H8: Col $ | I8: Col $ | J8: Col $
B9: =B7+0.01 -> 7.01 | C9: Switch Nivel 2 para comunicación, 8 puertos 10/100/1000 Base-T Rj45 cobre y puertos 100/1000 Base-X SFP slot, SFP auto detección | D9: Un | E9: 183 | F9: 1700201 | G9: =E9*F9 -> 311136783 | H9: 442619 | I9: =E9*H9 -> 80999277 | J9: =G9+I9 -> 392136060
B10: =B9+0.01 -> 7.02 | C10: Dispositivos de red de CCO, Switches de capa 3 | D10: Un | E10: 2 | F10: 5158994 | G10: =E10*F10 -> 10317988 | H10: 570804 | I10: =E10*H10 -> 1141608 | J10: =G10+I10 -> 11459596
B11: =B10+0.01 -> 7.03 | C11: Dispositivos de red CORE, Switches de capa 3 | D11: Un | E11: 2 | F11: 5158994 | G11: =E11*F11 -> 10317988 | H11: 570804 | I11: =E11*H11 -> 1141608 | J11: =G11+I11 -> 11459596
B12: =B11+0.01 -> 7.04 | C12: Conversores de medio | D12: Un | E12: 6 | F12: 396921 | G12: =E12*F12 -> 2381526 | H12: 240504 | I12: =E12*H12 -> 1443024 | J12: =G12+I12 -> 3824550
B13: =B12+0.01 -> 7.05 | C13: Transceiver SFP Fibra Óptica 10 Km 1G, con conector LC. | D13: Un | E13: 366 | F13: 121768 | G13: =E13*F13 -> 44567088 | H13: 23134 | I13: =E13*H13 -> 8467044 | J13: =G13+I13 -> 53034132
B14: =B13+0.01 -> 7.06 | C14: Transceiver SFP Fibra Óptica 10 Km 10G, con conector LC. | D14: Un | E14: 8 | F14: 385359 | G14: =E14*F14 -> 3082872 | H14: =15653+17853 -> 33506 | I14: =E14*H14 -> 268048 | J14: =G14+I14 -> 3350920
B15: =B14+0.01 -> 7.07 | C15: Transceiver SFP Fibra Óptica max 80 Km 10G, co conector LC. | D15: Un | E15: 8 | F15: 2443775 | G15: =E15*F15 -> 19550200 | H15: 132081 | I15: =E15*H15 -> 1056648 | J15: =G15+I15 -> 20606848
B16: =B15+0.01 -> 7.08 | C16: Transceiver SFP Fibra Óptica 10 Km 10G, con conector LC. | D16: Un | E16: 1 | F16: 408153 | G16: =E16*F16 -> 408153 | I16: =E16*H16 -> 0 | J16: =G16+I16 -> 408153
B17: =B16+0.01 -> 7.09 | C17: Ingeniería de integración…. Gbl | D17: Un | E17: 1 | G17: =E17*F17 -> 0 | H17: 114597000 | I17: =E17*H17 -> 114597000 | J17: =G17+I17 -> 114597000
B18: =B17+0.01 -> 7.1 | C18: Software licenciado para gestión de la red de datos | D18: Un | E18: 1 | F18: 25088477 | G18: =E18*F18 -> 25088477 | H18: 1330546 | I18: =E18*H18 -> 1330546 | J18: =G18+I18 -> 26419023
B19: =B18+0.01 -> 7.11 | C19: Estación de trabajo para el software de gestión | D19: Un | E19: 1 | F19: 21072438 | G19: =E19*F19 -> 21072438 | H19: 1330546 | I19: =E19*H19 -> 1330546 | J19: =G19+I19 -> 22402984
B20: =B19+0.01 -> 7.12 | C20: Suministro, instalación y puesta en marcha de micro cable de fibra óptica monomodo, de 48 hilos según las especificaciones, incluye la certificación. | D20: ml | E20: 291121.6 | F20: 2337 | G20: =E20*F20 -> 6.8035118e+08 | H20: 5271.572 | I20: =E20*H20 -> 1.5346685e+09 | J20: =G20+I20 -> 2.2150197e+09
B21: =B20+0.01 -> 7.13 | C21: Caja de paso (registro) de dimensiones 0.8 x 0.8 x 0.8 m (longitud x anchura x profundidad), dimensiones internas, para la red troncal de FO, para los pasos direccionados o para pasos especiales (puentes). | D21: Un | E21: 340.7244 | F21: 962106.06 | G21: =E21*F21 -> 3.2781301e+08 | H21: 817672.2 | I21: =E21*H21 -> 2.7860087e+08 | J21: =G21+I21 -> 6.0641388e+08
B22: =B21+0.01 -> 7.14 | C22: Caja de empalme tipo botella (mufla) para F.O de 48 hilos con cierre térmico para uso subterráneo. | D22: Un | E22: 219.6 | F22: 1540081.4 | G22: =E22*F22 -> 3.3820187e+08 | H22: 1634674.4 | I22: =E22*H22 -> 3.5897451e+08 | J22: =G22+I22 -> 6.9717638e+08
B23: =B22+0.01 -> 7.15 | C23: Caja de reserva para micro cable de Fibra Óptica | D23: Un | E23: 274.5 | F23: 455761 | G23: =E23*F23 -> 1.2510639e+08 | H23: 97311 | I23: =E23*H23 -> 26711870 | J23: =G23+I23 -> 151818264
B24: =B23+0.01 -> 7.16 | C24: Suministro de y colocación de ducto de PVC-TDP de 3" de diámetro para pasos direccionados incluye excavación de cualquier material y profundidad, relleno, herramientas, materiales, equipo, mano de obra, restauración de cualquier estructura afectadas como corona, cunetas entre otras, limpieza, remoción de escombros hasta el sitio de desechos, todo según especificaciones técnicas. | D24: ml | E24: 498 | F24: 77985 | G24: =E24*F24 -> 38836530 | H24: 473117.75 | I24: =E24*H24 -> 2.3561264e+08 | J24: =G24+I24 -> 2.7444917e+08
B25: =B24+0.01 -> 7.17 | C25: Suministro y colocación de Tritubos de Polietileno de alta densidad reforzado para instalaciones de comunicación troncal de fibra óptica en micro zanjado, microducto de 10/8mm de diámetro exterior e interior respectivamente, con interior prelubricado, incluye: conexiones, excavación de cualquier material y profundidad, relleno, herramientas, materiales, equipo, mano de obra, restauración de cualquier estructuras afectadas como corona, cunetas entre otras, limpieza, remoción de escombros hasta el sitio de desechos, todo según especificaciones técnicas. | D25: ml | E25: 280724.4 | F25: 9833 | G25: =E25*F25 -> 2.760363e+09 | H25: 25967 | I25: =E25*H25 -> 7.2895705e+09 | J25: =G25+I25 -> 10049933520
B26: =B25+0.01 -> 7.18 | C26: Certificación del microducto instalado | D26: ml | E26: 280724.4 | G26: =E26*F26 -> 0 | H26: 3500 | I26: =E26*H26 -> 9.825354e+08 | J26: =G26+I26 -> 9.825354e+08
B27: =B26+0.01 -> 7.19 | C27: Uniones | D27: Un | E27: 322.83306 | F27: 24801 | G27: =E27*F27 -> 8006582.7 | H27: 34377 | I27: =E27*H27 -> 11098032 | J27: =G27+I27 -> 19104615
B28: =B27+0.01 -> 7.2 | C28: Tapones | D28: Un | E28: 878.4 | F28: 13206 | G28: =E28*F28 -> 11600150 | H28: 8990 | I28: =E28*H28 -> 7896816 | J28: =G28+I28 -> 19496966
B29: =B28+0.01 -> 7.21 | C29: Cinta de advertencia (Rollo de longitud 300m) | D29: Un | E29: 935.748 | F29: 119655.6 | G29: =E29*F29 -> 1.1196749e+08 | H29: 17709.6 | I29: =E29*H29 -> 16571723 | J29: =G29+I29 -> 1.2853921e+08
B30: =B29+0.01 -> 7.22 | C30: Fusiones | D30: Un | E30: 9662.4 | F30: 7441 | G30: =E30*F30 -> 71897918 | H30: 45514 | I30: =E30*H30 -> 4.3977447e+08 | J30: =G30+I30 -> 5.1167239e+08
B31: =B30+0.01 -> 7.23 | C31: Capacitación | D31: Gbl | E31: 1 | F31: 9000000 | G31: =E31*F31 -> 9000000 | I31: =E31*H31 -> 0 | J31: =G31+I31 -> 9000000
H33: TOTAL COSTOS DIRECTOS | J33: =SUM(J9:J31) -> 1.6324858e+10
F34: ADMINISTRACION (A) | I34: 0.22 | J34: =J33*I34 -> 3.5914688e+09
F35: IMPREVISTOS (I) | I35: 0.04 | J35: =J33*I35 -> 6.5299433e+08
F36: UTILIDAD (U) | I36: 0.04 | J36: =J33*I36 -> 6.5299433e+08
F37: SUBTOTAL COSTOS DIRECTOS + AIU
F38: IVA SOBRE LA UTILIDAD 19% | I38: 0.19 | J38: =J36*I38 -> 1.2406892e+08
H40: TOTAL COSTO DIRECTO+AIU + IVA | J40: =SUM(J33:J38) -> 2.1346385e+10

Sheet PEAJE
B2: PROYECTO TRONCAL MAGDALENA 1
B3: TABLA DE CANTIDADES | D3: PRESUPUESTO WUXY
B4: UNIDADES FUNCIONALES 0 - 13
B6: ítem | C6: ITS | D6: Unidad | E6: Cantidad | F6: SUMINISTRO | H6: INSTALACIÓN PUESTA EN FUNCIONAMIENTO Y PRUEBAS | J6: COSTO TOTAL
B7: 8 | C7: PEAJE | F7: Costo unitario | G7: Total suministro | H7: Costo unitario | I7: Total Instalación | J7: TOTAL
F8: Col $ | G8: Col $ | H8: Col $ | I8: Col $ | J8: Col $
C9: Total Peajes | E9: 2
C10: Total de carriles | E10: =E9*7 -> 14
C11: Total vías Telepeaje | E11: 2
C12: Carriles reversibles | E12: =E9 -> 2
C13: EQUIPOS DE CARRIL
B14: =B7+0.01 -> 8.01 | C14: TABLERO DE CONTROL
B15: =B14+0.01 -> 8.02 | C15: Procesador core i5 | D15: Un | E15: 16 | F15: 20998146 | G15: =E15*F15 -> 335970336 | I15: =E15*H15 -> 0 | J15: =G15+I15 -> 335970336
B16: =B15+0.01 -> 8.03 | C16: Sistema de Entradas y salidas | D16: Un | E16: 16 | F16: 1528568 | G16: =E16*F16 -> 24457088 | I16: =E16*H16 -> 0 | J16: =G16+I16 -> 24457088
B17: =B16+0.01 -> 8.04 | C17: Detector de presencia 2 canales | D17: Un | E17: 16 | F17: 955090 | G17: =E17*F17 -> 15281440 | I17: =E17*H17 -> 0 | J17: =G17+I17 -> 15281440
B18: =B17+0.01 -> 8.05 | C18: EQUIPOS AL INTERIOR DE LA CABINA
B19: =B18+0.01 -> 8.06 | C19: Pantalla táctil de 15´, con tiempo de respuesta de 25 msec, 1280 a 60 Hz | D19: Un | E19: 16 | F19: 2493846 | G19: =E19*F19 -> 39901536 | I19: =E19*H19 -> 0 | J19: =G19+I19 -> 39901536
B20: =B19+0.01 -> 8.07 | C20: Impresora de puerto serial | D20: Un | E20: 16 | F20: 1412684 | G20: =E20*F20 -> 22602944 | I20: =E20*H20 -> 0 | J20: =G20+I20 -> 22602944
B21: =B20+0.01 -> 8.08 | C21: Cámaras de cabina, Domo de base metálica, protección IP66. Resolución 1920 X 1080 Pixeles | D21: Un | E21: 14 | F21: 811826 | G21: =E21*F21 -> 11365564 | I21: =E21*H21 -> 0 | J21: =G21+I21 -> 11365564
B22: =B21+0.01 -> 8.09 | C22: Lector de tarjeta sin contacto Mifare de Exentos y especiales | D22: Un | E22: 16 | F22: 2202013 | G22: =E22*F22 -> 35232208 | I22: =E22*H22 -> 0 | J22: =G22+I22 -> 35232208
B23: =B22+0.01 -> 8.1 | C23: Teléfono IP VoIP con POE | D23: Un | E23: 14 | F23: 265303 | G23: =E23*F23 -> 3714242 | I23: =E23*H23 -> 0 | J23: =G23+I23 -> 3714242
B24: =B23+0.01 -> 8.11 | C24: Cajón Monedero | D24: Un | E24: 16 | F24: 294781 | G24: =E24*F24 -> 4716496 | I24: =E24*H24 -> 0 | J24: =G24+I24 -> 4716496
B25: =B24+0.01 -> 8.12 | C25: EQUIPOS EXTERIOR CARRIL | G25: =E25*F25 -> 0 | I25: =E25*H25 -> 0 | J25: =G25+I25 -> 0
B26: =B25+0.01 -> 8.13 | C26: Peanas Trapezoidales | D26: Un | E26: 96 | F26: 3719544.8 | G26: =E26*F26 -> 3.570763e+08 | I26: =E26*H26 -> 0 | J26: =G26+I26 -> 3.570763e+08
B27: =B26+0.01 -> 8.14 | C27: Separador óptico de vehículos. Chasis de ópticos, puerta en vidrio para barrera emisora y barrera receptora. Incluye cableados. Para la salida. | D27: Un | E27: 16 | F27: 12914939 | G27: =E27*F27 -> 206639024 | I27: =E27*H27 -> 0 | J27: =G27+I27 -> 206639024
B28: =B27+0.01 -> 8.15 | C28: Talanquera de salida automática IP. Conjunto electromecánico, Operación fluida y silenciosa. Ancho de paso de 3 Mts, | D28: Un | E28: 16 | F28: 21208303 | G28: =E28*F28 -> 339332848 | I28: =E28*H28 -> 0 | J28: =G28+I28 -> 339332848
B29: =B28+0.01 -> 8.16 | C29: Foto celda reflectiva | D29: Un | E29: 16 | F29: 495000 | G29: =E29*F29 -> 7920000 | I29: =E29*H29 -> 0 | J29: =G29+I29 -> 7920000
B30: =B29+0.01 -> 8.17 | C30: Semáforo rojo, verde, amarillo : Señal de semáforo vehicular con tecnología LED con módulo 2X200 mm en Policarbonato color negro con bisagras del mismo material, Luz rojo y verde, 6W, 120 V. Carcaza plástica. | D30: Un | E30: 16 | F30: 1804058 | G30: =E30*F30 -> 28864928 | I30: =E30*H30 -> 0 | J30: =G30+I30 -> 28864928
B31: =B30+0.01 -> 8.18 | C31: Display alfanumérico. Sistema integrado de visualización de tarifas y mensajería de vía al usuario. | D31: Un | E31: 16 | F31: 4276681 | G31: =E31*F31 -> 68426896 | I31: =E31*H31 -> 0 | J31: =G31+I31 -> 68426896
B32: =B31+0.01 -> 8.19 | C32: Baliza LED AMBAR 12 - 24V ,4" de diámetro incluye fuente. Incluido en poste de semáforo | D32: Un | E32: 16 | F32: 172446 | G32: =E32*F32 -> 2759136 | I32: =E32*H32 -> 0 | J32: =G32+I32 -> 2759136
B33: =B32+0.01 -> 8.2 | C33: Sirena. SPL con intensidad mayor o igual a 100dB/1m. 110V. Incluido en poste de semáforo | D33: Un | E33: 16 | F33: 172446 | G33: =E33*F33 -> 2759136 | I33: =E33*H33 -> 0 | J33: =G33+I33 -> 2759136
B34: =B33+0.01 -> 8.21 | C34: Poste metálico para semáforo, display y cámara de ejes | D34: Un | E34: 16 | F34: 801214 | G34: =E34*F34 -> 12819424 | I34: =E34*H34 -> 0 | J34: =G34+I34 -> 12819424
B35: =B34+0.01 -> 8.22 | C35: Poste metálico para cámara de reconocimiento de placas LPR | D35: Un | E35: 16 | F35: 626115 | G35: =E35*F35 -> 10017840 | I35: =E35*H35 -> 0 | J35: =G35+I35 -> 10017840
B36: =B35+0.01 -> 8.23 | C36: Semáforo de entrada: Cruz y flecha. Sistema integrado de señalización de apertura de vía comandado desde la consola del Operario con registro de funcionamiento en base de datos. Tecnología LED 600X600 mm en luz rojo Cruz y luz verde flecha. Incluye modulo IP. | D36: Un | E36: 28 | F36: 3235297 | G36: =E36*F36 -> 90588316 | I36: =E36*H36 -> 0 | J36: =G36+I36 -> 90588316
B37: =B36+0.01 -> 8.24 | C37: Semáforo intermitente | D37: Un | E37: 26 | F37: 870193 | G37: =E37*F37 -> 22625018 | I37: =E37*H37 -> 0 | J37: =G37+I37 -> 22625018
... B40: =B39+0.01 -> 8.27 | C40: Talanquera manual de entrada. Conjunto electromecánico, Operación fluida y silenciosa. Ancho de paso de 3 Mts, | D40: Un | E40: 14 | F40: 21208303 | G40: =E40*F40 -> 296916242 | I40: =E40*H40 -> 0 | J40: =G40+I40 -> 296916242
B41: =B40+0.01 -> 8.28 | C41: EQUIPOS CARRIL IPREV | G41: =E41*F41 -> 0 | I41: =E41*H41 -> 0 | J41: =G41+I41 -> 0
B42: =B41+0.01 -> 8.29 | C42: Lector RFID Incluye: Antena, cableado y herraje | D42: Un | E42: 2 | F42: 21696460 | G42: =E42*F42 -> 43392920 | I42: =E42*H42 -> 0 | J42: =G42+I42 -> 43392920
B43: =B42+0.01 -> 8.3 | C43: Detector de presencia para Telepeaje | D43: Un | E43: 2 | F43: 955090 | G43: =E43*F43 -> 1910180 | I43: =E43*H43 -> 0 | J43: =G43+I43 -> 1910180
B44: =B43+0.01 -> 8.31 | C44: Separador óptico de vehículos, doble. Chasis de ópticos, puerta en vidrio para barrera emisora y barrera receptora. Incluye cableados. Para la entrada en carriles IPREV. | D44: Un | E44: 2 | F44: 12914939 | G44: =E44*F44 -> 25829878 | I44: =E44*H44 -> 0 | J44: =G44+I44 -> 25829878
B45: =B44+0.01 -> 8.32 | C45: Pórtico para antena de telepeaje | D45: Un | E45: 2 | F45: 1873038 | G45: =E45*F45 -> 3746076 | I45: =E45*H45 -> 0 | J45: =G45+I45 -> 3746076
B46: =B45+0.01 -> 8.33 | C46: EQUIPOS DE COMUNICACIÓN Y DATOS | F46: 0 | G46: =E46*F46 -> 0 | I46: =E46*H46 -> 0 | J46: =G46+I46 -> 0
B47: =B46+0.01 -> 8.34 | C47: Rack de 19" para Equipos computacionales de 42 U | D47: Un | E47: 1 | F47: 10612111 | G47: =E47*F47 -> 10612111 | I47: =E47*H47 -> 0 | J47: =G47+I47 -> 10612111
B48: =B47+0.01 -> 8.35 | C48: ODF para 48 fibras | D48: Un | E48: 1 | F48: 779504 | G48: =E48*F48 -> 779504 | H48: =(1397985+96942)*1.21 -> 1808861.7 | I48: =E48*H48 -> 1808861.7 | J48: =G48+I48 -> 2588365.7
B49: =B48+0.01 -> 8.36 | C49: Patch Panel | D49: Un | E49: 1 | F49: 1345654 | G49: =E49*F49 -> 1345654 | H49: =(372671+76500) -> 449171 | I49: =E49*H49 -> 449171 | J49: =G49+I49 -> 1794825
B50: =B49+0.01 -> 8.37 | C50: Patch Cord fibra óptica mono modo lc - lc | D50: Un | E50: 16 | F50: 31385 | G50: =E50*F50 -> 502160 | H50: 31603.894 | I50: =E50*H50 -> 505662.31 | J50: =G50+I50 -> 1007822.3
B51: =B50+0.01 -> 8.38 | C51: NAS (Network-Attached Storage) Special Video security grade Hard Drive 8 TB | D51: Un | E51: 1 | F51: 29246977 | G51: =E51*F51 -> 29246977 | I51: =E51*H51 -> 0 | J51: =G51+I51 -> 29246977
B52: =B51+0.01 -> 8.39 | C52: Sistema de grabación de video NVR Apoyo LX 1U, RAM 4Gb, 4 Hot swap Storage Bays, 4TB UP 6TB, | D52: Un | E52: 1 | F52: 17000601 | G52: =E52*F52 -> 17000601 | I52: =E52*H52 -> 0 | J52: =G52+I52 -> 17000601
B53: =B52+0.01 -> 8.4 | C53: Equipos de computo
B54: =B53+0.01 -> 8.41 | C54: SERVIDOR MEMORIA 16GB RAID 1 + FUENTE DE PODER REDUNDANTE | D54: Un | E54: 2 | F54: 15009769 | G54: =E54*F54 -> 30019538 | I54: =E54*H54 -> 0 | J54: =G54+I54 -> 30019538
B55: =B54+0.01 -> 8.42 | C55: PC de informes | D55: Un | E55: 2 | F55: 5093813 | G55: =E55*F55 -> 10187626 | I55: =E55*H55 -> 0 | J55: =G55+I55 -> 10187626
B56: =B55+0.01 -> 8.43 | C56: Impresora de informes | D56: Un | E56: 1 | F56: 2228543 | G56: =E56*F56 -> 2228543 | I56: =E56*H56 -> 0 | J56: =G56+I56 -> 2228543
B57: =B56+0.01 -> 8.44 | C57: Instalación
B58: =B57+0.01 -> 8.45 | C58: Instalación | D58: Un | E58: 16 | H58: =31985884*1.21 -> 38702920 | I58: =E58*H58 -> 6.1924671e+08 | J58: =G58+I58 -> 6.1924671e+08
B59: =B58+0.01 -> 8.46 | C59: Cableado datos y energía, Cables CAT6, alimentación 4X18, 2X18 y 3X18 para periféricos carriles. cableado oficina recaudo y equipos. | D59: Un | E59: 16 | F59: 3257300 | G59: =E59*F59 -> 52116800 | I59: =E59*H59 -> 0 | J59: =G59+I59 -> 52116800
B60: =B59+0.01 -> 8.47 | C60: SOFTWARE Y LICENCIAS
B61: =B60+0.01 -> 8.48 | C61: Software de carril
B62: =B61+0.01 -> 8.49 | C62: Licencia Software Vial de carril | D62: Un | E62: 16 | F62: 4458870 | G62: =E62*F62 -> 71341920 | I62: =E62*H62 -> 0 | J62: =G62+I62 -> 71341920
B63: =B62+0.01 -> 8.5 | C63: Licencia Software de Telepeaje incluido en licencia software de carril según Resolución 35125 | D63: Un | E63: 2 | F63: 2229435 | G63: =E63*F63 -> 4458870 | I63: =E63*H63 -> 0 | J63: =G63+I63 -> 4458870
B64: =B63+0.01 -> 8.51 | C64: Software de estación
B65: =B64+0.01 -> 8.52 | C65: Licencia Software web de estación (1 por estación) | D65: Un | E65: 1 | F65: 8917740 | G65: =E65*F65 -> 8917740 | I65: =E65*H65 -> 0 | J65: =G65+I65 -> 8917740
B66: =B65+0.01 -> 8.53 | C66: Licencia Software web de estación (1 por estación) IP/REV según resolución 35125 | D66: Un | E66: 1 | F66: 0 | G66: =E66*F66 -> 0 | I66: =E66*H66 -> 0 | J66: =G66+I66 -> 0
B67: =B66+0.01 -> 8.54 | C67: Licencia Base de datos | D67: Un | E67: 1 | F67: 0 | G67: =E67*F67 -> 0 | I67: =E67*H67 -> 0 | J67: =G67+I67 -> 0
B68: =B67+0.01 -> 8.55 | C68: Licencia Antivirus -( carriles + Pc informes) | D68: Un | E68: 18 | F68: 0 | G68: =E68*F68 -> 0 | I68: =E68*H68 -> 0 | J68: =G68+I68 -> 0
B69: =B68+0.01 -> 8.56 | C69: Suministro, instalación y puesta en marcha de Switch Nivel 3 para comunicación, 48 puertos 10/100/1000 Base-T, Ethernet 10/100/1000 Mbps, Gethernet, puertos SFP+ de 1Gbit/s embebidos en el chasis, incluye redundancia | D69: Un | E69: 4 | F69: 5158994 | G69: =E69*F69 -> 20635976 | H69: =326586+244218 -> 570804 | I69: =E69*H69 -> 2283216 | J69: =G69+I69 -> 22919192
B70: =B69+0.01 -> 8.57 | C70: Suministro, instalación y puesta en marcha de Switch Nivel 2 para comunicación, 16 puertos 10/100/1000 Base-T, Ethernet 10/100/1000 Mbps, Gethernet, puertos SFP+ de 1Gbit/s embebidos en el chasis, incluye redundancia | D70: Un | E70: 2 | F70: 1700201 | G70: =E70*F70 -> 3400402 | H70: =346081+96538 -> 442619 | I70: =E70*H70 -> 885238 | J70: =G70+I70 -> 4285640
B71: =B70+0.01 -> 8.58 | C71: Transceiver SFP Fibra Óptica 10 Km 1G, con conector LC. | D71: Un | E71: 16 | F71: 121768 | G71: =E71*F71 -> 1948288 | H71: =16601+6533 -> 23134 | I71: =E71*H71 -> 370144 | J71: =G71+I71 -> 2318432
B72: =B71+0.01 -> 8.59 | C72: Transceiver SFP Fibra Óptica max 80 Km 10G, LC conector LC. | D72: Un | E72: 4 | F72: 2447029 | G72: =E72*F72 -> 9788116 | H72: =16497+115585 -> 132082 | I72: =E72*H72 -> 528328 | J72: =G72+I72 -> 10316444
B73: =B72+0.01 -> 8.6 | C73: Transceiver SFP Fibra Óptica 10 Km 10G, con conector LC. | D73: Un | E73: 8 | F73: 385359 | G73: =E73*F73 -> 3082872 | H73: =15653+17853 -> 33506 | I73: =E73*H73 -> 268048 | J73: =G73+I73 -> 3350920
B74: =B73+0.01 -> 8.61 | C74: Caja de empalme tipo botella (mufla) para F.O de 48 hilos con cierre térmico para uso subterráneo. | D74: Un | E74: 2 | F74: 192904 | G74: =E74*F74 -> 385808 | H74: =153879+16384 -> 170263 | I74: =E74*H74 -> 340526 | J74: =G74+I74 -> 726334
B75: =B74+0.01 -> 8.62 | C75: Cajas para la Red Troncal, de paso o derivación, de 80X80X80, dimensiones internas | D75: Un | E75: 4 | F75: 962106 | G75: =E75*F75 -> 3848424 | H75: =1439361*0.54*1.052 -> 817672.2 | I75: =E75*H75 -> 3270688.8 | J75: =G75+I75 -> 7119112.8
B76: =B75+0.01 -> 8.63 | C76: Caja de reserva para micro cable de Fibra Óptica | D76: Un | E76: 2 | F76: 455761 | G76: =E76*F76 -> 911522 | H76: =72486+24969 -> 97455 | I76: =E76*H76 -> 194910 | J76: =G76+I76 -> 1106432
B77: =B76+0.01 -> 8.64 | C77: Canalización y ducto Conduit de 1 y 1/2", entre la troncal de FO y el ITS, en longitud promedio de 30 m | D77: Un | E77: 2 | F77: 263833 | G77: =E77*F77 -> 527666 | H77: 2265263.4 | I77: =E77*H77 -> 4530526.8 | J77: =G77+I77 -> 5058192.8
B78: =B77+0.01 -> 8.65 | C78: UPS bifásica de 20KVA, con autonomía de 30 minutos | D78: Un | E78: 2 | F78: 68106140 | G78: =E78*F78 -> 136212280 | I78: =E78*H78 -> 0 | J78: =G78+I78 -> 136212280
B79: =B78+0.01 -> 8.66 | C79: EQUIPOS PARA EL CCO (COP)
B80: =B79+0.01 -> 8.67 | C80: Servidor de aplicación de datos | D80: Un | E80: 1 | F80: 39852668 | G80: =E80*F80 -> 39852668 | H80: =(1089333+21858333)*1.051 -> 24117997 | I80: =E80*H80 -> 24117997 | J80: =G80+I80 -> 63970665
B81: =B80+0.01 -> 8.68 | C81: PC multifunción | D81: Un | E81: 1 | F81: 5389254.2 | G81: =E81*F81 -> 5389254.2 | I81: =E81*H81 -> 0 | J81: =G81+I81 -> 5389254.2
B82: =B81+0.01 -> 8.69 | C82: Pantalla de 21", de alta resolución | D82: Un | E82: 1 | F82: 12189721 | G82: =E82*F82 -> 12189721 | H82: =(40850+215000)*1.051 -> 268898.35 | I82: =E82*H82 -> 268898.35 | J82: =G82+I82 -> 12458619
B83: =B82+0.01 -> 8.7 | C83: Impresora Reportes | D83: Un | E83: 1 | F83: 4968343.1 | G83: =E83*F83 -> 4968343.1 | H83: =(116714+614286)*1.051 -> 768281 | I83: =E83*H83 -> 768281 | J83: =G83+I83 -> 5736624.1
B84: =B83+0.01 -> 8.71 | C84: Mobiliario para puesto de operador: Mesa + Silla | D84: Un | E84: 1 | F84: 5172350.4 | G84: =E84*F84 -> 5172350.4 | I84: =E84*H84 -> 0 | J84: =G84+I84 -> 5172350.4
B85: =B84+0.01 -> 8.72 | C85: Mobiliario para la impresora | D85: Un | E85: 1 | F85: 3068200 | G85: =E85*F85 -> 3068200 | H85: =(163400+860000)*1.051 -> 1075593.4 | I85: =E85*H85 -> 1075593.4 | J85: =G85+I85 -> 4143793.4
B86: =B85+0.01 -> 8.73 | C86: Licencia COP | D86: Un | E86: 1 | F86: 2229435 | G86: =E86*F86 -> 2229435 | I86: =E86*H86 -> 0 | J86: =G86+I86 -> 2229435
C87: Pig Tail | D87: Un | E87: 192 | F87: 7418.4565 | G87: =E87*F87 -> 1424343.7 | H87: 2017.5034 | I87: =E87*H87 -> 387360.65 | J87: =G87+I87 -> 1811704.3
B88: =B86+0.01 -> 8.74 | C88: Fusiones | D88: Un | E88: 384 | F88: 7441 | G88: =E88*F88 -> 2857344 | H88: =43397+2117 -> 45514 | I88: =E88*H88 -> 17477376 | J88: =G88+I88 -> 20334720
B89: =B88+0.01 -> 8.75 | C89: Pequeño material de montaje | D89: Gbl | E89: 2 | F89: 2977793.9 | G89: =E89*F89 -> 5955587.8 | I89: =E89*H89 -> 0 | J89: =G89+I89 -> 5955587.8
B90: =B89+0.01 -> 8.76 | C90: Puesta en Marcha Soporte técnico | D90: Glb | E90: 2 | G90: =E90*F90 -> 0 | H90: 18750000 | I90: =E90*H90 -> 37500000 | J90: =G90+I90 -> 37500000
B91: =B90+0.01 -> 8.77 | C91: Capacitación | D91: Glb | E91: 2 | F91: 9000000 | G91: =E91*F91 -> 18000000 | I91: =E91*H91 -> 0 | J91: =G91+I91 -> 18000000
H93: TOTAL COSTOS DIRECTOS | J93: =SUM(J10:J91) -> 3.3525228e+09
F94: ADMINISTRACION (A) | I94: 0.2 | J94: =J93*I94 -> 6.7050456e+08
F95: IMPREVISTOS (I) | I95: 0.04 | J95: =J93*I95 -> 1.3410091e+08
F96: UTILIDAD (U) | I96: 0.04 | J96: =J93*I96 -> 1.3410091e+08
F97: SUBTOTAL COSTOS DIRECTOS + AIU
F98: IVA SOBRE LA UTILIDAD 19% | I98: 0.19 | J98: =J96*I98 -> 25479173
H100: TOTAL COSTO DIRECTO+AIU + IVA | J100: =SUM(J93:J98) -> 4.3167084e+09

Sheet BásculaS Sur y Norte
B2: PROYECTO TRONCAL MAGDALENA 1
B3: TABLA DE CANTIDADES | D3: PRESUPUESTO WUXY
B4: UNIDADES FUNCIONALES TOTAL 0 - 13
B6: ítem | C6: ITS | D6: Unidad | E6: Cantidad | F6: SUMINISTRO | H6: INSTALACIÓN PUESTA EN FUNCIONAMIENTO Y PRUEBAS | J6: COSTO TOTAL
B7: 9 | C7: PESAJE | F7: Costo unitario | G7: Total suministro | H7: Costo unitario | I7: Total Instalación | J7: TOTAL
E8: TOTAL | F8: Col $ | G8: Col $ | H8: Col $ | I8: Col $ | J8: Col $
C9: BÁSCULA DINÁMICA
B10: =B7+0.01 -> 9.01 | C10: Plataforma fija de preselección (2X) | D10: Un | E10: 2 | F10: 120311790 | G10: =E10*F10 -> 240623580 | H10: 0 | I10: =E10*H10 -> 0 | J10: =G10+I10 -> 240623580
B11: =B10+0.01 -> 9.02 | C11: Gabinete de Bifurcación | D11: Un | E11: 2 | F11: 0 | G11: =E11*F11 -> 0 | H11: 0 | I11: =E11*H11 -> 0 | J11: =G11+I11 -> 0
B12: =B11+0.01 -> 9.03 | C12: Gabinete de Control de Selección WIM | D12: Un | E12: 2 | F12: 39686505 | G12: =E12*F12 -> 79373010 | H12: 0 | I12: =E12*H12 -> 0 | J12: =G12+I12 -> 79373010
B13: =B12+0.01 -> 9.04 | C13: Cortina Óptica infrarroja | D13: Un | E13: 2 | F13: 12892065 | G13: =E13*F13 -> 25784130 | H13: 0 | I13: =E13*H13 -> 0 | J13: =G13+I13 -> 25784130
B14: =B13+0.01 -> 9.05 | C14: Semáforo Cruz / Flecha, tipo led, hacia báscula estática | D14: Un | E14: 2 | F14: 4081567.5 | G14: =E14*F14 -> 8163135 | H14: 0 | I14: =E14*H14 -> 0 | J14: =G14+I14 -> 8163135
B15: =B14+0.01 -> 9.06 | C15: Semáforo Cruz / Flecha, tipo led, de retorno a vía principal | D15: Un | E15: 2 | F15: 4081567.5 | G15: =E15*F15 -> 8163135 | H15: 0 | I15: =E15*H15 -> 0 | J15: =G15+I15 -> 8163135
B16: =B15+0.01 -> 9.07 | C16: Poste tipo T o Pórtico | D16: Un | E16: 2 | F16: 0 | G16: =E16*F16 -> 0 | H16: 11176794 | I16: =E16*H16 -> 22353587 | J16: =G16+I16 -> 22353587
B17: =B16+0.01 -> 9.08 | C17: Cámara de reconocimiento de placas para evadidos, 1 por carril (en vía Principal) | D17: Un | E17: 4 | F17: 32391472 | G17: =E17*F17 -> 129565890 | H17: 0 | I17: =E17*H17 -> 0 | J17: =G17+I17 -> 129565890
B18: =B17+0.01 -> 9.09 | C18: Cámara de imágenes para evadidos, 1 por carril (en vía principal) | D18: Un | E18: 4 | F18: 0 | G18: =E18*F18 -> 0 | H18: 0 | I18: =E18*H18 -> 0 | J18: =G18+I18 -> 0
B19: =B18+0.01 -> 9.1 | C19: Pareja de postes de 6 m o pórtico para cámaras de evadidos | D19: Un | E19: 2 | F19: 0 | G19: =E19*F19 -> 0 | H19: 12932237 | I19: =E19*H19 -> 25864474 | J19: =G19+I19 -> 25864474
B20: =B19+0.01 -> 9.11 | C20: Cámara de Reconocimiento de Placas en Zona de Pesaje Dinámico | D20: Un | E20: 2 | F20: 21657990 | G20: =E20*F20 -> 43315980 | H20: 0 | I20: =E20*H20 -> 0 | J20: =G20+I20 -> 43315980
B21: =B20+0.01 -> 9.12 | C21: Cámara de evidencia de fugados | D21: Un | E21: 2 | F21: 35619795 | G21: =E21*F21 -> 71239590 | H21: 0 | I21: =E21*H21 -> 0 | J21: =G21+I21 -> 71239590
B22: =B21+0.01 -> 9.13 | C22: Poste multifuncional | D22: Un | E22: 6 | F22: 0 | G22: =E22*F22 -> 0 | H22: 11176794 | I22: =E22*H22 -> 67060762 | J22: =G22+I22 -> 67060762
... B26: =B25+0.01 -> 9.17 | C26: Licencia Software de Pesaje – clasificación | D26: Un | E26: 2 | F26: 4225897.5 | G26: =E26*F26 -> 8451795 | H26: 0 | I26: =E26*H26 -> 0 | J26: =G26+I26 -> 8451795
B27: =B26+0.01 -> 9.18 | C27: Material de montaje | D27: Un | E27: 2 | F27: 20898135 | G27: =E27*F27 -> 41796270 | I27: =E27*H27 -> 0 | J27: =G27+I27 -> 41796270
B28: =B27+0.01 -> 9.19 | C28: Servicio de instalación General, pruebas y entrega a la interventoría | D28: Un | E28: 2 | F28: 1.6503187e+08 | G28: =E28*F28 -> 330063749 | H28: 3981600 | I28: =E28*H28 -> 7963200 | J28: =G28+I28 -> 338026949
C29: BÁSCULA ESTÁTICA | E29: 0 | G29: =E29*F29 -> 0 | I29: =E29*H29 -> 0
B30: =B28+0.01 -> 9.2 | C30: Báscula camionera digital multiplataforma incluye la certificación, con 4 plataformas independientes de tal manera que sirven para hacer un pesaje por grupo de ejes y peso total. La longitud total de la báscula es de 21 m, con un ancho libre de 3,4 m sin considerar los bordillos. Se incluye el concreto requerido para las plataformas de la báscula estática. | D30: Un | E30: 2 | G30: =E30*F30 -> 0 | H30: 5.0393028e+08 | I30: =E30*H30 -> 1.0078606e+09 | J30: =G30+I30 -> 1.0078606e+09
B31: =B30+0.01 -> 9.21 | C31: Celdas de carga | D31: Un | E31: 32 | G31: =E31*F31 -> 0 | H31: 5442460.1 | I31: =E31*H31 -> 1.7415872e+08 | J31: =G31+I31 -> 1.7415872e+08
B32: =B31+0.01 -> 9.22 | C32: Juego de tarjetas de unión digitales | D32: Un | E32: 2 | G32: =E32*F32 -> 0 | H32: 38320942 | I32: =E32*H32 -> 76641885 | J32: =G32+I32 -> 76641885
B33: =B32+0.01 -> 9.23 | C33: Indicador de peso multicanal | D33: Un | E33: 2 | G33: =E33*F33 -> 0 | H33: 16564009 | I33: =E33*H33 -> 33128018 | J33: =G33+I33 -> 33128018
B34: =B33+0.01 -> 9.24 | C34: Computador Servidor de Respaldo | D34: Un | E34: 2 | G34: =E34*F34 -> 0 | H34: 13990900 | I34: =E34*H34 -> 27981800 | J34: =G34+I34 -> 27981800
B35: =B34+0.01 -> 9.25 | C35: Computador para Software de Báscula Estática | D35: Un | E35: 2 | G35: =E35*F35 -> 0 | H35: 11900560 | I35: =E35*H35 -> 23801120 | J35: =G35+I35 -> 23801120
B36: =B35+0.01 -> 9.26 | C36: Software para báscula estática | D36: Un | E36: 2 | G36: =E36*F36 -> 0 | H36: 14134680 | I36: =E36*H36 -> 28269360 | J36: =G36+I36 -> 28269360
B37: =B36+0.01 -> 9.27 | C37: Impresora de informes | D37: Un | E37: 2 | G37: =E37*F37 -> 0 | H37: 1858080 | I37: =E37*H37 -> 3716160 | J37: =G37+I37 -> 3716160
B38: =B37+0.01 -> 9.28 | C38: 1 Semáforo tipo led. | D38: Un | E38: 2 | G38: =E38*F38 -> 0 | H38: 1378076 | I38: =E38*H38 -> 2756152 | J38: =G38+I38 -> 2756152
B39: =B38+0.01 -> 9.29 | C39: 1 Poste multifuncional | D39: Un | E39: 2 | G39: =E39*F39 -> 0 | H39: 1526280 | I39: =E39*H39 -> 3052560 | J39: =G39+I39 -> 3052560
B40: =B39+0.01 -> 9.3 | C40: Talanqueras (Entrada + Salida) | D40: Un | E40: 4 | G40: =E40*F40 -> 0 | H40: 11834200 | I40: =E40*H40 -> 47336800 | J40: =G40+I40 -> 47336800
B41: =B40+0.01 -> 9.31 | C41: Gabinete de control | D41: Un | E41: 2 | G41: =E41*F41 -> 0 | H41: 12442500 | I41: =E41*H41 -> 24885000 | J41: =G41+I41 -> 24885000
B42: =B41+0.01 -> 9.32 | C42: Sistema de Categorización post pesaje | D42: Un | E42: 2 | G42: =E42*F42 -> 0 | H42: 14988512 | I42: =E42*H42 -> 29977024 | J42: =G42+I42 -> 29977024
... B64: =B63+0.01 -> 9.54 | C64: Patch Panel | D64: Un | E64: 2 | G64: =E64*F64 -> 0 | H64: 3871000 | I64: =E64*H64 -> 7742000 | J64: =G64+I64 -> 7742000
B65: =B64+0.01 -> 9.55 | C65: Patch Cord fibra óptica mono modo lc - lc | D65: Un | E65: 16 | F65: 31385 | G65: =E65*F65 -> 502160 | H65: 31603.894 | I65: =E65*H65 -> 505662.31 | J65: =G65+I65 -> 1007822.3
B66: =B65+0.01 -> 9.56 | C66: Suministro, instalación y puesta en marcha de Switch Nivel 3 para comunicación, 48 puertos 10/100/1000 Base-T, Ethernet 10/100/1000 Mbps, Gethernet, puertos SFP+ de 1Gbit/s embebidos en el chasis | D66: Un | E66: 4 | F66: 5158994 | G66: =E66*F66 -> 20635976 | H66: 570804 | I66: =E66*H66 -> 2283216 | J66: =G66+I66 -> 22919192
B67: =B66+0.01 -> 9.57 | C67: Suministro, instalación y puesta en marcha de Switch Nivel 2 para comunicación, 16 puertos 10/100/1000 Base-T, Ethernet 10/100/1000 Mbps, Gethernet, puertos SFP+ de 1Gbit/s embebidos en el chasis | D67: Un | E67: 2 | F67: 1700201 | G67: =E67*F67 -> 3400402 | H67: 442619 | I67: =E67*H67 -> 885238 | J67: =G67+I67 -> 4285640
B68: =B67+0.01 -> 9.58 | C68: Transceiver SFP Fibra Óptica 10 Km 1G, con conector LC. | D68: Un | E68: 16 | F68: 121768 | G68: =E68*F68 -> 1948288 | H68: 23134 | I68: =E68*H68 -> 370144 | J68: =G68+I68 -> 2318432
B69: =B68+0.01 -> 9.59 | C69: Transceiver SFP Fibra Óptica max 80 Km 10G, con conector LC. | D69: Un | E69: 4 | F69: 2447029 | G69: =E69*F69 -> 9788116 | H69: 132082 | I69: =E69*H69 -> 528328 | J69: =G69+I69 -> 10316444
B70: =B69+0.01 -> 9.6 | C70: Transceiver SFP Fibra Óptica 10 Km 10G, con conector LC. | D70: Un | E70: 8 | F70: 385359 | G70: =E70*F70 -> 3082872 | H70: 33506 | I70: =E70*H70 -> 268048 | J70: =G70+I70 -> 3350920
B71: =B70+0.01 -> 9.61 | C71: Cable de servicio de FO, 8 hilos y longitud promedio de 30 m, con características de calidad iguales o mejores a las del microducto de la troncal. | D71: Un | E71: 2 | F71: 149435 | G71: =E71*F71 -> 298870 | H71: 138607.72 | I71: =E71*H71 -> 277215.43 | J71: =G71+I71 -> 576085.43
B72: =B71+0.01 -> 9.62 | C72: Canalización y ducto Conduit de 1 y 1/2", entre la troncal de FO y el ITS, en longitud promedio de 30 m | D72: Un | E72: 2 | F72: 263833 | G72: =E72*F72 -> 527666 | H72: 2265263.4 | I72: =E72*H72 -> 4530526.8 | J72: =G72+I72 -> 5058192.8
B73: =B72+0.01 -> 9.63 | C73: Caja de empalme tipo botella (mufla) para F.O de 48 hilos con cierre térmico para uso subterráneo. | D73: Un | E73: 2 | F73: 192904 | G73: =E73*F73 -> 385808 | H73: 170263 | I73: =E73*H73 -> 340526 | J73: =G73+I73 -> 726334
B74: =B73+0.01 -> 9.64 | C74: Cajas para la Red Troncal, de paso o derivación, de 80X80X80, dimensiones internas | D74: Un | E74: 4 | F74: 962106 | G74: =E74*F74 -> 3848424 | H74: 817672.2 | I74: =E74*H74 -> 3270688.8 | J74: =G74+I74 -> 7119112.8
B75: =B74+0.01 -> 9.65 | C75: Caja de reserva para micro cable de Fibra Óptica | D75: Un | E75: 2 | F75: 455761 | G75: =E75*F75 -> 911522 | H75: 97455 | I75: =E75*H75 -> 194910 | J75: =G75+I75 -> 1106432
B76: =B75+0.01 -> 9.66 | C76: Pig Tail | D76: Un | E76: 192 | F76: 7418.4565 | G76: =E76*F76 -> 1424343.7 | H76: 2017.5034 | I76: =E76*H76 -> 387360.65 | J76: =G76+I76 -> 1811704.3
B77: =B76+0.01 -> 9.67 | C77: Fusiones | D77: Un | E77: 384 | F77: 7441 | G77: =E77*F77 -> 2857344 | H77: 45514 | I77: =E77*H77 -> 17477376 | J77: =G77+I77 -> 20334720
B78: =B77+0.01 -> 9.68 | C78: Material de montaje | D78: Glb | E78: 2 | F78: 2977793.9 | G78: =E78*F78 -> 5955587.8 | I78: =E78*H78 -> 0 | J78: =G78+I78 -> 5955587.8
B79: =B78+0.01 -> 9.69 | C79: Capacitación | D79: Glb | E79: 2 | F79: 9000000 | G79: =E79*F79 -> 18000000 | I79: =E79*H79 -> 0 | J79: =G79+I79 -> 18000000
H81: TOTAL COSTOS DIRECTOS | J81: =SUM(J9:J79) -> 3.2916973e+09
F82: ADMINISTRACION (A) | I82: 0.22 | J82: =J81*I82 -> 7.2417341e+08
F83: IMPREVISTOS (I) | I83: 0.04 | J83: =J81*I83 -> 1.3166789e+08
F84: UTILIDAD (U) | I84: 0.04 | J84: =J81*I84 -> 1.3166789e+08
F85: SUBTOTAL COSTOS DIRECTOS + AIU
F86: IVA SOBRE LA UTILIDAD 19% | I86: 0.19 | J86: =J84*I86 -> 25016900
H88: TOTAL COSTO DIRECTO+AIU + IVA | J88: =SUM(J81:J86) -> 4.3042234e+09

Sheet RADIO COMUNICACIONES
B2: PROYECTO TRONCAL MAGDALENA 1
B3: TABLA DE CANTIDADES | D3: PRESUPUESTO WUXY
B4: UNIDADES FUNCIONALES TOTAL 0 - 13
D5: Estaciones repetidoras | E5: 6
B8: ítem | C8: ITS | D8: Unidad | E8: Cantidad | F8: SUMINISTRO | H8: INSTALACIÓN PUESTA EN FUNCIONAMIENTO Y PRUEBAS | J8: COSTO TOTAL
B9: 10 | C9: RADIO COMUNICACIONES | F9: Costo unitario | G9: Total suministro | H9: Costo unitario | I9: Total Instalación | J9: TOTAL
E10: TOTAL | F10: Col $ | G10: Col $ | H10: Col $ | I10: Col $ | J10: Col $
B11: =B9+0.01 -> 10.01 | C11: Repetidor vhf 50w, capacidad de canal: 64, ciclo de operación 100% | D11: Un | E11: 6 | F11: 24711872 | G11: =E11*F11 -> 1.4827123e+08 | I11: =E11*H11 -> 0 | J11: =G11+I11 -> 1.4827123e+08
B12: =B11+0.01 -> 10.02 | C12: Licencia de conexión ip site | D12: Un | E12: 6 | F12: 2822790.7 | G12: =E12*F12 -> 16936744 | I12: =E12*H12 -> 0 | J12: =G12+I12 -> 16936744
B13: =B12+0.01 -> 10.03 | C13: Licencia ras | D13: Un | E13: 6 | F13: 691860.47 | G13: =E13*F13 -> 4151162.8 | I13: =E13*H13 -> 0 | J13: =G13+I13 -> 4151162.8
B14: =B13+0.01 -> 10.04 | C14: Duplexer vhf | D14: Un | E14: 6 | F14: 4545523.3 | G14: =E14*F14 -> 27273140 | I14: =E14*H14 -> 0 | J14: =G14+I14 -> 27273140
B15: =B14+0.01 -> 10.05 | C15: Cable heliax negro de 1/2 | D15: Un | E15: 240 | F15: 236616.28 | G15: =E15*F15 -> 56787907 | I15: =E15*H15 -> 0 | J15: =G15+I15 -> 56787907
B16: =B15+0.01 -> 10.06 | C16: Protector de línea | D16: Un | E16: 6 | F16: 632360.47 | G16: =E16*F16 -> 3794162.8 | I16: =E16*H16 -> 0 | J16: =G16+I16 -> 3794162.8
B17: =B16+0.01 -> 10.07 | C17: Antena 4 dipolos vhf | D17: Un | E17: 6 | F17: 24709105 | G17: =E17*F17 -> 1.4825463e+08 | I17: =E17*H17 -> 0 | J17: =G17+I17 -> 1.4825463e+08
B18: =B17+0.01 -> 10.08 | C18: Fuente cargadora 35a para rack | D18: Un | E18: 6 | F18: 5880814 | G18: =E18*F18 -> 35284884 | I18: =E18*H18 -> 0 | J18: =G18+I18 -> 35284884
B19: =B18+0.01 -> 10.09 | C19: Grounding kit de 1/2 | D19: Un | E19: 6 | F19: 592232.56 | G19: =E19*F19 -> 3553395.3 | I19: =E19*H19 -> 0 | J19: =G19+I19 -> 3553395.3
B20: =B19+0.01 -> 10.1 | C20: Hanger kit de 1/2 | D20: Un | E20: 6 | F20: 395329.07 | G20: =E20*F20 -> 2371974.4 | I20: =E20*H20 -> 0 | J20: =G20+I20 -> 2371974.4
B21: =B20+0.01 -> 10.11 | C21: Hanger adapter de 1/2 torre ángulo | D21: Un | E21: 6 | F21: 99628 | G21: =E21*F21 -> 597768 | I21: =E21*H21 -> 0 | J21: =G21+I21 -> 597768
B22: =B21+0.01 -> 10.12 | C22: Cable tipo rg8 / 8237 | D22: Un | E22: 36 | F22: 138372 | G22: =E22*F22 -> 4981392 | I22: =E22*H22 -> 0 | J22: =G22+I22 -> 4981392
B23: =B22+0.01 -> 10.13 | C23: Conector bnc para rg8 | D23: Un | E23: 6 | F23: 23523 | G23: =E23*F23 -> 141138 | I23: =E23*H23 -> 0 | J23: =G23+I23 -> 141138
... B44: =B43+0.01 -> 10.34 | C44: Servicio ip publica para rpt maestro para monitoreo remoto - mensual | D44: Un | E44: 0 | F44: 0 | G44: =E44*F44 -> 0 | I44: =E44*H44 -> 0 | J44: =G44+I44 -> 0
B45: =B44+0.01 -> 10.35 | C45: Casetas para equipos de 2,5x2,5 m, con sistema de tierras y bandejas de transporte para líneas de antena, barrajes para tierra, pasa muros. | D45: Un | E45: 6 | G45: =E45*F45 -> 0 | H45: 30137442 | I45: =E45*H45 -> 1.8082465e+08 | J45: =G45+I45 -> 1.8082465e+08
B46: =B45+0.01 -> 10.36 | C46: Torre riendada de 35 mts en predio de la concesión vial, con sistema de puesta a tierras / para rayos/ luces de construcción | D46: Un | E46: 6 | F46: 67124302 | G46: =E46*F46 -> 402745812 | H46: 16244081 | I46: =E46*H46 -> 97464484 | J46: =G46+I46 -> 5.002103e+08
B47: =B46+0.01 -> 10.37 | C47: Encerramiento de 22x22 m para sistema caseta de equipo y torre. | D47: Un | E47: 6 | G47: =E47*F47 -> 0 | H47: 22100791 | I47: =E47*H47 -> 1.3260474e+08 | J47: =G47+I47 -> 1.3260474e+08
B48: =B47+0.01 -> 10.38 | C48: INSTALACIÓN Y CONFIGURACIÓN DEL SISTEMA | E48: 6 | G48: =E48*F48 -> 0 | I48: =E48*H48 -> 0 | J48: =G48+I48 -> 0
B49: =B48+0.01 -> 10.39 | C49: Configuración del sistema completo | D49: Un | E49: 2 | G49: =E49*F49 -> 0 | H49: 58600581 | I49: =E49*H49 -> 1.1720116e+08 | J49: =G49+I49 -> 1.1720116e+08
B50: =B49+0.01 -> 10.4 | C50: RADIOS PORTÁTILES Y BASE / MÓVILES | G50: =E50*F50 -> 0 | I50: =E50*H50 -> 0 | J50: =G50+I50 -> 0
B51: =B50+0.01 -> 10.41 | C51: Radio portátil digital vhf 1000 ch con gps, pantalla a color y teclado - bluetooth | D51: Un | E51: 20 | F51: 3150000 | G51: =E51*F51 -> 63000000 | I51: =E51*H51 -> 0 | J51: =G51+I51 -> 63000000
B52: =B51+0.01 -> 10.42 | C52: Radio móvil digital vhf 45w pantalla alfanumérica a color - bluetooth - 1000ch | D52: Un | E52: 8 | F52: 9397402.3 | G52: =E52*F52 -> 75179219 | I52: =E52*H52 -> 0 | J52: =G52+I52 -> 75179219
B53: =B52+0.01 -> 10.43 | C53: Caja para empalme de 8 puertos | D53: Un | E53: 6 | F53: 275560 | G53: =E53*F53 -> 1653360 | H53: 180620 | I53: =E53*H53 -> 1083720 | J53: =G53+I53 -> 2737080
B54: =B53+0.01 -> 10.44 | C54: Patch Cord fibra óptica mono modo lc - lc | D54: Un | E54: 12 | F54: 31385 | G54: =E54*F54 -> 376620 | H54: 31603.894 | I54: =E54*H54 -> 379246.73 | J54: =G54+I54 -> 755866.73
B55: =B54+0.01 -> 10.45 | C55: Caja de empalme tipo botella (mufla) para F.O de 48 hilos con cierre térmico para uso subterráneo. | D55: Un | E55: 6 | F55: 192904 | G55: =E55*F55 -> 1157424 | H55: 170263 | I55: =E55*H55 -> 1021578 | J55: =G55+I55 -> 2179002
B56: =B55+0.01 -> 10.46 | C56: Cajas para la Red Troncal, de paso o derivación, de 80X80X80, dimensiones internas | D56: Un | E56: 12 | F56: 962106 | G56: =E56*F56 -> 11545272 | H56: 817672.2 | I56: =E56*H56 -> 9812066.4 | J56: =G56+I56 -> 21357338
B57: =B56+0.01 -> 10.47 | C57: Caja de reserva para micro cable de Fibra Óptica | D57: Un | E57: 6 | F57: 455761 | G57: =E57*F57 -> 2734566 | H57: 97455 | I57: =E57*H57 -> 584730 | J57: =G57+I57 -> 3319296
B58: =B57+0.01 -> 10.48 | C58: Pig Tail | D58: Un | E58: 24 | F58: 7418.4565 | G58: =E58*F58 -> 178042.96 | H58: 2017.5034 | I58: =E58*H58 -> 48420.082 | J58: =G58+I58 -> 226463.04
B59: =B58+0.01 -> 10.49 | C59: Cable de servicio de FO, 8 hilos y longitud promedio de 30 m, con características de calidad iguales o mejores a las del microducto de la troncal. | D59: Un | E59: 6 | F59: 149435 | G59: =E59*F59 -> 896610 | H59: 138607.72 | I59: =E59*H59 -> 831646.3 | J59: =G59+I59 -> 1728256.3
B60: =B59+0.01 -> 10.5 | C60: Canalización y ducto Conduit de 1 y 1/2", entre la troncal de FO y el ITS, en longitud promedio de 30 m | D60: Un | E60: 6 | F60: 263833 | G60: =E60*F60 -> 1582998 | H60: 2265263.4 | I60: =E60*H60 -> 13591580 | J60: =G60+I60 -> 15174578
B61: =B60+0.01 -> 10.51 | C61: Fusiones | D61: Un | E61: 96 | F61: 7441 | G61: =E61*F61 -> 714336 | H61: 45514 | I61: =E61*H61 -> 4369344 | J61: =G61+I61 -> 5083680
B62: =B61+0.01 -> 10.52 | C62: Pequeño material de montaje | D62: Gbl | E62: 6 | F62: 2977793.9 | G62: =E62*F62 -> 17866763 | I62: =E62*H62 -> 0 | J62: =G62+I62 -> 17866763
B63: =B62+0.01 -> 10.53 | C63: Estudio de propagación | D63: Gbl | E63: 1 | G63: =E63*F63 -> 0 | H63: 12600000 | I63: =E63*H63 -> 12600000 | J63: =G63+I63 -> 12600000
B64: =B63+0.01 -> 10.54 | C64: Capacitación | D64: Gbl | E64: 1 | F64: 9000000 | G64: =E64*F64 -> 9000000 | I64: =E64*H64 -> 0 | J64: =G64+I64 -> 9000000
H66: TOTAL COSTOS DIRECTOS | J66: =SUM(J11:J64) -> 1.8120381e+09
F67: ADMINISTRACION (A) | I67: 0.22 | J67: =J66*I67 -> 3.9864838e+08
F68: IMPREVISTOS (I) | I68: 0.04 | J68: =J66*I68 -> 72481524
F69: UTILIDAD (U) | I69: 0.04 | J69: =J66*I69 -> 72481524
F70: SUBTOTAL COSTOS DIRECTOS + AIU
F71: IVA SOBRE LA UTILIDAD 19% | I71: 0.19 | J71: =J69*I71 -> 13771490
H73: TOTAL COSTO DIRECTO+AIU + IVA | J73: =SUM(J66:J71) -> 2.369421e+09

Sheet CCO
B2: PROYECTO TRONCAL MAGDALENA 1
B3: TABLA DE CANTIDADES | D3: PRESUPUESTO WUXY
B4: UNIDADES FUNCIONALES TOTAL 0 - 13
B6: ítem | C6: ITS | D6: Unidad | E6: Cantidad | F6: SUMINISTRO | H6: INSTALACIÓN PUESTA EN FUNCIONAMIENTO Y PRUEBAS | J6: COSTO TOTAL
B7: 11 | C7: CCO | F7: Costo unitario | G7: Total suministro | H7: Costo unitario | I7: Total Instalación | J7: TOTAL
E8: TOTAL | F8: Col $ | G8: Col $ | H8: Col $ | I8: Col $ | J8: Col $
B9: =B7+0.01 -> 11.01 | C9: Servidores | D9: Un | E9: 3 | F9: 2.7647687e+08 | G9: =E9*F9 -> 8.2943062e+08 | H9: 24117997 | I9: =E9*H9 -> 72353991 | J9: =G9+I9 -> 9.0178461e+08
B10: =B9+0.01 -> 11.02 | C10: Cabina de almacenamiento | D10: Un | E10: 1 | F10: 1.1049555e+08 | G10: =E10*F10 -> 1.1049555e+08 | I10: =E10*H10 -> 0 | J10: =G10+I10 -> 1.1049555e+08
B11: =B10+0.01 -> 11.03 | C11: Servidor de Backups ITS | D11: Un | E11: 1 | F11: 64997379 | G11: =E11*F11 -> 64997379 | I11: =E11*H11 -> 0 | J11: =G11+I11 -> 64997379
B12: =B11+0.01 -> 11.04 | C12: Servidor de cronometría | D12: Un | E12: 1 | F12: 39852668 | G12: =E12*F12 -> 39852668 | H12: 24117997 | I12: =E12*H12 -> 24117997 | J12: =G12+I12 -> 63970665
B13: =B12+0.01 -> 11.05 | C13: KVM | D13: Un | E13: 1 | F13: 18722734 | G13: =E13*F13 -> 18722734 | H13: 3092331 | I13: =E13*H13 -> 3092331 | J13: =G13+I13 -> 21815065
B14: =B13+0.01 -> 11.06 | C14: Licenciamiento | I14: =E14*H14 -> 0
B15: =B14+0.01 -> 11.07 | C15: Aclarar separadamente cada una de las licencias, la forma de calculo, si es por Tags u otra forma, duración etc. El valor allí obtenido se trae a esta línea de licenciamiento. | D15: Gbl | E15: 1 | F15: 6.7767931e+08 | G15: 6.7767931e+08 | I15: =E15*H15 -> 0 | J15: 6.7767931e+08
B16: =B15+0.01 -> 11.08 | C16: Servidor grabación de video para las cámaras PTZ, con capacidad de hasta 50 TB, con sus licencias. | D16: Un | E16: 1 | F16: 84358292 | G16: =E16*F16 -> 84358292 | I16: =E16*H16 -> 0 | J16: =G16+I16 -> 84358292
B17: =B16+0.01 -> 11.09 | C17: Software para el Sistema de Gestión de Video VMS con licencias para 70 cámaras PTZ | D17: Un | E17: 1 | F17: 56458000 | G17: =E17*F17 -> 56458000 | I17: =E17*H17 -> 0 | J17: =G17+I17 -> 56458000
B18: =B17+0.01 -> 11.1 | C18: Puesto de trabajo para alojar el VMS | D18: Un | E18: 1 | F18: 28405693 | G18: =E18*F18 -> 28405693 | H18: 672140.77 | I18: =E18*H18 -> 672140.77 | J18: =G18+I18 -> 29077834
B19: =B18+0.01 -> 11.11 | C19: Joystick | D19: Un | E19: 1 | F19: 6916220.1 | G19: =E19*F19 -> 6916220.1 | I19: =E19*H19 -> 0 | J19: =G19+I19 -> 6916220.1
B20: =B19+0.01 -> 11.12 | C20: Suministro, instalación y puesta en marcha de VideoWall basado en tecnología LCD, arreglo de pantallas del tipo 4x2, con pantallas de 70", resolución Full HD (1920 x 1080 pixeles). | D20: Un | E20: 1 | F20: 95452998 | G20: =E20*F20 -> 95452998 | H20: 2398198.1 | I20: =E20*H20 -> 2398198.1 | J20: =G20+I20 -> 97851196
B21: =B20+0.01 -> 11.13 | C21: Controlador para el Video Wall incluye licencias | D21: Un | E21: 1 | F21: 78445981 | G21: =E21*F21 -> 78445981 | H21: 1328858.1 | I21: =E21*H21 -> 1328858.1 | J21: =G21+I21 -> 79774839
B22: =B21+0.01 -> 11.14 | C22: Monitor de 55", de alta resolución, - sala de crisis. | D22: Un | E22: 1 | F22: 27850000 | G22: =E22*F22 -> 27850000 | I22: =E22*H22 -> 0 | J22: =G22+I22 -> 27850000
B23: =B22+0.01 -> 11.15 | C23: Puestos de operador + Jefe de ITS | D23: Un | E23: 4 | F23: 28405693 | G23: =E23*F23 -> 1.1362277e+08 | H23: 672140.77 | I23: =E23*H23 -> 2688563.1 | J23: =G23+I23 -> 1.1631133e+08
B24: =B23+0.01 -> 11.16 | C24: Pantallas de 21", de alta resolución: Operadores + KVM | D24: Un | E24: 9 | F24: 12189721 | G24: =E24*F24 -> 1.0970749e+08 | H24: 268898.35 | I24: =E24*H24 -> 2420085.1 | J24: =G24+I24 -> 1.1212757e+08
B25: =B24+0.01 -> 11.17 | C25: Mobiliario para puestos de operador, KVM y SOS: Mesa + Silla | D25: Un | E25: 6 | F25: 4942576.8 | G25: =E25*F25 -> 29655461 | H25: 12907121 | I25: =E25*H25 -> 77442725 | J25: =G25+I25 -> 1.0709819e+08
B26: =B25+0.01 -> 11.18 | C26: Impresora a color | D26: Un | E26: 1 | F26: 4968343.1 | G26: =E26*F26 -> 4968343.1 | H26: 768281 | I26: =E26*H26 -> 768281 | J26: =G26+I26 -> 5736624.1
B27: =B26+0.01 -> 11.19 | C27: Mobiliario para la impresora | D27: Un | E27: 1 | F27: 2931900 | G27: =E27*F27 -> 2931900 | H27: 1075593.4 | I27: =E27*H27 -> 1075593.4 | J27: =G27+I27 -> 4007493.4
B28: =B27+0.01 -> 11.2 | C28: PC Portátil con características de trabajo pesado, para utilizarlo como escritorio remoto | D28: Un | E28: 1 | F28: 27170625 | G28: =E28*F28 -> 27170625 | I28: =E28*H28 -> 0 | J28: =G28+I28 -> 27170625
B29: =B28+0.01 -> 11.21 | C29: Software y licencia SCADA para PC portátil | D29: Un | E29: 1 | F29: 1.73892e+08 | G29: =E29*F29 -> 1.73892e+08 | I29: =E29*H29 -> 0 | J29: =G29+I29 -> 1.73892e+08
B30: =B29+0.01 -> 11.22 | C30: Suministro, instalación y puesta en marcha de Firewall | D30: Un | E30: 2 | F30: 35374700 | G30: =E30*F30 -> 70749400 | I30: =E30*H30 -> 0 | J30: =G30+I30 -> 70749400
B31: =B30+0.01 -> 11.23 | C31: Servidor SOS | D31: Un | E31: 1 | F31: 1.0520239e+08 | G31: =E31*F31 -> 1.0520239e+08 | I31: =E31*H31 -> 0 | J31: =G31+I31 -> 1.0520239e+08
B32: =B31+0.01 -> 11.24 | C32: Estación de operador SOS | D32: Un | E32: 1 | F32: 17478301 | G32: =E32*F32 -> 17478301 | I32: =E32*H32 -> 0 | J32: =G32+I32 -> 17478301
B33: =B32+0.01 -> 11.25 | C33: Central IP | D33: Un | E33: 1 | F33: 13624846 | G33: =E33*F33 -> 13624846 | H33: 1344491.8 | I33: =E33*H33 -> 1344491.8 | J33: =G33+I33 -> 14969337
B34: =B33+0.01 -> 11.26 | C34: Consola para central IP, incluyendo 4 diademas para operador | D34: Un | E34: 1 | F34: 1611415.5 | G34: =E34*F34 -> 1611415.5 | H34: 10890833 | I34: =E34*H34 -> 10890833 | J34: =G34+I34 -> 12502248
B35: =B34+0.01 -> 11.27 | C35: Teléfonos IP | D35: Un | E35: 20 | F35: 555937.74 | G35: =E35*F35 -> 11118755 | I35: =E35*H35 -> 0 | J35: =G35+I35 -> 11118755
B36: =B35+0.01 -> 11.28 | C36: Cable UTP Cat 6 | D36: ml | E36: 800 | F36: 7003.2987 | G36: =E36*F36 -> 5602639 | H36: 15780 | I36: =E36*H36 -> 12624000 | J36: =G36+I36 -> 18226639
B37: =B36+0.01 -> 11.29 | C37: Gateway GSM de 4 vías | D37: Un | E37: 1 | F37: 6261296.9 | G37: =E37*F37 -> 6261296.9 | H37: 956902.92 | I37: =E37*H37 -> 956902.92 | J37: =G37+I37 -> 7218199.8
B38: =B37+0.01 -> 11.3 | C38: Rack de 19" para Equipos computacionales de 42 U | D38: UN | E38: 3 | F38: 5618376.8 | G38: =E38*F38 -> 16855130 | H38: 426968.75 | I38: =E38*H38 -> 1280906.2 | J38: =G38+I38 -> 18136036
B39: =B38+0.01 -> 11.31 | C39: ODF para 48 fibras | D39: UN | E39: 3 | F39: 485000 | G39: =E39*F39 -> 1455000 | I39: =E39*H39 -> 0 | J39: =G39+I39 -> 1455000
B40: =B39+0.01 -> 11.32 | C40: Patch Panel | D40: UN | E40: 3 | F40: 893000 | G40: =E40*F40 -> 2679000 | I40: =E40*H40 -> 0 | J40: =G40+I40 -> 2679000
B41: =B40+0.01 -> 11.33 | C41: Patch Cord fibra óptica mono modo lc - lc | D41: Un | E41: 48 | F41: 31385 | G41: =E41*F41 -> 1506480 | H41: 31603.894 | I41: =E41*H41 -> 1516986.9 | J41: =G41+I41 -> 3023466.9
B42: =B41+0.01 -> 11.34 | C42: Tubería IMC ¾” | D42: ml | E42: 18 | F42: 76579.098 | G42: =E42*F42 -> 1378423.8 | I42: =E42*H42 -> 0 | J42: =G42+I42 -> 1378423.8
B43: =B42+0.01 -> 11.35 | C43: Cableado 3x10 Energía | D43: ml | E43: 20 | F43: 12759480 | G43: =E43*F43 -> 255189600 | H43: 5377967 | I43: =E43*H43 -> 107559340 | J43: =G43+I43 -> 362748940
B44: =B43+0.01 -> 11.36 | C44: Tablero de energía con interruptores monopolares | D44: Un | E44: 1 | F44: 8461488.3 | G44: =E44*F44 -> 8461488.3 | H44: 2043627.5 | I44: =E44*H44 -> 2043627.5 | J44: =G44+I44 -> 10505116
B45: =B44+0.01 -> 11.37 | C45: UPS de 30 KVA, bifásica | D45: Un | E45: 1 | F45: 70450000 | G45: =E45*F45 -> 70450000 | H45: 3760000 | I45: =E45*H45 -> 3760000 | J45: =G45+I45 -> 74210000
B46: =B45+0.01 -> 11.38 | C46: Aire acondicionado | D46: Un | E46: 1 | F46: 31845800 | G46: =E46*F46 -> 31845800 | H46: 5377967 | I46: =E46*H46 -> 5377967 | J46: =G46+I46 -> 37223767
B47: =B46+0.01 -> 11.39 | C47: Cableado Energía Aire acondicionado | D47: Gbl | E47: 1 | F47: 6250000 | G47: =E47*F47 -> 6250000 | H47: 2600000 | I47: =E47*H47 -> 2600000 | J47: =G47+I47 -> 8850000
B48: =B47+0.01 -> 11.4 | C48: Material de instalación, incluye canaletas etc. | D48: Gbl | E48: 1 | F48: 20370891 | G48: =E48*F48 -> 20370891 | H48: 5117001.1 | I48: =E48*H48 -> 5117001.1 | J48: =G48+I48 -> 25487892
B49: =B48+0.01 -> 11.41 | C49: Control de Accesos (Equipos que reciben la información desde los peajes y la integran al SCADA) | D49: Gbl | E49: 1 | F49: 75825701 | G49: =E49*F49 -> 75825701 | H49: 34626895 | I49: =E49*H49 -> 34626895 | J49: =G49+I49 -> 110452596
B50: =B49+0.01 -> 11.42 | C50: Integración de todos los subsistemas al SCADA y pruebas | D50: Gbl | E50: 1 | F50: 230000000 | G50: =E50*F50 -> 230000000 | I50: =E50*H50 -> 0 | J50: =G50+I50 -> 230000000
B51: =B50+0.01 -> 11.43 | C51: Caja de empalme tipo botella (mufla) para F.O de 48 hilos con cierre térmico para uso subterráneo. | D51: Un | E51: 1 | F51: 192904 | G51: =E51*F51 -> 192904 | H51: 170263 | I51: =E51*H51 -> 170263 | J51: =G51+I51 -> 363167
B52: =B51+0.01 -> 11.44 | C52: Cajas para la Red Troncal, de paso o derivación, de 80X80X80, dimensiones internas | D52: Un | E52: 2 | F52: 962106 | G52: =E52*F52 -> 1924212 | H52: 817672.2 | I52: =E52*H52 -> 1635344.4 | J52: =G52+I52 -> 3559556.4
B53: =B52+0.01 -> 11.45 | C53: Caja de reserva para micro cable de Fibra Óptica | D53: Un | E53: 1 | F53: 455761 | G53: =E53*F53 -> 455761 | H53: 97455 | I53: =E53*H53 -> 97455 | J53: =G53+I53 -> 553216
B54: =B53+0.01 -> 11.46 | C54: Canalización y ducto Conduit de 1 y 1/2", entre la troncal de FO y el CCO, en longitud promedio de 30 m | D54: Un | E54: 1 | F54: 263833 | G54: =E54*F54 -> 263833 | H54: 2265263.4 | I54: =E54*H54 -> 2265263.4 | J54: =G54+I54 -> 2529096.4
B55: =B54+0.01 -> 11.47 | C55: Fusiones | D55: Un | E55: 96 | F55: 7441 | G55: =E55*F55 -> 714336 | H55: 45514 | I55: =E55*H55 -> 4369344 | J55: =G55+I55 -> 5083680
B56: =B55+0.01 -> 11.48 | C56: Material de montaje | D56: Gbl | E56: 1 | F56: 2977793.9 | G56: =E56*F56 -> 2977793.9 | I56: =E56*H56 -> 0
B57: =B56+0.01 -> 11.49 | C57: Capacitación | D57: Gbl | E57: 1 | F57: 9000000 | G57: =E57*F57 -> 9000000 | I57: =E57*H57 -> 0 | J57: =G57+I57 -> 9000000
H59: TOTAL COSTOS DIRECTOS | J59: =SUM(J9:J57) -> 3.934077e+09
F60: ADMINISTRACION (A) | I60: 0.22 | J60: =J59*I60 -> 8.6549694e+08
F61: IMPREVISTOS (I) | I61: 0.04 | J61: =J59*I61 -> 1.5736308e+08
F62: UTILIDAD (U) | I62: 0.04 | J62: =J59*I62 -> 1.5736308e+08
F63: SUBTOTAL COSTOS DIRECTOS + AIU
F64: IVA SOBRE LA UTILIDAD 19% | I64: 0.19 | J64: =J62*I64 -> 29898985
H66: TOTAL COSTO DIRECTO+AIU + IVA | J66: =SUM(J59:J64) -> 5.1441991e+09

Sheet Control de accesos en Peaje
B2: PROYECTO TRONCAL MAGDALENA 1
B3: TABLA DE CANTIDADES | D3: PRESUPUESTO WUXY
B4: CONTROL DE ACCESOS EN PEAJE
B5: UNIDADES FUNCIONALES TOTAL 0 - 13
B7: ítem | C7: ITS | D7: Unidad | E7: Cantidad | F7: SUMINISTRO | H7: INSTALACIÓN PUESTA EN FUNCIONAMIENTO Y PRUEBAS | J7: COSTO TOTAL
B8: 12 | C8: CONTROL DE ACCESOS | F8: Costo unitario | G8: Total suministro | H8: Costo unitario | I8: Total Instalación | J8: TOTAL
E9: TOTAL | F9: Col $ | G9: Col $ | H9: Col $ | I9: Col $ | J9: Col $
B10: =B8+0.01 -> 12.01 | C10: Electroimán Rectangular 600 LBS, Incluye Soporte L/Z, Antiremanente | D10: Un | E10: 8 | F10: 220981.39 | G10: =E10*F10 -> 1767851.1 | H10: 80216.244 | I10: =E10*H10 -> 641729.95 | J10: =G10+I10 -> 2409581.1
B11: =B10+0.01 -> 12.02 | C11: Electroimán Rectangular 400 LBS, Incluye Soporte L/Z, Antiremanente | D11: Un | E11: 0 | F11: 210421.59 | G11: =E11*F11 -> 0 | H11: 76383.037 | I11: =E11*H11 -> 0 | J11: =G11+I11 -> 0
B12: =B11+0.01 -> 12.03 | C12: Lectora de tarjetas tipo proximidad. iCLASS Contactless Smart Card Reader, Mini-Mullion. multiCLASS | D12: Un | E12: 8 | F12: 673081.57 | G12: =E12*F12 -> 5384652.6 | H12: 244328.61 | I12: =E12*H12 -> 1954628.9 | J12: =G12+I12 -> 7339281.5
B13: =B12+0.01 -> 12.04 | C13: Pulsador de salida sin contacto. Botón Verde | D13: Un | E13: 8 | F13: 166563.23 | G13: =E13*F13 -> 1332505.8 | H13: 60462.451 | I13: =E13*H13 -> 483699.61 | J13: =G13+I13 -> 1816205.4
B14: =B13+0.01 -> 12.05 | C14: Contacto Magnético Liviano Puerta/Ventana | D14: Un | E14: 0 | F14: 13076.939 | G14: =E14*F14 -> 0 | H14: 4746.9289 | I14: =E14*H14 -> 0 | J14: =G14+I14 -> 0
B15: =B14+0.01 -> 12.06 | C15: Controladora de accesos para 4 puertas. 4 Door Expansion Kit. Includes: • four door controller, IP ready, •accessory kit, •Metal cabinet w/ lock transformer, wire-in, 110 VAC/ 16.5 VAC (75 VA), UL approved | D15: Un | E15: 2 | F15: 8799832.3 | G15: =E15*F15 -> 17599665 | H15: 3194339.1 | I15: =E15*H15 -> 6388678.3 | J15: =G15+I15 -> 23988343
B16: =B15+0.01 -> 12.07 | C16: Controladora de accesos para 2 puertas, Two door controller, 128KB memory, accessory kit, metal cabinet w/ lock | D16: Un | E16: 0 | F16: 4329517.5 | G16: =E16*F16 -> 0 | H16: 1571614.9 | I16: =E16*H16 -> 0 | J16: =G16+I16 -> 0
B17: =B16+0.01 -> 12.08 | C17: Tarjeta expansora para señales de puertas no controladas | D17: Un | E17: 0 | F17: 3167939.6 | G17: =E17*F17 -> 0 | H17: 1149962.1 | I17: =E17*H17 -> 0 | J17: =G17+I17 -> 0
B18: =B17+0.01 -> 12.09 | C18: EntraPass Corporate Edition license only, includes: one server workstation and 2 additional workstations license, one gateway license and one EntraPass WEB license. One year of updates included. Email delivery. | D18: Un | E18: 2 | F18: 3379135.6 | G18: =E18*F18 -> 6758271.2 | H18: 1226626.2 | I18: =E18*H18 -> 2453252.5 | J18: =G18+I18 -> 9211523.7
B19: =B18+0.01 -> 12.1 | C19: Tarjetas de control de accesos (1326) | D19: Un | E19: 40 | F19: 12742.157 | G19: =E19*F19 -> 509686.29 | H19: 4625.4031 | I19: =E19*H19 -> 185016.12 | J19: =G19+I19 -> 694702.41
B20: =B19+0.01 -> 12.11 | C20: Canastilla 10X5 (Charofil) | D20: ml | E20: 24 | F20: 168834.88 | G20: =E20*F20 -> 4052037.1 | H20: 96578.659 | I20: =E20*H20 -> 2317887.8 | J20: =G20+I20 -> 6369924.9
B21: =B20+0.01 -> 12.12 | C21: Tubería EMT 1" (Colmena) | D21: ml | E21: 12 | F21: 102056.72 | G21: =E21*F21 -> 1224680.7 | H21: 32836.744 | I21: =E21*H21 -> 394040.93 | J21: =G21+I21 -> 1618721.6
B22: =B21+0.01 -> 12.13 | C22: Tubería EMT 3/4 (Colmena) | D22: ml | E22: 60 | F22: 82042.126 | G22: =E22*F22 -> 4922527.6 | H22: 32836.744 | I22: =E22*H22 -> 1970204.6 | J22: =G22+I22 -> 6892732.2
... B24: =B23+0.01 -> 12.15 | C24: Cable Duplex 2X18 (Centelsa) | D24: ml | E24: 440 | F24: 2427.8902 | G24: =E24*F24 -> 1068271.7 | H24: 8428.6829 | I24: =E24*H24 -> 3708620.5 | J24: =G24+I24 -> 4776892.2
B25: =B24+0.01 -> 12.16 | C25: Programación, pruebas, capacitación y documentación del sistema | D25: Gbl | E25: 1 | G25: =E25*F25 -> 0 | H25: 7082926.8 | I25: =E25*H25 -> 7082926.8 | J25: =G25+I25 -> 7082926.8
H27: TOTAL COSTOS DIRECTOS | J27: =SUM(J10:J25) -> 78424521
F28: ADMINISTRACION (A) | I28: 0.22 | J28: =J27*I28 -> 17253395
F29: IMPREVISTOS (I) | I29: 0.04 | J29: =J27*I29 -> 3136980.8
F30: UTILIDAD (U) | I30: 0.04 | J30: =J27*I30 -> 3136980.8
F31: SUBTOTAL COSTOS DIRECTOS + AIU
F32: IVA SOBRE LA UTILIDAD 19% | I32: 0.19 | J32: =J30*I32 -> 596026.36
H34: TOTAL COSTO DIRECTO+AIU + IVA | J34: =SUM(J27:J32) -> 1.025479e+08

Sheet Paso elevado FO
B2: PROYECTO TRONCAL MAGDALENA 1
B3: TABLA DE CANTIDADES | D3: PRESUPUESTO WUXY
B4: PASO ELEVADO FIBRA OPTICA
B5: UNIDADES FUNCIONALES TOTAL 0 - 13
B7: ítem | C7: ITS | D7: Unidad | E7: Cantidad | F7: SUMINISTRO | H7: INSTALACIÓN PUESTA EN FUNCIONAMIENTO Y PRUEBAS | J7: COSTO TOTAL
B8: 13 | C8: PASOS ELEVADOS FIBRA OPTICA | F8: Costo unitario | G8: Total suministro | H8: Costo unitario | I8: Total Instalación | J8: TOTAL
E9: TOTAL | F9: Col $ | G9: Col $ | H9: Col $ | I9: Col $ | J9: Col $
B10: =B8+0.01 -> 13.01 | C10: Suministro Fibra Óptica aérea 48 Hilos Spam 300, incluye reserva | D10: ml | E10: 410 | F10: 26444.18 | G10: =E10*F10 -> 10842114 | I10: =E10*H10 -> 0 | J10: =G10+I10 -> 10842114
B11: =B10+0.01 -> 13.02 | C11: KIT HERRAJERIA PARA FIBRA 48 HILOS SPAM 600, COMPUESTO POR: *Hilos de blindaje largo 1.80mtrs * Herraje de retención largo 1.40mtrs *Brazo extensor *Tuerca de ojo *Clevis * Atenuador de efecto eólico tipo Corona Coil *Cinta bandit-Hebillas | D11: Gbl | E11: 12 | F11: 849915 | G11: =E11*F11 -> 10198980 | I11: =E11*H11 -> 0 | J11: =G11+I11 -> 10198980
B12: =B11+0.01 -> 13.03 | C12: Adosamiento Tubería Bajantes postes 6mt cada una | D12: Un | E12: 12 | F12: 472175 | G12: =E12*F12 -> 5666100 | I12: =E12*H12 -> 0 | J12: =G12+I12 -> 5666100
B13: =B12+0.01 -> 13.04 | C13: Postes concreto de 14 m | D13: Un | E13: 8 | F13: 2999598 | G13: =E13*F13 -> 23996784 | H13: 680994.05 | I13: =E13*H13 -> 5447952.4 | J13: =G13+I13 -> 29444736
B14: =B13+0.01 -> 13.05 | C14: Cajas para la Red Troncal, de paso o derivación, de 80X80X80, dimensiones internas | D14: Un | E14: 6 | F14: 962106 | G14: =E14*F14 -> 5772636 | H14: 817672.2 | I14: =E14*H14 -> 4906033.2 | J14: =G14+I14 -> 10678669
B15: =B14+0.01 -> 13.06 | C15: Fusiones | D15: Un | E15: 288 | F15: 7441 | G15: =E15*F15 -> 2143008 | H15: 45514 | I15: =E15*H15 -> 13108032 | J15: =G15+I15 -> 15251040
H17: TOTAL COSTOS DIRECTOS | J17: =SUM(J10:J15) -> 82081639
F18: ADMINISTRACION (A) | I18: 0.22 | J18: =J17*I18 -> 18057961
F19: IMPREVISTOS (I) | I19: 0.04 | J19: =J17*I19 -> 3283265.6
F20: UTILIDAD (U) | I20: 0.04 | J20: =J17*I20 -> 3283265.6
F21: SUBTOTAL COSTOS DIRECTOS + AIU
F22: IVA SOBRE LA UTILIDAD 19% | I22: 0.19 | J22: =J20*I22 -> 623820.46
H24: TOTAL COSTO DIRECTO+AIU + IVA | J24: =SUM(J17:J22) -> 1.0732995e+08

Sheet Basculas Dinamicas en peaje
B2: PROYECTO TRONCAL MAGDALENA 1
B3: TABLA DE CANTIDADES | D3: PRESUPUESTO WUXY
B4: UNIDADES FUNCIONALES TOTAL 0 - 13
B6: ítem | C6: ITS | D6: Unidad | E6: Cantidad | F6: SUMINISTRO | H6: INSTALACIÓN PUESTA EN FUNCIONAMIENTO Y PRUEBAS | J6: COSTO TOTAL
B7: 14 | C7: BÁSCULAS DINAMICAS EN ZONA DE PEAJE | F7: Costo unitario | G7: Total suministro | H7: Costo unitario | I7: Total Instalación | J7: TOTAL
E8: TOTAL | F8: Col $ | G8: Col $ | H8: Col $ | I8: Col $ | J8: Col $
C9: BÁSCULA DINÁMICA
B10: =B7+0.01 -> 14.01 | C10: Plataforma fija de preselección (2X) | D10: Un | E10: 16 | F10: 120311790 | G10: =E10*F10 -> 1924988640 | H10: 0 | I10: =E10*H10 -> 0 | J10: =G10+I10 -> 1924988640
B11: =B10+0.01 -> 14.02 | C11: Gabinete de Bifurcación | D11: Un | E11: 0 | F11: 0 | G11: =E11*F11 -> 0 | H11: 0 | I11: =E11*H11 -> 0 | J11: =G11+I11 -> 0
B12: =B11+0.01 -> 14.03 | C12: Gabinete de Control de Selección WIM | D12: Un | E12: 16 | F12: 39686505 | G12: =E12*F12 -> 634984080 | H12: 0 | I12: =E12*H12 -> 0 | J12: =G12+I12 -> 634984080
B13: =B12+0.01 -> 14.04 | C13: Cortina Óptica infrarroja | D13: Un | E13: 0 | F13: 12892065 | G13: =E13*F13 -> 0 | H13: 0 | I13: =E13*H13 -> 0 | J13: =G13+I13 -> 0
B14: =B13+0.01 -> 14.05 | C14: Semáforo Cruz / Flecha, tipo led, hacia báscula estática | D14: Un | E14: 0 | F14: 4081567.5 | G14: =E14*F14 -> 0 | H14: 0 | I14: =E14*H14 -> 0 | J14: =G14+I14 -> 0
B15: =B14+0.01 -> 14.06 | C15: Semáforo Cruz / Flecha, tipo led, de retorno a vía principal | D15: Un | E15: 0 | F15: 4081567.5 | G15: =E15*F15 -> 0 | H15: 0 | I15: =E15*H15 -> 0 | J15: =G15+I15 -> 0
B16: =B15+0.01 -> 14.07 | C16: Poste tipo T o Pórtico | D16: Un | E16: 0 | F16: 0 | G16: =E16*F16 -> 0 | H16: 11176794 | I16: =E16*H16 -> 0 | J16: =G16+I16 -> 0
B17: =B16+0.01 -> 14.08 | C17: Cámara de reconocimiento de placas para evadidos, 1 por carril (en vía Principal) | D17: Un | E17: 0 | F17: 32391472 | G17: =E17*F17 -> 0 | H17: 0 | I17: =E17*H17 -> 0 | J17: =G17+I17 -> 0
B18: =B17+0.01 -> 14.09 | C18: Cámara de imágenes para evadidos, 1 por carril (en vía principal) | D18: Un | E18: 0 | F18: 0 | G18: =E18*F18 -> 0 | H18: 0 | I18: =E18*H18 -> 0 | J18: =G18+I18 -> 0
B19: =B18+0.01 -> 14.1 | C19: Pareja de postes de 6 m o pórtico para cámaras de evadidos | D19: Un | E19: 0 | F19: 0 | G19: =E19*F19 -> 0 | H19: 12932237 | I19: =E19*H19 -> 0 | J19: =G19+I19 -> 0
B20: =B19+0.01 -> 14.11 | C20: Cámara de Reconocimiento de Placas en Zona de Pesaje Dinámico | D20: Un | E20: 0 | F20: 21657990 | G20: =E20*F20 -> 0 | H20: 0 | I20: =E20*H20 -> 0 | J20: =G20+I20 -> 0
B21: =B20+0.01 -> 14.12 | C21: Cámara de evidencia de fugados | D21: Un | E21: 0 | F21: 35619795 | G21: =E21*F21 -> 0 | H21: 0 | I21: =E21*H21 -> 0 | J21: =G21+I21 -> 0
B22: =B21+0.01 -> 14.13 | C22: Poste multifuncional | D22: Un | E22: 0 | F22: 0 | G22: =E22*F22 -> 0 | H22: 11176794 | I22: =E22*H22 -> 0 | J22: =G22+I22 -> 0
... B26: =B25+0.01 -> 14.17 | C26: Licencia Software de Pesaje – Integración con el carril de peaje | D26: Un | E26: 4 | F26: 19500000 | G26: =E26*F26 -> 78000000 | H26: 0 | I26: =E26*H26 -> 0 | J26: =G26+I26 -> 78000000
B27: =B26+0.01 -> 14.18 | C27: Material de montaje | D27: Un | E27: 2 | F27: 20898135 | G27: =E27*F27 -> 41796270 | I27: =E27*H27 -> 0 | J27: =G27+I27 -> 41796270
B28: =B27+0.01 -> 14.19 | C28: Servicio de instalación General, pruebas y entrega a la interventoría | D28: Un | E28: 2 | F28: 130000000 | G28: =E28*F28 -> 260000000 | H28: 3981600 | I28: =E28*H28 -> 7963200 | J28: =G28+I28 -> 267963200
B29: =B28+0.01 -> 14.2 | C29: Capacitación | D29: Glb | E29: 2 | F29: 9000000 | G29: =E29*F29 -> 18000000 | I29: =E29*H29 -> 0 | J29: =G29+I29 -> 18000000
H31: TOTAL COSTOS DIRECTOS | J31: =SUM(J9:J29) -> 3182719610
F32: ADMINISTRACION (A) | I32: 0.22 | J32: =J31*I32 -> 7.0019831e+08
F33: IMPREVISTOS (I) | I33: 0.04 | J33: =J31*I33 -> 1.2730878e+08
F34: UTILIDAD (U) | I34: 0.04 | J34: =J31*I34 -> 1.2730878e+08
F35: SUBTOTAL COSTOS DIRECTOS + AIU
F36: IVA SOBRE LA UTILIDAD 19% | I36: 0.19 | J36: =J34*I36 -> 24188669
H38: TOTAL COSTO DIRECTO+AIU + IVA | J38: =SUM(J31:J36) -> 4.1617242e+09
